Workbook
Name tab: '[1]tab 0D4'!$A$22:$H$27

Sheet PIB_Annuel (2016)
A1: REPUBLIQUE DU CAMEROUN
A2: Paix – Travail – Patrie
A3: ---------------
A4: INSTITUT NATIONAL DE LA STATISTIQUE
A7: Les Comptes Nationaux du Cameroun, troisième édition, selon le SCN 2008
A9: Optique production
A11: ="Tableau "&B11&": " -> Tableau 1: | B11: 1
A12: PIB courant, optique production
A13: Libellé | C13: =IF(ISNUMBER(B13),B13+1,1993) -> 1993 | D13: =IF(ISNUMBER(C13),C13+1,1993) -> 1994 | E13: =IF(ISNUMBER(D13),D13+1,1993) -> 1995 | F13: =IF(ISNUMBER(E13),E13+1,1993) -> 1996 | G13: =IF(ISNUMBER(F13),F13+1,1993) -> 1997 | H13: =IF(ISNUMBER(G13),G13+1,1993) -> 1998 | I13: =IF(ISNUMBER(H13),H13+1,1993) -> 1999 | J13: =IF(ISNUMBER(I13),I13+1,1993) -> 2000 | ... Y13: =IF(ISNUMBER(X13),X13+1,1993) -> 2015 | Z13: 2016 | AA13: 2017 | AB13: 2018 | AC13: 2019 | AD13: 2020 | AE13: 2021 | AF13: 2022 | AG13: 2023
A14: 1.Production | C14: 6451.0058 | D14: 7196.2655 | E14: 8053.9961 | F14: 8718.6443 | G14: 9411.0046 | H14: 10021.799 | I14: 10750.002 | J14: 11149.936 | K14: 12241.755 | L14: 12849.735 | M14: 13801.332 | N14: 14591.658 | O14: 15207.882 | P14: 16270.577 | Q14: 17203.184 | R14: 18985.061 | S14: 19575.51 | T14: 20668.467 | U14: 21794.216 | V14: 23299.339 | W14: 24785.014 | X14: 26524.661 | Y14: 27724.473 | Z14: 28744.934 | AA14: 29715.783 | AB14: 31667.666 | AC14: 33043.125 | AD14: 32915.833 | AE14: 35000.255 | AF14: 38576.808 | AG14: 41131.018
A15: 2.Consommation intermédiaire | C15: 2107.8862 | D15: 2523.2524 | E15: 2959.431 | F15: 3426.4008 | G15: 3574.0858 | H15: 3882.0357 | I15: 4192.6051 | J15: 4273.5991 | K15: 4922.1281 | L15: 4950.8597 | M15: 5299.8612 | N15: 5324.2508 | O15: 5655.3545 | P15: 6192.0018 | Q15: 6656.8954 | R15: 7464.5601 | S15: 7289.8447 | T15: 7908.9872 | U15: 8190.23 | V15: 8820.4878 | W15: 9162.1189 | X15: 9823.09 | Y15: 10231.279 | Z15: 10341.261 | AA15: 10574.777 | AB15: 11323.315 | AC15: 11738.906 | AD15: 11255.14 | AE15: 11938.478 | AF15: 12828.713 | AG15: 13328.025
A16: 3.Valeur Ajoutée(1-2) | C16: =+C14-C15 -> 4343.1196 | D16: =+D14-D15 -> 4673.0131 | E16: =+E14-E15 -> 5094.5651 | F16: =+F14-F15 -> 5292.2435 | G16: =+G14-G15 -> 5836.9189 | H16: =+H14-H15 -> 6139.7631 | I16: =+I14-I15 -> 6557.3969 | J16: =+J14-J15 -> 6876.3371 | ... Y16: =+Y14-Y15 -> 17493.194 | Z16: 18403.673 | AA16: 19141.006 | AB16: 20344.351 | AC16: 21304.219 | AD16: 21660.693 | AE16: 23061.777 | AF16: 25748.095 | AG16: 27802.993
A17: 4.Impôts sur les produits | C17: 238.96475 | D17: 269.66686 | E17: 328.56895 | F17: 382.68325 | G17: 460.55757 | H17: 525.59764 | I17: 561.06103 | J17: 628.13184 | K17: 702.68004 | L17: 715.13584 | M17: 759.67386 | N17: 660.372 | O17: 734.20484 | P17: 845.61215 | Q17: 906.57885 | R17: 840.45357 | S17: 851.0274 | T17: 851.07468 | U17: 830.78878 | V17: 917.00743 | W17: 1035.6585 | X17: 1264.5526 | Y17: 1549.8722 | Z17: 1634.893 | AA17: 1819.859 | AB17: 1858.978 | AC17: 1939.443 | AD17: 1807.814 | AE17: 1898.719 | AF17: 1913.925 | AG17: 2088.41
A18: PIB(3+4) | C18: =+C16+C17 -> 4582.0844 | D18: =+D16+D17 -> 4942.68 | E18: =+E16+E17 -> 5423.1341 | F18: =+F16+F17 -> 5674.9268 | G18: =+G16+G17 -> 6297.4764 | H18: =+H16+H17 -> 6665.3607 | I18: =+I16+I17 -> 7118.4579 | J18: =+J16+J17 -> 7504.4689 | ... Y18: =+Y16+Y17 -> 19043.067 | Z18: 20038.566 | AA18: 20960.865 | AB18: 22203.329 | AC18: 23243.662 | AD18: 23468.507 | AE18: 24960.496 | AF18: 27662.02 | AG18: 29891.403
A21: ="Tableau "&B21&": " -> Tableau 2: | B21: 2
A22: PIB aux prix de l'année précédente, optique production
A23: Libellé | C23: =IF(ISNUMBER(B23),B23+1,1993) -> 1993 | D23: =IF(ISNUMBER(C23),C23+1,1993) -> 1994 | E23: =IF(ISNUMBER(D23),D23+1,1993) -> 1995 | F23: =IF(ISNUMBER(E23),E23+1,1993) -> 1996 | G23: =IF(ISNUMBER(F23),F23+1,1993) -> 1997 | H23: =IF(ISNUMBER(G23),G23+1,1993) -> 1998 | I23: =IF(ISNUMBER(H23),H23+1,1993) -> 1999 | J23: =IF(ISNUMBER(I23),I23+1,1993) -> 2000 | ... Y23: =IF(ISNUMBER(X23),X23+1,1993) -> 2015 | Z23: 2016 | AA23: 2017 | AB23: 2018 | AC23: 2019 | AD23: 2020 | AE23: 2021 | AF23: 2022 | AG23: 2023
A24: 1.Production | D24: 6721.9212 | E24: 7550.3253 | F24: 8379.7953 | G24: 9363.6865 | H24: 9916.187 | I24: 10575.277 | J24: 11225.442 | K24: 11937.997 | L24: 12502.47 | M24: 13453.913 | N24: 14534.33 | O24: 14865.104 | P24: 15780.845 | Q24: 16962.232 | R24: 17938.633 | S24: 19367.8 | T24: 20329.016 | U24: 20995.399 | V24: 22737.896 | W24: 24391.358 | X24: 26191.539 | Y24: 27729.342 | Z24: 28730.147 | AA24: 29493.134 | AB24: 30770.424 | AC24: 33043.125 | AD24: 32656.279 | AE24: 33974.43 | AF24: 36023.615 | AG24: 39711.327
A25: 2.Consommation intermédiaire | D25: 2297.4008 | E25: 2769.7738 | F25: 3109.0922 | G25: 3894.8308 | H25: 3807.9544 | I25: 4190.3325 | J25: 4431.3181 | K25: 4761.6792 | L25: 4794.8968 | M25: 5138.8387 | N25: 5302.0691 | O25: 5427.4473 | P25: 5921.7411 | Q25: 6443.8404 | R25: 6960.6849 | S25: 7527.4384 | T25: 7677.7782 | U25: 7784.1612 | V25: 8576.5841 | W25: 9259.9149 | X25: 9822.78 | Y25: 10280.1 | Z25: 10499.395 | AA25: 10453.044 | AB25: 10807.988 | AC25: 11998.56 | AD25: 11203.557 | AE25: 11612.436 | AF25: 12113.462 | AG25: 13154.764
A26: 3.Valeur Ajoutée(1-2) | D26: =+D24-D25 -> 4424.5205 | E26: =+E24-E25 -> 4780.5515 | F26: =+F24-F25 -> 5270.7032 | G26: =+G24-G25 -> 5468.8557 | H26: =+H24-H25 -> 6108.2326 | I26: =+I24-I25 -> 6384.9448 | J26: =+J24-J25 -> 6794.1236 | K26: =+K24-K25 -> 7176.3181 | ... Y26: =+Y24-Y25 -> 17449.242 | Z26: 18230.751 | AA26: 19040.09 | AB26: 19962.436 | AC26: 21044.565 | AD26: 21452.722 | AE26: 22361.994 | AF26: 23910.153 | AG26: 26556.563
A27: 4.Impôts sur les produits | D27: 243.5609 | E27: 305.16968 | F27: 381.01991 | G27: 462.99284 | H27: 486.8333 | I27: 581.11063 | J27: 597.1434 | K27: 652.66362 | L27: 673.89504 | M27: 768.67291 | N27: 681.68871 | O27: 711.33962 | P27: 819.51058 | Q27: 878.55032 | R27: 801.05998 | S27: 839.41268 | T27: 866.29018 | U27: 859.24613 | V27: 941.21249 | W27: 1033.5193 | X27: 1242.6332 | Y27: 1535.0131 | Z27: 1676.0695 | AA27: 1708.077 | AB27: 1827.539 | AC27: 1930.338 | AD27: 1851.363 | AE27: 1890.093 | AF27: 1983.094 | AG27: 2003.943
A28: PIB(3+4) | D28: =+D26+D27 -> 4668.0814 | E28: =+E26+E27 -> 5085.7212 | F28: =+F26+F27 -> 5651.7231 | G28: =+G26+G27 -> 5931.8485 | H28: =+H26+H27 -> 6595.0659 | I28: =+I26+I27 -> 6966.0554 | J28: =+J26+J27 -> 7391.267 | K28: =+K26+K27 -> 7828.9817 | ... Y28: =+Y26+Y27 -> 18984.255 | Z28: 19906.821 | AA28: 20748.167 | AB28: 21789.975 | AC28: 22974.903 | AD28: 23304.085 | AE28: 24252.087 | AF28: 25893.247 | AG28: 28560.506
A31: ="Tableau "&C31&": " -> Tableau :
A32: PIB en volumes chaînés, optique production (base 100 = 2016)
A33: Libellé | C33: =C$13 -> 1993 | D33: =D$13 -> 1994 | E33: =E$13 -> 1995 | F33: =F$13 -> 1996 | G33: =G$13 -> 1997 | H33: =H$13 -> 1998 | I33: =I$13 -> 1999 | J33: =J$13 -> 2000 | ... Y33: =Y$13 -> 2015 | Z33: 2016 | AA33: 2017 | AB33: 2018 | AC33: 2019 | AD33: 2020 | AE33: 2021 | AF33: 2022 | AG33: 2023
A34: 1.Production | C34: 10869.691 | D34: 11326.173 | E34: 11883.426 | F34: 12364.133 | G34: 13278.884 | H34: 13991.694 | I34: 14764.42 | J34: 15417.405 | K34: 16507.084 | L34: 16858.638 | M34: 17651.309 | N34: 18588.782 | O34: 18937.135 | P34: 19650.598 | Q34: 20485.935 | R34: 21361.725 | S34: 21792.378 | T34: 22631.217 | U34: 22989.195 | V34: 23984.617 | W34: 25108.756 | X34: 26533.653 | Y34: 27738.743 | Z34: 28744.934 | AA34: 29493.134 | AB34: 30539.873 | AC34: 31866.347 | AD34: 31493.278 | AE34: 32506.125 | AF34: 33456.56 | AG34: 34440.496
A35: 2.Consommation intermédiaire | C35: 3437.7574 | D35: 3746.8373 | E35: 4112.9027 | F35: 4320.896 | G35: 4911.6142 | H35: 5233.0033 | I35: 5648.5889 | J35: 5970.2009 | K35: 6652.0468 | L35: 6480.0991 | M35: 6726.1418 | N35: 6728.9439 | O35: 6859.3666 | P35: 7182.4663 | Q35: 7474.5887 | R35: 7815.6939 | S35: 7881.53 | T35: 8300.9503 | U35: 8169.9381 | V35: 8555.3351 | W35: 8981.5525 | X35: 9629.1934 | Y35: 10077.183 | Z35: 10341.261 | AA35: 10453.044 | AB35: 10683.57 | AC35: 11320.665 | AD35: 10804.39 | AE35: 11147.377 | AF35: 11310.766 | AG35: 11598.237
A36: 3.Valeur Ajoutée(1-2) | C36: 7509.0622 | D36: 7649.8007 | E36: 7825.8428 | F36: 8096.4113 | G36: 8366.6038 | H36: 8755.5033 | I36: 9105.1404 | J36: 9433.8424 | K36: 9845.395 | L36: 10367.208 | M36: 10913.465 | N36: 11851.592 | O36: 12069.316 | P36: 12456.665 | Q36: 13000.257 | R36: 13532.358 | S36: 13908.077 | T36: 14321.927 | U36: 14829.004 | V36: 15436.516 | W36: 16132.273 | X36: 16902.456 | Y36: 17659.12 | Z36: 18403.673 | AA36: 19040.09 | AB36: 19857.189 | AC36: 20540.636 | AD36: 20683.816 | AE36: 21353.489 | AF36: 22139.022 | AG36: 22834.169
A37: 4.Impôts sur les produits | C37: 370.88372 | D37: 378.01713 | E37: 427.78473 | F37: 496.07396 | G37: 600.17963 | H37: 634.42107 | I37: 701.42786 | J37: 746.53734 | K37: 775.69346 | L37: 743.91751 | M37: 799.60925 | N37: 717.52449 | O37: 772.90314 | P37: 862.70516 | Q37: 896.30914 | R37: 791.98559 | S37: 791.00473 | T37: 805.19104 | U37: 812.92194 | V37: 920.9709 | W37: 1037.9864 | X37: 1245.4263 | Y37: 1511.7961 | Z37: 1634.893 | AA37: 1708.077 | AB37: 1715.2853 | AC37: 1781.1294 | AD37: 1700.2392 | AE37: 1777.6222 | AF37: 1856.6159 | AG37: 1943.9384
A38: PIB | C38: 7873.4899 | D38: 8021.2603 | E38: 8253.3956 | F38: 8601.2822 | G38: 8990.6893 | H38: 9415.5474 | I38: 9840.3114 | J38: 10217.433 | K38: 10659.262 | L38: 11136.48 | M38: 11743.769 | N38: 12571.571 | O38: 12851.7 | P38: 13341.296 | Q38: 13918.653 | R38: 14315.011 | S38: 14684.231 | T38: 15109.931 | U38: 15620.527 | V38: 16343.129 | W38: 17159.555 | X38: 18141.05 | Y38: 19169.095 | Z38: 20038.566 | AA38: 20748.167 | AB38: 21568.864 | AC38: 22318.39 | AD38: 22376.408 | AE38: 23123.524 | AF38: 23987.629 | AG38: 24766.768
A41: ="Tableau "&C41&": " -> Tableau :
A42: Tableau 3: Indice de volume du PIB (variation en pourcentage)
A43: Libellé | C43: =C$13 -> 1993 | D43: =D$13 -> 1994 | E43: =E$13 -> 1995 | F43: =F$13 -> 1996 | G43: =G$13 -> 1997 | H43: =H$13 -> 1998 | I43: =I$13 -> 1999 | J43: =J$13 -> 2000 | ... Y43: =Y$13 -> 2015 | Z43: 2016 | AA43: 2017 | AB43: 2018 | AC43: 2019 | AD43: 2020 | AE43: 2021 | AF43: 2022 | AG43: 2023
A44: 1.Production | C44: =IFERROR(100*(C34/B34-1),"") | D44: =IFERROR(100*(D34/C34-1),"") -> 4.1995839 | E44: =IFERROR(100*(E34/D34-1),"") -> 4.9200492 | F44: =IFERROR(100*(F34/E34-1),"") -> 4.0451868 | G44: =IFERROR(100*(G34/F34-1),"") -> 7.3984226 | H44: =IFERROR(100*(H34/G34-1),"") -> 5.3679956 | I44: =IFERROR(100*(I34/H34-1),"") -> 5.5227462 | J44: =IFERROR(100*(J34/I34-1),"") -> 4.4226944 | ... Y44: =IFERROR(100*(Y34/X34-1),"") -> 4.5417422 | Z44: 3.6273846 | AA44: 2.6028934 | AB44: 3.5490938 | AC44: 4.3434177 | AD44: -1.1707307 | AE44: 3.2160723 | AF44: 2.9238644 | AG44: 2.9409354
A45: 2.Consommation intermédiaire | C45: =IFERROR(100*(C35/B35-1),"") | D45: =IFERROR(100*(D35/C35-1),"") -> 8.9907398 | E45: =IFERROR(100*(E35/D35-1),"") -> 9.7699853 | F45: =IFERROR(100*(F35/E35-1),"") -> 5.0570918 | G45: =IFERROR(100*(G35/F35-1),"") -> 13.671197 | H45: =IFERROR(100*(H35/G35-1),"") -> 6.5434521 | I45: =IFERROR(100*(I35/H35-1),"") -> 7.9416272 | J45: =IFERROR(100*(J35/I35-1),"") -> 5.6936688 | ... Y45: =IFERROR(100*(Y35/X35-1),"") -> 4.6524103 | Z45: 2.6205542 | AA45: 1.0809417 | AB45: 2.2053515 | AC45: 5.9633155 | AD45: -4.5604676 | AE45: 3.174514 | AF45: 1.4657145 | AG45: 2.5415722
A46: 3.Valeur Ajoutée(1-2) | C46: =IFERROR(100*(C36/B36-1),"") | D46: =IFERROR(100*(D36/C36-1),"") -> 1.8742482 | E46: =IFERROR(100*(E36/D36-1),"") -> 2.301265 | F46: =IFERROR(100*(F36/E36-1),"") -> 3.4573716 | G46: =IFERROR(100*(G36/F36-1),"") -> 3.3371887 | H46: =IFERROR(100*(H36/G36-1),"") -> 4.6482352 | I46: =IFERROR(100*(I36/H36-1),"") -> 3.9933416 | J46: =IFERROR(100*(J36/I36-1),"") -> 3.610071 | ... Y46: =IFERROR(100*(Y36/X36-1),"") -> 4.4766524 | Z46: 4.2162514 | AA46: 3.4580977 | AB46: 4.2914672 | AC46: 3.4418105 | AD46: 0.69705911 | AE46: 3.2376665 | AF46: 3.6787104 | AG46: 3.1399138
A47: 4.Impôts sur les produits | C47: =IFERROR(100*(C37/B37-1),"") | D47: =IFERROR(100*(D37/C37-1),"") -> 1.9233558 | E47: =IFERROR(100*(E37/D37-1),"") -> 13.165434 | F47: =IFERROR(100*(F37/E37-1),"") -> 15.963458 | G47: =IFERROR(100*(G37/F37-1),"") -> 20.985917 | H47: =IFERROR(100*(H37/G37-1),"") -> 5.7051984 | I47: =IFERROR(100*(I37/H37-1),"") -> 10.561879 | J47: =IFERROR(100*(J37/I37-1),"") -> 6.431094 | ... Y47: =IFERROR(100*(Y37/X37-1),"") -> 21.387841 | Z47: 8.14243 | AA47: 4.4763786 | AB47: 0.42201072 | AC47: 3.8386683 | AD47: -4.5415101 | AE47: 4.5512979 | AF47: 4.4437855 | AG47: 4.7033191
A48: PIB | C48: =IFERROR(100*(C38/B38-1),"") | D48: =IFERROR(100*(D38/C38-1),"") -> 1.8768092 | E48: =IFERROR(100*(E38/D38-1),"") -> 2.8940014 | F48: =IFERROR(100*(F38/E38-1),"") -> 4.2150721 | G48: =IFERROR(100*(G38/F38-1),"") -> 4.5273138 | H48: =IFERROR(100*(H38/G38-1),"") -> 4.7255348 | I48: =IFERROR(100*(I38/H38-1),"") -> 4.5113042 | J48: =IFERROR(100*(J38/I38-1),"") -> 3.8324178 | ... Y48: =IFERROR(100*(Y38/X38-1),"") -> 5.666953 | Z48: 4.5357942 | AA48: 3.5411765 | AB48: 3.9555142 | AC48: 3.4750375 | AD48: 0.25995474 | AE48: 3.3388575 | AF48: 3.7369089 | AG48: 3.2480853
A51: ="Tableau "&C51&": " -> Tableau :
A52: Variation du déflateur du PIB (en pourcentage)
A53: Libellé | C53: =C$13 -> 1993 | D53: =D$13 -> 1994 | E53: =E$13 -> 1995 | F53: =F$13 -> 1996 | G53: =G$13 -> 1997 | H53: =H$13 -> 1998 | I53: =I$13 -> 1999 | J53: =J$13 -> 2000 | ... Y53: =Y$13 -> 2015 | Z53: 2016 | AA53: 2017 | AB53: 2018 | AC53: 2019 | AD53: 2020 | AE53: 2021 | AF53: 2022 | AG53: 2023
A54: 1.Production | C54: =IFERROR(100*(C14/C24-1),"") | D54: =IFERROR(100*(D14/D24-1),"") -> 7.0566764 | E54: =IFERROR(100*(E14/E24-1),"") -> 6.6708501 | F54: =IFERROR(100*(F14/F24-1),"") -> 4.0436427 | G54: =IFERROR(100*(G14/G24-1),"") -> 0.50533695 | H54: =IFERROR(100*(H14/H24-1),"") -> 1.0650441 | I54: =IFERROR(100*(I14/I24-1),"") -> 1.6522002 | J54: =IFERROR(100*(J14/J24-1),"") -> -0.67262837 | ... Y54: =IFERROR(100*(Y14/Y24-1),"") -> -0.017559006 | Z54: 0.051470105 | AA54: 0.75491808 | AB54: 2.9159234 | AC54: 0 | AD54: 0.7948058 | AE54: 3.0194031 | AF54: 7.0875535 | AG54: 3.5750279
A55: 2.Consommation intermédiaire | C55: =IFERROR(100*(C15/C25-1),"") | D55: =IFERROR(100*(D15/D25-1),"") -> 9.8307447 | E55: =IFERROR(100*(E15/E25-1),"") -> 6.847392 | F55: =IFERROR(100*(F15/F25-1),"") -> 10.20583 | G55: =IFERROR(100*(G15/G25-1),"") -> -8.2351467 | H55: =IFERROR(100*(H15/H25-1),"") -> 1.9454352 | I55: =IFERROR(100*(I15/I25-1),"") -> 0.0542344 | J55: =IFERROR(100*(J15/J25-1),"") -> -3.5591886 | ... Y55: =IFERROR(100*(Y15/Y25-1),"") -> -0.47491239 | Z55: -1.5061266 | AA55: 1.1645699 | AB55: 4.7680197 | AC55: -2.164043 | AD55: 0.46041628 | AE55: 2.8076969 | AF55: 5.9045961 | AG55: 1.317097
A56: 3.Valeur Ajoutée(1-2) | C56: =IFERROR(100*(C16/C26-1),"") | D56: =IFERROR(100*(D16/D26-1),"") -> 5.6162612 | E56: =IFERROR(100*(E16/E26-1),"") -> 6.5685646 | F56: =IFERROR(100*(F16/F26-1),"") -> 0.40868029 | G56: =IFERROR(100*(G16/G26-1),"") -> 6.7301685 | H56: =IFERROR(100*(H16/H26-1),"") -> 0.51619646 | I56: =IFERROR(100*(I16/I26-1),"") -> 2.7009184 | J56: =IFERROR(100*(J16/J26-1),"") -> 1.2100672 | ... Y56: =IFERROR(100*(Y16/Y26-1),"") -> 0.25188758 | Z56: 0.94851612 | AA56: 0.5300185 | AB56: 1.9131683 | AC56: 1.2338293 | AD56: 0.96943875 | AE56: 3.1293408 | AF56: 7.6868684 | AG56: 4.6934914
A57: 4.Impôts sur les produits | C57: =IFERROR(100*(C17/C27-1),"") | D57: =IFERROR(100*(D17/D27-1),"") -> 10.718456 | E57: =IFERROR(100*(E17/E27-1),"") -> 7.6676261 | F57: =IFERROR(100*(F17/F27-1),"") -> 0.43654871 | G57: =IFERROR(100*(G17/G27-1),"") -> -0.52598362 | H57: =IFERROR(100*(H17/H27-1),"") -> 7.9625491 | I57: =IFERROR(100*(I17/I27-1),"") -> -3.4502195 | J57: =IFERROR(100*(J17/J27-1),"") -> 5.1894479 | ... Y57: =IFERROR(100*(Y17/Y27-1),"") -> 0.9680157 | Z57: -2.4567291 | AA57: 6.5443186 | AB57: 1.7202916 | AC57: 0.47167905 | AD57: -2.352267 | AE57: 0.45637966 | AF57: -3.4879335 | AG57: 4.21504
A58: PIB | C58: =IFERROR(100*(C18/C28-1),"") | D58: =IFERROR(100*(D18/D28-1),"") -> 5.8824723 | E58: =IFERROR(100*(E18/E28-1),"") -> 6.634514 | F58: =IFERROR(100*(F18/F28-1),"") -> 0.41055908 | G58: =IFERROR(100*(G18/G28-1),"") -> 6.1638111 | H58: =IFERROR(100*(H18/H28-1),"") -> 1.0658699 | I58: =IFERROR(100*(I18/I28-1),"") -> 2.1877885 | J58: =IFERROR(100*(J18/J28-1),"") -> 1.531563 | ... Y58: =IFERROR(100*(Y18/Y28-1),"") -> 0.30979167 | Z58: 0.66180898 | AA58: 1.0251412 | AB58: 1.8969916 | AC58: 1.1697938 | AD58: 0.70555012 | AE58: 2.9210228 | AF58: 6.8310205 | AG58: 4.6599209
A61: ="Tableau "&C61&": " -> Tableau :
A62: Ventilation du PIB courant par secteurs d’activités
A63: Libellé | C63: =C$13 -> 1993 | D63: =D$13 -> 1994 | E63: =E$13 -> 1995 | F63: =F$13 -> 1996 | G63: =G$13 -> 1997 | H63: =H$13 -> 1998 | I63: =I$13 -> 1999 | J63: =J$13 -> 2000 | ... Y63: =Y$13 -> 2015 | Z63: 2016 | AA63: 2017 | AB63: 2018 | AC63: 2019 | AD63: 2020 | AE63: 2021 | AF63: 2022 | AG63: 2023
A64: Secteur primaire | C64: =SUM(C65:C68) -> 835.62223 | D64: =SUM(D65:D68) -> 969.24739 | E64: =SUM(E65:E68) -> 1038.2511 | F64: =SUM(F65:F68) -> 1039.7782 | G64: =SUM(G65:G68) -> 1194.4983 | H64: =SUM(H65:H68) -> 1266.4852 | I64: =SUM(I65:I68) -> 1350.9972 | J64: =SUM(J65:J68) -> 1359.6403 | ... Y64: =SUM(Y65:Y68) -> 3277.2005 | Z64: 3445.163 | AA64: 3499.365 | AB64: 3663.283 | AC64: 3905.466 | AD64: 4106.253 | AE64: 4233.092 | AF64: 4577.102 | AG64: 5169.756
A65: Agriculture | C65: =C284 -> 469.12853 | D65: =D284 -> 524.37301 | E65: =E284 -> 550.0443 | F65: =F284 -> 574.22165 | G65: =G284 -> 653.98451 | H65: =H284 -> 683.10445 | I65: =I284 -> 735.15374 | J65: =J284 -> 740.62809 | ... Y65: =Y284 -> 1813.8875 | Z65: 1985.241 | AA65: 1962.65 | AB65: 2072.637 | AC65: 2192.535 | AD65: 2325.129 | AE65: 2377.514 | AF65: 2555.013 | AG65: 2944.921
A66: Elevage et chasse | C66: =C285 -> 95.640259 | D66: =D285 -> 113.20343 | E66: =E285 -> 131.07005 | F66: =F285 -> 134.12217 | G66: =G285 -> 148.01797 | H66: =H285 -> 159.70594 | I66: =I285 -> 180.02642 | J66: =J285 -> 180.42112 | ... Y66: =Y285 -> 432.4155 | Z66: 425.983 | AA66: 452.174 | AB66: 476.48 | AC66: 495.575 | AD66: 516.904 | AE66: 544.376 | AF66: 591.648 | AG66: 653.841
A67: Sylviculture et exploitation forestière | C67: =C286 -> 183.63515 | D67: =D286 -> 233.33762 | E67: =E286 -> 253.18173 | F67: =F286 -> 237.44929 | G67: =G286 -> 288.89504 | H67: =H286 -> 312.74577 | I67: =I286 -> 309.36096 | J67: =J286 -> 307.64286 | ... Y67: =Y286 -> 773.88869 | Z67: 747.062 | AA67: 777.444 | AB67: 792.206 | AC67: 885.735 | AD67: 913.817 | AE67: 940.928 | AF67: 1027.592 | AG67: 1125.235
A68: Pêche et pisciculture | C68: =C287 -> 87.218289 | D68: =D287 -> 98.333335 | E68: =E287 -> 103.95501 | F68: =F287 -> 93.985096 | G68: =G287 -> 103.60073 | H68: =H287 -> 110.92906 | I68: =I287 -> 126.45609 | J68: =J287 -> 130.94828 | ... Y68: =Y287 -> 257.00882 | Z68: 286.877 | AA68: 307.097 | AB68: 321.96 | AC68: 331.621 | AD68: 350.403 | AE68: 370.274 | AF68: 402.849 | AG68: 445.759
A69: Secteur secondaire | C69: =SUM(C70:C76)-C71 -> 1334.7191 | D69: =SUM(D70:D76)-D71 -> 1487.8824 | E69: =SUM(E70:E76)-E71 -> 1566.4418 | F69: =SUM(F70:F76)-F71 -> 1692.6394 | G69: =SUM(G70:G76)-G71 -> 1788.9546 | H69: =SUM(H70:H76)-H71 -> 1835.9214 | I69: =SUM(I70:I76)-I71 -> 1954.7679 | J69: =SUM(J70:J76)-J71 -> 2137.4754 | ... Y69: =SUM(Y70:Y76)-Y71 -> 4778.1888 | Z69: 4845.755 | AA69: 5016.299 | AB69: 5480.277 | AC69: 5538.239 | AD69: 5406.69 | AE69: 6113.461 | AF69: 7504.726 | AG69: 7632.341
A70: Industries extractives | C70: =SUM(C288:C289) -> 184.92523 | D70: =SUM(D288:D289) -> 273.26688 | E70: =SUM(E288:E289) -> 237.96161 | F70: =SUM(F288:F289) -> 354.33731 | G70: =SUM(G288:G289) -> 349.24559 | H70: =SUM(H288:H289) -> 324.94618 | I70: =SUM(I288:I289) -> 297.43082 | J70: =SUM(J288:J289) -> 471.40368 | ... Y70: =SUM(Y288:Y289) -> 741.73886 | Z70: 698.735 | AA70: 709.653 | AB70: 871.677 | AC70: 915.266 | AD70: 517.027 | AE70: 923.122 | AF70: 1739.986 | AG70: 1234.824
A71: dont extraction d'hydrocarbures | C71: =+C288 -> 171.08357 | D71: =+D288 -> 258.19292 | E71: =+E288 -> 220.46568 | F71: =+F288 -> 336.31848 | G71: =+G288 -> 326.01621 | H71: =+H288 -> 299.32119 | I71: =+I288 -> 268.4597 | J71: =+J288 -> 439.85556 | ... Y71: =+Y288 -> 656.9386 | Z71: 652.42 | AA71: 660.144 | AB71: 829.734 | AC71: 871.965 | AD71: 477.07 | AE71: 886.615 | AF71: 1698.038 | AG71: 1183.898
A72: Industries Agro-alimentaires | C72: =SUM(C290:C297) -> 408.12547 | D72: =SUM(D290:D297) -> 449.21004 | E72: =SUM(E290:E297) -> 467.95666 | F72: =SUM(F290:F297) -> 467.2655 | G72: =SUM(G290:G297) -> 505.59946 | H72: =SUM(H290:H297) -> 537.43395 | I72: =SUM(I290:I297) -> 604.0578 | J72: =SUM(J290:J297) -> 617.34116 | ... Y72: =SUM(Y290:Y297) -> 1334.864 | Z72: 1345.425 | AA72: 1386.663 | AB72: 1420.424 | AC72: 1392.774 | AD72: 1486.253 | AE72: 1659.502 | AF72: 1879.558 | AG72: 2108.554
A73: Autres Industries manufacturières | C73: =SUM(C298:C311) -> 366.73189 | D73: =SUM(D298:D311) -> 388.65235 | E73: =SUM(E298:E311) -> 436.03454 | F73: =SUM(F298:F311) -> 441.47016 | G73: =SUM(G298:G311) -> 485.52966 | H73: =SUM(H298:H311) -> 486.63859 | I73: =SUM(I298:I311) -> 494.51599 | J73: =SUM(J298:J311) -> 488.83777 | ... Y73: =SUM(Y298:Y311) -> 1397.8272 | Z73: 1428.22 | AA73: 1444.302 | AB73: 1618.105 | AC73: 1588.407 | AD73: 1607.128 | AE73: 1659.395 | AF73: 1817.181 | AG73: 1923.005
A74: Production et distribution d'électricité | C74: =+C312 -> 45.329326 | D74: =+D312 -> 40.040942 | E74: =+E312 -> 40.087722 | F74: =+F312 -> 42.095636 | G74: =+G312 -> 43.668525 | H74: =+H312 -> 45.903127 | I74: =+I312 -> 50.491346 | J74: =+J312 -> 52.905449 | ... Y74: =+Y312 -> 198.44371 | Z74: 208.603 | AA74: 214.264 | AB74: 202.014 | AC74: 202.036 | AD74: 211.023 | AE74: 210.487 | AF74: 209.187 | AG74: 247.626
A75: Production et distribution d'eau et assainissement | C75: =+C313 -> 36.36123 | D75: =+D313 -> 34.207197 | E75: =+E313 -> 37.571308 | F75: =+F313 -> 38.458931 | G75: =+G313 -> 40.87954 | H75: =+H313 -> 42.227804 | I75: =+I313 -> 46.564143 | J75: =+J313 -> 48.3161 | ... Y75: =+Y313 -> 125.50912 | Z75: 126.463 | AA75: 129.547 | AB75: 130.75 | AC75: 135.915 | AD75: 140.168 | AE75: 140.286 | AF75: 143.138 | AG75: 149.022
A76: BTP | C76: =+C314 -> 293.24591 | D76: =+D314 -> 302.50501 | E76: =+E314 -> 346.82994 | F76: =+F314 -> 349.01183 | G76: =+G314 -> 364.03183 | H76: =+H314 -> 398.77179 | I76: =+I314 -> 461.70785 | J76: =+J314 -> 458.67128 | ... Y76: =+Y314 -> 979.80594 | Z76: 1038.309 | AA76: 1131.87 | AB76: 1237.307 | AC76: 1303.841 | AD76: 1445.091 | AE76: 1520.669 | AF76: 1715.676 | AG76: 1969.31
A77: Secteur tertiaire | C77: =SUM(C78:C86) -> 2172.7783 | D77: =SUM(D78:D86) -> 2215.8833 | E77: =SUM(E78:E86) -> 2489.8723 | F77: =SUM(F78:F86) -> 2559.8259 | G77: =SUM(G78:G86) -> 2853.466 | H77: =SUM(H78:H86) -> 3037.3564 | I77: =SUM(I78:I86) -> 3251.6318 | J77: =SUM(J78:J86) -> 3379.2213 | ... Y77: =SUM(Y78:Y86) -> 9437.805 | Z77: 10112.755 | AA77: 10625.342 | AB77: 11200.791 | AC77: 11860.514 | AD77: 12147.75 | AE77: 12715.224 | AF77: 13666.267 | AG77: 15000.896
A78: Commerce, réparation véhicules | C78: =+C315+C316 -> 366.89554 | D78: =+D315+D316 -> 457.75061 | E78: =+E315+E316 -> 507.13627 | F78: =+F315+F316 -> 506.22929 | G78: =+G315+G316 -> 562.23327 | H78: =+H315+H316 -> 629.87656 | I78: =+I315+I316 -> 618.93923 | J78: =+J315+J316 -> 626.85645 | ... Y78: =+Y315+Y316 -> 2033.7328 | Z78: 2237.077 | AA78: 2326.717 | AB78: 2398.393 | AC78: 2551.862 | AD78: 2562.94 | AE78: 2705.399 | AF78: 3098.152 | AG78: 3305.177
A79: Restaurants et hôtels | C79: =+C318 -> 234.86716 | D79: =+D318 -> 236.4564 | E79: =+E318 -> 261.02796 | F79: =+F318 -> 258.00024 | G79: =+G318 -> 285.87595 | H79: =+H318 -> 295.25298 | I79: =+I318 -> 318.48519 | J79: =+J318 -> 345.85341 | ... Y79: =+Y318 -> 933.75623 | Z79: 976.647 | AA79: 1039.979 | AB79: 1131.246 | AC79: 1256.998 | AD79: 1186.746 | AE79: 1320.734 | AF79: 1427.4 | AG79: 1591.378
A80: Transports, entrepôts, communications | C80: =+C317 -> 293.92065 | D80: =+D317 -> 333.87711 | E80: =+E317 -> 390.44754 | F80: =+F317 -> 418.13495 | G80: =+G317 -> 488.91358 | H80: =+H317 -> 505.03993 | I80: =+I317 -> 532.52648 | J80: =+J317 -> 543.71547 | ... Y80: =+Y317 -> 1957.6789 | Z80: 2043.577 | AA80: 2133.636 | AB80: 2232.245 | AC80: 2368.174 | AD80: 2481.882 | AE80: 2571.267 | AF80: 2773.524 | AG80: 3240.531
A81: Informations et télécommunications | C81: =+C319 -> 63.980937 | D81: =+D319 -> 62.64971 | E81: =+E319 -> 76.616845 | F81: =+F319 -> 80.913054 | G81: =+G319 -> 92.667286 | H81: =+H319 -> 97.413194 | I81: =+I319 -> 120.97803 | J81: =+J319 -> 159.8963 | ... Y81: =+Y319 -> 404.13222 | Z81: 448.186 | AA81: 480.008 | AB81: 475.005 | AC81: 483.923 | AD81: 517.812 | AE81: 513.754 | AF81: 544.754 | AG81: 591.275
A82: Activités financières et d'assurance | C82: =C320 -> 72.432236 | D82: =D320 -> 68.113494 | E82: =E320 -> 113.77957 | F82: =F320 -> 99.57335 | G82: =G320 -> 83.101892 | H82: =H320 -> 82.272547 | I82: =I320 -> 81.001162 | J82: =J320 -> 84.894797 | ... Y82: =Y320 -> 338.59035 | Z82: 401.898 | AA82: 420.153 | AB82: 487.455 | AC82: 509.159 | AD82: 518.701 | AE82: 574.035 | AF82: 607.037 | AG82: 646.717
A83: Administration publique, sécurité sociale | C83: =C324 -> 343.50589 | D83: =D324 -> 292.95011 | E83: =E324 -> 298.61183 | F83: =F324 -> 317.22331 | G83: =G324 -> 336.57531 | H83: =H324 -> 333.21094 | I83: =I324 -> 372.30776 | J83: =J324 -> 388.92909 | ... Y83: =Y324 -> 961.55759 | Z83: 1093.065 | AA83: 1139.78 | AB83: 1238.472 | AC83: 1290.303 | AD83: 1347.116 | AE83: 1382.502 | AF83: 1462.46 | AG83: 1596.072
A84: Education | C84: =C325 -> 135.87635 | D84: =D325 -> 106.94564 | E84: =E325 -> 113.95826 | F84: =F325 -> 121.57719 | G84: =G325 -> 133.50345 | H84: =H325 -> 141.97743 | I84: =I325 -> 191.10833 | J84: =J325 -> 202.55544 | ... Y84: =Y325 -> 630.23733 | Z84: 706.594 | AA84: 747.357 | AB84: 786.754 | AC84: 814.892 | AD84: 824.587 | AE84: 842.57 | AF84: 895.499 | AG84: 997.135
A85: Santé et action sociale | C85: =C326 -> 67.169549 | D85: =D326 -> 62.412559 | E85: =E326 -> 76.578581 | F85: =F326 -> 83.873442 | G85: =G326 -> 95.685496 | H85: =H326 -> 108.33398 | I85: =I326 -> 87.388248 | J85: =J326 -> 73.414968 | ... Y85: =Y326 -> 206.24734 | Z85: 214.746 | AA85: 215.709 | AB85: 224.358 | AC85: 229.93 | AD85: 242.543 | AE85: 253.127 | AF85: 265.629 | AG85: 288.791
A86: Autres services | C86: =SUM(C321:C323,C327:C330) -> 594.13004 | D86: =SUM(D321:D323,D327:D330) -> 594.72765 | E86: =SUM(E321:E323,E327:E330) -> 651.71541 | F86: =SUM(F321:F323,F327:F330) -> 674.30111 | G86: =SUM(G321:G323,G327:G330) -> 774.90977 | H86: =SUM(H321:H323,H327:H330) -> 843.97883 | I86: =SUM(I321:I323,I327:I330) -> 928.89734 | J86: =SUM(J321:J323,J327:J330) -> 953.10534 | ... Y86: =SUM(Y321:Y323,Y327:Y330) -> 1971.8722 | Z86: 1990.965 | AA86: 2122.003 | AB86: 2226.863 | AC86: 2355.273 | AD86: 2465.423 | AE86: 2551.836 | AF86: 2591.812 | AG86: 2743.82
A87: TOTAL DES VALEURS AJOUTEES | C87: =C64+C69+C77 -> 4343.1196 | D87: =D64+D69+D77 -> 4673.0131 | E87: =E64+E69+E77 -> 5094.5651 | F87: =F64+F69+F77 -> 5292.2435 | G87: =G64+G69+G77 -> 5836.9189 | H87: =H64+H69+H77 -> 6139.7631 | I87: =I64+I69+I77 -> 6557.3969 | J87: =J64+J69+J77 -> 6876.3371 | ... Y87: =Y64+Y69+Y77 -> 17493.194 | Z87: 18403.673 | AA87: 19141.006 | AB87: 20344.351 | AC87: 21304.219 | AD87: 21660.693 | AE87: 23061.777 | AF87: 25748.095 | AG87: 27802.993
A88: Impôts et taxes nets des Subventions | C88: =+C332 -> 238.96475 | D88: =+D332 -> 269.66686 | E88: =+E332 -> 328.56895 | F88: =+F332 -> 382.68325 | G88: =+G332 -> 460.55757 | H88: =+H332 -> 525.59764 | I88: =+I332 -> 561.06103 | J88: =+J332 -> 628.13184 | ... Y88: =+Y332 -> 1549.8722 | Z88: 1634.893 | AA88: 1819.859 | AB88: 1858.978 | AC88: 1939.443 | AD88: 1807.814 | AE88: 1898.719 | AF88: 1913.925 | AG88: 2088.41
A89: PIB | C89: =+C87+C88 -> 4582.0844 | D89: =+D87+D88 -> 4942.68 | E89: =+E87+E88 -> 5423.1341 | F89: =+F87+F88 -> 5674.9268 | G89: =+G87+G88 -> 6297.4764 | H89: =+H87+H88 -> 6665.3607 | I89: =+I87+I88 -> 7118.4579 | J89: =+J87+J88 -> 7504.4689 | ... Y89: =+Y87+Y88 -> 19043.067 | Z89: 20038.566 | AA89: 20960.865 | AB89: 22203.329 | AC89: 23243.662 | AD89: 23468.507 | AE89: 24960.496 | AF89: 27662.02 | AG89: 29891.403
A90: PIB hors pétrole et gaz naturel | Z90: =Z89-Z71 -> 19386.146 | AA90: =AA89-AA71 -> 20300.721 | AB90: =AB89-AB71 -> 21373.595 | AC90: =AC89-AC71 -> 22371.697 | AD90: =AD89-AD71 -> 22991.437 | AE90: =AE89-AE71 -> 24073.881 | AF90: =AF89-AF71 -> 25963.982 | AG90: =AG89-AG71 -> 28707.505
A92: ="Tableau "&C92&": " -> Tableau :
A93: Ventilation du PIB aux prix de l'année précédente par secteurs d’activités
A94: Libellé | C94: =C$13 -> 1993 | D94: =D$13 -> 1994 | E94: =E$13 -> 1995 | F94: =F$13 -> 1996 | G94: =G$13 -> 1997 | H94: =H$13 -> 1998 | I94: =I$13 -> 1999 | J94: =J$13 -> 2000 | ... Y94: =Y$13 -> 2015 | Z94: 2016 | AA94: 2017 | AB94: 2018 | AC94: 2019 | AD94: 2020 | AE94: 2021 | AF94: 2022 | AG94: 2023
A95: Secteur primaire | D95: =SUM(D96:D99) -> 892.79301 | E95: =SUM(E96:E99) -> 1031.3753 | F95: =SUM(F96:F99) -> 1060.8283 | G95: =SUM(G96:G99) -> 1069.5765 | H95: =SUM(H96:H99) -> 1234.174 | I95: =SUM(I96:I99) -> 1356.0689 | J95: =SUM(J96:J99) -> 1375.1015 | K95: =SUM(K96:K99) -> 1405.6413 | ... Y95: =SUM(Y96:Y99) -> 3181.6653 | Z95: 3360.1096 | AA95: 3531.992 | AB95: 3633.481 | AC95: 3804.838 | AD95: 3959.085 | AE95: 4225.733 | AF95: 4376.723 | AG95: 4676.692
A96: Agriculture | D96: =D339 -> 493.42675 | E96: =E339 -> 541.2445 | F96: =F339 -> 576.65971 | G96: =G339 -> 588.61228 | H96: =H339 -> 660.67689 | I96: =I339 -> 722.1139 | J96: =J339 -> 765.62856 | K96: =K339 -> 773.87266 | ... Y96: =Y339 -> 1740.651 | Z96: 1873.1225 | AA96: 2010.138 | AB96: 2025.802 | AC96: 2141.005 | AD96: 2230.082 | AE96: 2400.749 | AF96: 2429.069 | AG96: 2583.831
A97: Elevage et chasse | D97: =D340 -> 101.40091 | E97: =E340 -> 115.06198 | F97: =F340 -> 134.67548 | G97: =G340 -> 140.68082 | H97: =H340 -> 160.59067 | I97: =I340 -> 168.91609 | J97: =J340 -> 181.41508 | K97: =K340 -> 192.18068 | ... Y97: =Y340 -> 422.03645 | Z97: 455.63642 | AA97: 444.93 | AB97: 468.259 | AC97: 494.493 | AD97: 509.048 | AE97: 530.036 | AF97: 567.209 | AG97: 618.122
A98: Sylviculture et exploitation forestière | D98: =D341 -> 206.79588 | E98: =E341 -> 275.65583 | F98: =F341 -> 247.59585 | G98: =G341 -> 239.24545 | H98: =H341 -> 293.94291 | I98: =I341 -> 344.36006 | J98: =J341 -> 297.06218 | K98: =K341 -> 305.7119 | ... Y98: =Y341 -> 764.69122 | Z98: 754.87063 | AA98: 778.431 | AB98: 822.535 | AC98: 840.515 | AD98: 885.023 | AE98: 936.834 | AF98: 990.121 | AG98: 1065.383
A99: Pêche et pisciculture | D99: =D342 -> 91.169473 | E99: =E342 -> 99.413017 | F99: =F342 -> 101.89725 | G99: =G342 -> 101.03793 | H99: =H342 -> 118.96356 | I99: =I342 -> 120.67883 | J99: =J342 -> 130.9957 | K99: =K342 -> 133.87606 | ... Y99: =Y342 -> 254.28664 | Z99: 276.47995 | AA99: 298.493 | AB99: 316.885 | AC99: 328.825 | AD99: 334.932 | AE99: 358.114 | AF99: 390.324 | AG99: 409.356
A100: Secteur secondaire | D100: =SUM(D101:D107)-D102 -> 1310.5935 | E100: =SUM(E101:E107)-E102 -> 1405.3031 | F100: =SUM(F101:F107)-F102 -> 1590.1428 | G100: =SUM(G101:G107)-G102 -> 1682.8629 | H100: =SUM(H101:H107)-H102 -> 1900.9396 | I100: =SUM(I101:I107)-I102 -> 1877.5577 | J100: =SUM(J101:J107)-J102 -> 1995.336 | K100: =SUM(K101:K107)-K102 -> 2177.5072 | ... Y100: =SUM(Y101:Y107)-Y102 -> 4915.0362 | Z100: 5014.866 | AA100: 4914.086 | AB100: 5234.702 | AC100: 5686.404 | AD100: 5617.383 | AE100: 5621.782 | AF100: 6317.823 | AG100: 7676.505
A101: Industries extractives | D101: =SUM(D343:D344) -> 184.06657 | E101: =SUM(E343:E344) -> 226.3652 | F101: =SUM(F343:F344) -> 200.72193 | G101: =SUM(G343:G344) -> 361.15539 | H101: =SUM(H343:H344) -> 338.72433 | I101: =SUM(I343:I344) -> 320.84262 | J101: =SUM(J343:J344) -> 239.56369 | K101: =SUM(K343:K344) -> 356.0283 | ... Y101: =SUM(Y343:Y344) -> 906.10592 | Z101: 719.42621 | AA101: 576.365 | AB101: 689.805 | AC101: 942.895 | AD101: 938.649 | AE101: 501.553 | AF101: 910.818 | AG101: 1706.987
A102: dont extraction d'hydrocarbures | D102: =+D343 -> 169.48283 | E102: =+E343 -> 211.23314 | F102: =+F343 -> 183.46815 | G102: =+G343 -> 334.33761 | H102: =+H343 -> 310.55175 | I102: =+I343 -> 291.55406 | J102: =+J343 -> 208.92149 | K102: =+K343 -> 323.90941 | ... Y102: =+Y343 -> 822.40352 | Z102: 628.50193 | AA102: 527.183 | AB102: 640.265 | AC102: 899.088 | AD102: 898.443 | AE102: 467.337 | AF102: 872.784 | AG102: 1661.857
A103: Industries Agro-alimentaires | D103: =SUM(D345:D352) -> 426.99734 | E103: =SUM(E345:E352) -> 433.28595 | F103: =SUM(F345:F352) -> 492.25018 | G103: =SUM(G345:G352) -> 453.87805 | H103: =SUM(H345:H352) -> 548.63738 | I103: =SUM(I345:I352) -> 565.79861 | J103: =SUM(J345:J352) -> 615.32074 | K103: =SUM(K345:K352) -> 628.59803 | ... Y103: =SUM(Y345:Y352) -> 1301.8246 | Z103: 1401.5285 | AA103: 1404.367 | AB103: 1425.874 | AC103: 1453.936 | AD103: 1431.592 | AE103: 1627.933 | AF103: 1728.321 | AG103: 1953.17
A104: Autres Industries manufacturières | D104: =SUM(D353:D366) -> 356.00926 | E104: =SUM(E353:E366) -> 368.03935 | F104: =SUM(F353:F366) -> 456.89837 | G104: =SUM(G353:G366) -> 431.87425 | H104: =SUM(H353:H366) -> 534.03156 | I104: =SUM(I353:I366) -> 473.36406 | J104: =SUM(J353:J366) -> 555.55901 | K104: =SUM(K353:K366) -> 620.05853 | ... Y104: =SUM(Y353:Y366) -> 1417.4733 | Z104: 1458.0663 | AA104: 1454.344 | AB104: 1550.957 | AC104: 1619.114 | AD104: 1511.323 | AE104: 1657.847 | AF104: 1733.224 | AG104: 1863.167
A105: Production et distribution d'électricité | D105: =+D367 -> 41.110637 | E105: =+E367 -> 40.48346 | F105: =+F367 -> 45.285251 | G105: =+G367 -> 42.2216 | H105: =+H367 -> 45.040744 | I105: =+I367 -> 46.849091 | J105: =+J367 -> 53.626217 | K105: =+K367 -> 52.237844 | ... Y105: =+Y367 -> 195.7772 | Z105: 215.75557 | AA105: 223.195 | AB105: 216.467 | AC105: 202.002 | AD105: 204.019 | AE105: 210.474 | AF105: 216.459 | AG105: 220.002
A106: Production et distribution d'eau et assainissement | D106: =+D368 -> 35.27597 | E106: =+E368 -> 35.83884 | F106: =+F368 -> 38.916099 | G106: =+G368 -> 41.107263 | H106: =+H368 -> 41.757891 | I106: =+I368 -> 45.497945 | J106: =+J368 -> 48.561332 | K106: =+K368 -> 49.166644 | ... Y106: =+Y368 -> 125.6552 | Z106: 122.75001 | AA106: 129.704 | AB106: 132.721 | AC106: 133.053 | AD106: 139.841 | AE106: 140.273 | AF106: 144.028 | AG106: 146.819
A107: BTP | D107: =+D369 -> 267.13375 | E107: =+E369 -> 301.29033 | F107: =+F369 -> 356.07097 | G107: =+G369 -> 352.62632 | H107: =+H369 -> 392.74765 | I107: =+I369 -> 425.20536 | J107: =+J369 -> 482.70502 | K107: =+K369 -> 471.4179 | ... Y107: =+Y369 -> 968.19999 | Z107: 1097.3395 | AA107: 1126.111 | AB107: 1218.878 | AC107: 1335.404 | AD107: 1391.959 | AE107: 1483.702 | AF107: 1584.973 | AG107: 1786.36
A108: Secteur tertiaire | D108: =SUM(D109:D117) -> 2221.1339 | E108: =SUM(E109:E117) -> 2343.8731 | F108: =SUM(F109:F117) -> 2619.7321 | G108: =SUM(G109:G117) -> 2716.4163 | H108: =SUM(H109:H117) -> 2973.119 | I108: =SUM(I109:I117) -> 3151.3182 | J108: =SUM(J109:J117) -> 3423.6861 | K108: =SUM(K109:K117) -> 3593.1696 | ... Y108: =SUM(Y109:Y117) -> 9352.5403 | Z108: 9855.7758 | AA108: 10594.012 | AB108: 11094.253 | AC108: 11553.323 | AD108: 11876.254 | AE108: 12514.479 | AF108: 13215.607 | AG108: 14203.366
A109: Commerce, réparation véhicules | D109: =+D370+D371 -> 419.06013 | E109: =+E370+E371 -> 461.30311 | F109: =+F370+F371 -> 525.76042 | G109: =+G370+G371 -> 545.97774 | H109: =+H370+H371 -> 606.80659 | I109: =+I370+I371 -> 620.09004 | J109: =+J370+J371 -> 659.12689 | K109: =+K370+K371 -> 659.90401 | ... Y109: =+Y370+Y371 -> 1988.7422 | Z109: 2157.1004 | AA109: 2335.825 | AB109: 2391.286 | AC109: 2466.478 | AD109: 2560.091 | AE109: 2637.204 | AF109: 2770.132 | AG109: 3186.862
A110: Restaurants et hôtels | D110: =+D373 -> 219.85286 | E110: =+E373 -> 240.44604 | F110: =+F373 -> 277.80231 | G110: =+G373 -> 279.31467 | H110: =+H373 -> 309.11078 | I110: =+I373 -> 320.6161 | J110: =+J373 -> 338.75892 | K110: =+K373 -> 358.93775 | ... Y110: =+Y373 -> 907.44063 | Z110: 979.71143 | AA110: 1037.647 | AB110: 1093.68 | AC110: 1178.603 | AD110: 1151.559 | AE110: 1301.706 | AF110: 1375.099 | AG110: 1495.882
A111: Transports, entrepôts, communications | D111: =+D372 -> 315.56395 | E111: =+E372 -> 361.71957 | F111: =+F372 -> 402.428 | G111: =+G372 -> 426.20401 | H111: =+H372 -> 440.10569 | I111: =+I372 -> 498.88674 | J111: =+J372 -> 582.92757 | K111: =+K372 -> 551.86599 | ... Y111: =+Y372 -> 1936.4548 | Z111: 2002.1762 | AA111: 2129.797 | AB111: 2218.556 | AC111: 2324.803 | AD111: 2368.817 | AE111: 2521.21 | AF111: 2717.707 | AG111: 2890.176
A112: Informations et télécommunications | D112: =+D374 -> 63.799554 | E112: =+E374 -> 68.898057 | F112: =+F374 -> 83.600004 | G112: =+G374 -> 92.58502 | H112: =+H374 -> 103.1322 | I112: =+I374 -> 120.59087 | J112: =+J374 -> 149.22955 | K112: =+K374 -> 199.22085 | ... Y112: =+Y374 -> 427.53062 | Z112: 441.53225 | AA112: 479.243 | AB112: 475.976 | AC112: 482.657 | AD112: 509.4 | AE112: 531.188 | AF112: 550.188 | AG112: 598.233
A113: Activités financières et d'assurance | D113: =D375 -> 70.388372 | E113: =E375 -> 113.65945 | F113: =F375 -> 102.40713 | G113: =G375 -> 82.882713 | H113: =H375 -> 81.591392 | I113: =I375 -> 82.140641 | J113: =J375 -> 83.804667 | K113: =K375 -> 81.545267 | ... Y113: =Y375 -> 340.56815 | Z113: 364.04851 | AA113: 421.978 | AB113: 477.917 | AC113: 503.131 | AD113: 523.312 | AE113: 566.493 | AF113: 610.783 | AG113: 657.72
A114: Administration publique, sécurité sociale | D114: =D379 -> 318.32468 | E114: =E379 -> 305.15163 | F114: =F379 -> 320.96836 | G114: =G379 -> 292.15715 | H114: =H379 -> 357.2251 | I114: =I379 -> 363.79659 | J114: =J379 -> 407.12161 | K114: =K379 -> 429.72244 | ... Y114: =Y379 -> 959.44962 | Z114: 980.13186 | AA114: 1131.787 | AB114: 1196.409 | AC114: 1276.275 | AD114: 1322.362 | AE114: 1376.968 | AF114: 1443.96 | AG114: 1508.079
A115: Education | D115: =D380 -> 129.73609 | E115: =E380 -> 109.17287 | F115: =F380 -> 117.40325 | G115: =G380 -> 129.88183 | H115: =H380 -> 149.88294 | I115: =I380 -> 145.89579 | J115: =J380 -> 185.1856 | K115: =K380 -> 218.5057 | ... Y115: =Y380 -> 611.0883 | Z115: 668.27361 | AA115: 736.098 | AB115: 762.513 | AC115: 802.873 | AD115: 819.508 | AE115: 850.046 | AF115: 865.522 | AG115: 924.279
...

Sheet PIB_Trimestriel_Brut (2016)
A1: REPUBLIQUE DU CAMEROUN
A2: Paix – Travail – Patrie
A3: ---------------
A4: INSTITUT NATIONAL DE LA STATISTIQUE
A8: Offre du PIB trimestriel en volume chainé (reference 2016), Données brutes
A10: Libellé | B10: T1_1999 | C10: T2_1999 | D10: T3_1999 | E10: T4_1999 | F10: T1_2000 | G10: T2_2000 | H10: T3_2000 | I10: T4_2000 | J10: T1_2001 | K10: T2_2001 | L10: T3_2001 | M10: T4_2001 | N10: T1_2002 | O10: T2_2002 | P10: T3_2002 | Q10: T4_2002 | R10: T1_2003 | S10: T2_2003 | T10: T3_2003 | U10: T4_2003 | V10: T1_2004 | W10: T2_2004 | X10: T3_2004 | Y10: T4_2004 | Z10: T1_2005 | AA10: T2_2005 | AB10: T3_2005 | AC10: T4_2005 | AD10: T1_2006 | AE10: T2_2006 | AF10: T3_2006 | AG10: T4_2006 | AH10: T1_2007 | AI10: T2_2007 | AJ10: T3_2007 | AK10: T4_2007 | AL10: T1_2008 | AM10: T2_2008 | AN10: T3_2008 | AO10: T4_2008 | AP10: T1_2009 | AQ10: T2_2009 | AR10: T3_2009 | AS10: T4_2009 | AT10: T1_2010 | AU10: T2_2010 | AV10: T3_2010 | AW10: T4_2010 | AX10: T1_2011 | AY10: T2_2011 | AZ10: T3_2011 | BA10: T4_2011 | BB10: T1_2012 | BC10: T2_2012 | BD10: T3_2012 | BE10: T4_2012 | BF10: T1_2013 | BG10: T2_2013 | BH10: T3_2013 | BI10: T4_2013 | BJ10: T1_2014 | BK10: T2_2014 | BL10: T3_2014 | BM10: T4_2014 | BN10: T1_2015 | BO10: T2_2015 | BP10: T3_2015 | BQ10: T4_2015 | BR10: T1_2016 | BS10: T2_2016 | BT10: T3_2016 | BU10: T4_2016 | BV10: T1_2017 | BW10: T2_2017 | BX10: T3_2017 | BY10: T4_2017 | BZ10: T1_2018 | CA10: T2_2018 | CB10: T3_2018 | CC10: T4_2018 | CD10: T1_2019 | CE10: T2_2019 | CF10: T3_2019 | CG10: T4_2019 | CH10: T1_2020 | CI10: T2_2020 | CJ10: T3_2020 | CK10: T4_2020 | CL10: T1_2021 | CM10: T2_2021 | CN10: T3_2021 | CO10: T4_2021 | CP10: T1_2022 | CQ10: T2_2022 | CR10: T3_2022 | CS10: T4_2022 | CT10: T1_2023 | CU10: T2_2023 | CV10: T3_2023 | CW10: T4_2023 | CX10: T1_2024 | CY10: T2_2024 | CZ10: T3_2024 | DA10: T4_2024 | DD10: Croissance réelle 2024/2023 (en %) | DG10: 2023 | DH10: 2024
A11: Secteur primaire | B11: 475.82041 | C11: 553.79322 | D11: 510.6411 | E11: 487.17955 | F11: 477.18093 | G11: 568.69738 | H11: 523.76422 | I11: 493.96495 | J11: 504.06469 | K11: 575.63097 | L11: 544.90544 | M11: 508.82479 | N11: 484.61782 | O11: 573.40333 | P11: 561.15273 | Q11: 567.85595 | R11: 498.33092 | S11: 572.6477 | T11: 578.80902 | U11: 607.18923 | V11: 570.98413 | W11: 651.33722 | X11: 623.83928 | Y11: 598.56601 | Z11: 540.20482 | AA11: 587.90362 | AB11: 600.96905 | AC11: 594.42815 | AD11: 497.65008 | AE11: 592.07182 | AF11: 622.47632 | AG11: 611.5301 | AH11: 548.30036 | AI11: 634.34065 | AJ11: 634.26501 | AK11: 631.9867 | AL11: 588.30915 | AM11: 647.35308 | AN11: 626.81207 | AO11: 675.45808 | AP11: 596.31305 | AQ11: 660.22898 | AR11: 663.0404 | AS11: 683.33639 | AT11: 605.24741 | AU11: 696.20701 | AV11: 707.55743 | AW11: 724.55968 | AX11: 648.98311 | AY11: 724.32496 | AZ11: 722.0155 | BA11: 718.1314 | BB11: 668.95258 | BC11: 761.71968 | BD11: 755.72281 | BE11: 724.53789 | BF11: 720.05806 | BG11: 784.87105 | BH11: 780.23605 | BI11: 748.72931 | BJ11: 725.68264 | BK11: 825.64604 | BL11: 813.27024 | BM11: 827.93805 | BN11: 794.86586 | BO11: 872.91628 | BP11: 858.43961 | BQ11: 833.93357 | BR11: 770.15644 | BS11: 888.17341 | BT11: 877.98098 | BU11: 908.85217 | BV11: 853.93046 | BW11: 922.92598 | BX11: 906.52836 | BY11: 848.6072 | BZ11: 865.70766 | CA11: 961.89359 | CB11: 918.17194 | CC11: 921.98356 | CD11: 853.37212 | CE11: 1017.9222 | CF11: 978.57522 | CG11: 959.61503 | CH11: 898.38357 | CI11: 964.41985 | CJ11: 978.1266 | CK11: 1020.4365 | CL11: 952.19351 | CM11: 1012.1161 | CN11: 1002.7841 | CO11: 1006.6273 | CP11: 971.51953 | CQ11: 1089.7688 | CR11: 1040.6861 | CS11: 1006.577 | CT11: 947.09891 | CU11: 1111.3185 | CV11: 1087.1647 | CW11: 1052.3644 | CX11: 1026.5005 | CY11: 1105.0003 | CZ11: 1108.5796 | DA11: 1105.0668 | DD11: =(SUM(CX11:DA11)/SUM(CT11:CW11)-1)*100 -> 3.5064911 | DG11: =+SUM(CT11:CW11) -> 4197.9466 | DH11: =+SUM(CX11:DA11) -> 4345.1472
A12: Agrivriere | B12: 110.42004 | C12: 184.61926 | D12: 172.54472 | E12: 119.81086 | F12: 117.84399 | G12: 193.37086 | H12: 183.80127 | I12: 132.46288 | J12: 132.31098 | K12: 217.13538 | L12: 205.99642 | M12: 147.87917 | N12: 144.53971 | O12: 236.1626 | P12: 223.26108 | Q12: 159.8489 | R12: 140.69941 | S12: 230.82701 | T12: 220.31612 | U12: 160.13642 | V12: 161.51244 | W12: 266.86423 | X12: 253.92898 | Y12: 182.13512 | Z12: 161.2764 | AA12: 262.01955 | AB12: 246.40468 | AC12: 175.56013 | AD12: 152.64474 | AE12: 248.16638 | AF12: 233.71892 | AG12: 166.90093 | AH12: 156.49931 | AI12: 255.0802 | AJ12: 240.91368 | AK12: 172.56957 | AL12: 165.4053 | AM12: 269.86134 | AN12: 253.48437 | AO12: 179.4708 | AP12: 182.52677 | AQ12: 290.13229 | AR12: 263.22463 | AS12: 178.32121 | AT12: 179.53061 | AU12: 280.94339 | AV12: 259.5587 | AW12: 185.31097 | AX12: 171.12696 | AY12: 280.7823 | AZ12: 264.72008 | BA12: 187.74944 | BB12: 178.39649 | BC12: 287.54541 | BD12: 269.49269 | BE12: 192.20254 | BF12: 185.6571 | BG12: 303.09803 | BH12: 286.86702 | BI12: 205.99582 | BJ12: 192.59424 | BK12: 315.28044 | BL12: 298.50556 | BM12: 213.97084 | BN12: 200.53644 | BO12: 330.55883 | BP12: 317.56225 | BQ12: 233.19256 | BR12: 239.45078 | BS12: 390.87703 | BT12: 369.8281 | BU12: 265.4541 | BV12: 250.43865 | BW12: 409.7077 | BX12: 387.33212 | BY12: 277.00053 | BZ12: 259.97355 | CA12: 423.8132 | CB12: 400.49616 | CC12: 287.15237 | CD12: 272.28824 | CE12: 440.1251 | CF12: 410.35908 | CG12: 295.67182 | CH12: 225.41466 | CI12: 366.87892 | CJ12: 346.15308 | CK12: 247.77231 | CL12: 226.25134 | CM12: 370.27203 | CN12: 351.41994 | CO12: 253.15529 | CP12: 234.59036 | CQ12: 385.5012 | CR12: 366.4625 | CS12: 263.82321 | CT12: 241.64111 | CU12: 395.99302 | CV12: 374.70498 | CW12: 268.01034 | CX12: 250.57487 | CY12: 408.09195 | CZ12: 384.9164 | DA12: 275.20984 | DB12: =+SUM(CP12:CS12) -> 1250.3773 | DC12: =+SUM(CT12:CW12) -> 1280.3494 | DD12: =(SUM(CX12:DA12)/SUM(CT12:CW12)-1)*100 -> 3.0025877 | DG12: =+SUM(CT12:CW12) -> 1280.3494 | DH12: =+SUM(CX12:DA12) -> 1318.7931
A13: Agriexport | B13: 167.44766 | C13: 149.38359 | D13: 118.16583 | E13: 176.33729 | F13: 159.38347 | G13: 163.19571 | H13: 120.85687 | I13: 167.17574 | J13: 171.46529 | K13: 130.36752 | L13: 103.85338 | M13: 151.38096 | N13: 116.83648 | O13: 97.937655 | P13: 109.01749 | Q13: 214.36933 | R13: 145.49424 | S13: 113.47279 | T13: 133.98853 | U13: 237.60273 | V13: 175.98075 | W13: 123.0849 | X13: 100.73374 | Y13: 185.13216 | Z13: 147.58027 | AA13: 95.842998 | AB13: 127.47722 | AC13: 195.21933 | AD13: 102.59043 | AE13: 100.40582 | AF13: 155.9165 | AG13: 220.53996 | AH13: 136.38686 | AI13: 121.61009 | AJ13: 134.19765 | AK13: 210.97403 | AL13: 158.78335 | AM13: 102.43996 | AN13: 93.18782 | AO13: 233.04924 | AP13: 140.74864 | AQ13: 99.255932 | AR13: 126.96547 | AS13: 236.17714 | AT13: 138.94209 | AU13: 126.42555 | AV13: 160.40063 | AW13: 260.76656 | AX13: 193.91159 | AY13: 135.63384 | AZ13: 152.86422 | BA13: 247.95114 | BB13: 189.13017 | BC13: 152.33531 | BD13: 171.27949 | BE13: 245.53556 | BF13: 235.74037 | BG13: 147.97975 | BH13: 160.71972 | BI13: 241.73143 | BJ13: 208.29016 | BK13: 165.29294 | BL13: 155.62371 | BM13: 285.1627 | BN13: 250.00171 | BO13: 168.70266 | BP13: 187.48171 | BQ13: 274.3319 | BR13: 180.52943 | BS13: 119.60395 | BT13: 126.47714 | BU13: 293.02048 | BV13: 232.08355 | BW13: 136.98062 | BX13: 135.00411 | BY13: 181.59072 | BZ13: 217.13087 | CA13: 122.20399 | CB13: 113.72021 | CC13: 249.67581 | CD13: 188.51451 | CE13: 149.54352 | CF13: 140.26352 | CG13: 245.51427 | CH13: 279.36118 | CI13: 148.84728 | CJ13: 207.84355 | CK13: 397.28976 | CL13: 344.32053 | CM13: 201.2993 | CN13: 203.52694 | CO13: 353.86013 | CP13: 337.82909 | CQ13: 226.21105 | CR13: 202.59873 | CS13: 323.25321 | CT13: 298.60579 | CU13: 230.73935 | CV13: 198.06519 | CW13: 344.32471 | CX13: 370.64363 | CY13: 191.56177 | CZ13: 213.9705 | DA13: 397.68256 | DB13: =+SUM(CP13:CS13) -> 1089.8921 | DC13: =+SUM(CT13:CW13) -> 1071.735 | DD13: =(SUM(CX13:DA13)/SUM(CT13:CW13)-1)*100 -> 9.5287925 | DE13: =+DE15+DE16 -> 2583.831 | DG13: =+SUM(CT13:CW13) -> 1071.735 | DH13: =+SUM(CX13:DA13) -> 1173.8585
A14: Elev_Chass_Pech | B14: 89.09799 | C14: 89.165908 | D14: 89.302917 | E14: 89.511392 | F14: 90.147958 | G14: 90.681986 | H14: 91.267866 | I14: 91.887332 | J14: 92.601869 | K14: 93.928876 | L14: 95.942874 | M14: 98.68076 | N14: 102.09994 | O14: 104.69001 | P14: 106.38 | Q14: 107.14923 | R14: 106.9813 | S14: 107.33638 | T14: 108.19389 | U14: 109.59676 | V14: 111.65219 | W14: 112.98277 | X14: 113.5008 | Y14: 113.17265 | Z14: 112.07397 | AA14: 111.5818 | AB14: 111.65445 | AC14: 112.2734 | AD14: 113.36634 | AE14: 114.32385 | AF14: 115.10121 | AG14: 115.69952 | AH14: 116.10338 | AI14: 116.93106 | AJ14: 118.14848 | AK14: 119.7339 | AL14: 121.67159 | AM14: 123.79151 | AN14: 126.14082 | AO14: 128.76171 | AP14: 131.75831 | AQ14: 134.16572 | AR14: 135.9707 | AS14: 137.13865 | AT14: 137.60403 | AU14: 138.66468 | AV14: 140.34397 | AW14: 142.6664 | AX14: 145.70762 | AY14: 148.24119 | AZ14: 150.25156 | BA14: 151.70955 | BB14: 152.59464 | BC14: 153.51836 | BD14: 154.49777 | BE14: 155.54687 | BF14: 156.64652 | BG14: 157.97576 | BH14: 159.51055 | BI14: 161.24586 | BJ14: 163.25107 | BK14: 164.70699 | BL14: 165.64199 | BM14: 166.04997 | BN14: 165.90553 | BO14: 166.59973 | BP14: 168.15567 | BQ14: 170.62992 | BR14: 174.04408 | BS14: 177.11974 | BT14: 179.77017 | BU14: 181.92601 | BV14: 183.48485 | BW14: 185.07138 | BX14: 186.64601 | BY14: 188.22075 | BZ14: 189.80707 | CA14: 191.393 | CB14: 192.98165 | CC14: 194.57626 | CD14: 196.1801 | CE14: 197.62152 | CF14: 198.89876 | CG14: 200.01077 | CH14: 200.86539 | CI14: 201.75692 | CJ14: 202.64422 | CK14: 203.52678 | CL14: 204.40281 | CM14: 205.81603 | CN14: 207.76397 | CO14: 210.24731 | CP14: 213.26738 | CQ14: 215.87442 | CR14: 218.06873 | CS14: 219.85084 | CT14: 221.21484 | CU14: 222.85729 | CV14: 224.77558 | CW14: 226.96843 | CX14: 229.43518 | CY14: 231.28411 | CZ14: 232.51654 | DA14: 233.13266 | DD14: =(SUM(CX14:DA14)/SUM(CT14:CW14)-1)*100 -> 3.4105599 | DG14: =+SUM(CT14:CW14) -> 895.81614 | DH14: =+SUM(CX14:DA14) -> 926.36849
A15: Sylviculture | B15: 146.02944 | C15: 152.11038 | D15: 142.55347 | E15: 138.30258 | F15: 142.3628 | G15: 143.67811 | H15: 137.23317 | I15: 132.70355 | J15: 140.69499 | K15: 141.65963 | L15: 138.23896 | M15: 131.89438 | N15: 130.7348 | O15: 129.99021 | P15: 120.41577 | Q15: 117.6663 | R15: 116.59086 | S15: 122.98946 | T15: 122.8691 | U15: 131.18987 | V15: 139.43447 | W15: 146.43345 | X15: 146.64698 | Y15: 137.9067 | Z15: 124.13357 | AA15: 119.9146 | AB15: 121.59242 | AC15: 125.43745 | AD15: 125.26915 | AE15: 127.20732 | AF15: 127.20216 | AG15: 129.78742 | AH15: 141.39163 | AI15: 144.60542 | AJ15: 146.15266 | AK15: 143.98534 | AL15: 146.19798 | AM15: 152.91362 | AN15: 152.33235 | AO15: 149.49236 | AP15: 140.69057 | AQ15: 141.64472 | AR15: 142.19329 | AS15: 142.14383 | AT15: 150.37108 | AU15: 153.23665 | AV15: 153.50155 | AW15: 151.49804 | AX15: 150.65431 | AY15: 156.29304 | AZ15: 154.59014 | BA15: 152.28315 | BB15: 160.5522 | BC15: 163.3391 | BD15: 161.48214 | BE15: 156.45185 | BF15: 167.2679 | BG15: 164.79433 | BH15: 167.01648 | BI15: 164.49801 | BJ15: 176.75341 | BK15: 172.85184 | BL15: 184.19496 | BM15: 195.82753 | BN15: 199.31595 | BO15: 200.95924 | BP15: 184.97699 | BQ15: 180.63114 | BR15: 180.54972 | BS15: 186.17031 | BT15: 189.52282 | BU15: 190.81915 | BV15: 187.92341 | BW15: 191.16628 | BX15: 197.54612 | BY15: 201.79519 | BZ15: 206.35184 | CA15: 215.20029 | CB15: 201.64086 | CC15: 200.71478 | CD15: 200.84008 | CE15: 223.02412 | CF15: 221.98513 | CG15: 228.30063 | CH15: 216.93567 | CI15: 225.05174 | CJ15: 214.3124 | CK15: 216.79918 | CL15: 219.07753 | CM15: 218.94704 | CN15: 228.17696 | CO15: 228.88887 | CP15: 226.98956 | CQ15: 247.44891 | CR15: 235.84825 | CS15: 231.60022 | CT15: 222.90507 | CU15: 235.62796 | CV15: 258.29521 | CW15: 259.69779 | CX15: 228.77605 | CY15: 235.34208 | CZ15: 251.97139 | DA15: 254.69591 | DC15: =+DC12/DB12-1 -> 0.023970507 | DD15: =(SUM(CX15:DA15)/SUM(CT15:CW15)-1)*100 -> -0.5878592 | DE15: =+DB61*(1+DC15) -> 1799.023 | DG15: =+SUM(CT15:CW15) -> 976.52603 | DH15: =+SUM(CX15:DA15) -> 970.78543
A16: Secteur secondaire | B16: 804.51373 | C16: 828.43201 | D16: 768.84344 | E16: 787.62202 | F16: 814.68717 | G16: 827.32406 | H16: 808.25396 | I16: 805.3371 | J16: 830.65798 | K16: 846.37235 | L16: 801.19667 | M16: 838.34797 | N16: 944.67192 | O16: 925.09469 | P16: 945.79971 | Q16: 924.49414 | R16: 938.15393 | S16: 946.89369 | T16: 942.2018 | U16: 947.2727 | V16: 997.35587 | W16: 1032.5701 | X16: 1015.0908 | Y16: 999.70918 | Z16: 1015.5646 | AA16: 985.03731 | AB16: 977.04615 | AC16: 951.66561 | AD16: 1020.9247 | AE16: 1008.2866 | AF16: 991.5699 | AG16: 1092.7291 | AH16: 1055.2564 | AI16: 1000.318 | AJ16: 1014.1175 | AK16: 976.0148 | AL16: 1042.053 | AM16: 1054.5594 | AN16: 994.90345 | AO16: 946.94153 | AP16: 1024.7376 | AQ16: 1002.2558 | AR16: 992.6389 | AS16: 985.85586 | AT16: 1027.0829 | AU16: 993.97063 | AV16: 969.4421 | AW16: 953.58995 | AX16: 1004.8738 | AY16: 937.09729 | AZ16: 967.35065 | BA16: 975.34651 | BB16: 1075.4859 | BC16: 1054.8575 | BD16: 1034.0396 | BE16: 976.57183 | BF16: 1123.0012 | BG16: 1037.2164 | BH16: 1061.5498 | BI16: 1047.5175 | BJ16: 1078.9604 | BK16: 1055.4436 | BL16: 1074.8062 | BM16: 1129.4739 | BN16: 1114.0078 | BO16: 1120.5115 | BP16: 1163.0517 | BQ16: 1219.4879 | BR16: 1228.3376 | BS16: 1235.8674 | BT16: 1190.4939 | BU16: 1191.0561 | BV16: 1231.9179 | BW16: 1248.2788 | BX16: 1238.0332 | BY16: 1195.8561 | BZ16: 1281.2894 | CA16: 1306.541 | CB16: 1239.4199 | CC16: 1230.9429 | CD16: 1322.5325 | CE16: 1325.7503 | CF16: 1296.0082 | CG16: 1304.1583 | CH16: 1344.7198 | CI16: 1362.6752 | CJ16: 1335.6705 | CK16: 1353.8901 | CL16: 1393.9321 | CM16: 1451.0386 | CN16: 1383.0074 | CO16: 1383.6822 | CP16: 1443.6984 | CQ16: 1494.7214 | CR16: 1421.1146 | CS16: 1439.7136 | CT16: 1497.1089 | CU16: 1512.2798 | CV16: 1449.4107 | CW16: 1473.1901 | CX16: 1513.287 | CY16: 1543.7871 | CZ16: 1472.3528 | DA16: 1470.8741 | DC16: =+DC13/DB13-1 -> -0.016659483 | DD16: =(SUM(CX16:DA16)/SUM(CT16:CW16)-1)*100 -> 1.1515773 | DE16: =+DB62*(1+DC16) -> 784.808 | DG16: =+SUM(CT16:CW16) -> 5931.9896 | DH16: =+SUM(CX16:DA16) -> 6000.301
A17: Industries Extractives | B17: 2743.1515 | C17: 2667.6171 | D17: 2377.5173 | E17: 1978.0159 | F17: 1994.964 | G17: 1939.9469 | H17: 1941.3797 | I17: 1989.9126 | J17: 1588.6165 | K17: 1582.3655 | L17: 1455.2461 | M17: 1314.733 | N17: 1624.2956 | O17: 1440.3761 | P17: 1360.7256 | Q17: 1183.734 | R17: 1116.7383 | S17: 1101.4563 | T17: 1115.0165 | U17: 1135.3962 | V17: 1097.6211 | W17: 1103.1582 | X17: 1116.9627 | Y17: 969.54259 | Z17: 815.52131 | AA17: 723.45603 | AB17: 685.63444 | AC17: 669.09897 | AD17: 750.87735 | AE17: 730.66519 | AF17: 664.34984 | AG17: 587.39683 | AH17: 546.68028 | AI17: 498.0478 | AJ17: 506.81187 | AK17: 510.39131 | AL17: 572.99837 | AM17: 596.20085 | AN17: 575.851 | AO17: 525.27233 | AP17: 531.22898 | AQ17: 483.7944 | AR17: 489.25916 | AS17: 461.86924 | AT17: 444.33067 | AU17: 410.64062 | AV17: 355.56091 | AW17: 285.62727 | AX17: 202.38028 | AY17: 165.81204 | AZ17: 147.71368 | BA17: 125.76189 | BB17: 192.98547 | BC17: 180.37325 | BD17: 170.18188 | BE17: 149.63794 | BF17: 165.31448 | BG17: 159.24647 | BH17: 177.24766 | BI17: 168.88297 | BJ17: 163.2625 | BK17: 155.43568 | BL17: 154.22037 | BM17: 151.31328 | BN17: 156.36865 | BO17: 180.78545 | BP17: 187.42901 | BQ17: 195.82281 | BR17: 192.2554 | BS17: 183.98304 | BT17: 164.87888 | BU17: 157.61768 | BV17: 152.0608 | BW17: 150.48618 | BX17: 139.3641 | BY17: 134.45392 | BZ17: 130.68082 | CA17: 139.77521 | CB17: 145.38115 | CC17: 144.53721 | CD17: 144.36716 | CE17: 145.76079 | CF17: 154.99095 | CG17: 161.03934 | CH17: 156.46239 | CI17: 154.79342 | CJ17: 153.35589 | CK17: 156.88887 | CL17: 150.53295 | CM17: 155.41431 | CN17: 149.17215 | CO17: 147.7804 | CP17: 147.46865 | CQ17: 150.93329 | CR17: 141.99913 | CS17: 154.46286 | CT17: 150.20101 | CU17: 145.78633 | CV17: 140.07616 | CW17: 147.51879 | CX17: 143.78111 | CY17: 136.50762 | CZ17: 132.72891 | DA17: 121.07562 | DD17: =(SUM(CX17:DA17)/SUM(CT17:CW17)-1)*100 -> -8.4802157 | DG17: =+SUM(CT17:CW17) -> 583.58229 | DH17: =+SUM(CX17:DA17) -> 534.09326
A18: dont extraction d'hydrocarbure | B18: 4432.263 | C18: 4270.9804 | D18: 3820.3721 | E18: 3049.6347 | F18: 3097.5017 | G18: 2941.9641 | H18: 2957.2466 | I18: 3122.748 | J18: 2388.2108 | K18: 2363.8247 | L18: 2207.216 | M18: 1965.5127 | N18: 2434.7117 | O18: 2144.6654 | P18: 2006.2793 | Q18: 1753.1156 | R18: 1607.0338 | S18: 1564.314 | T18: 1581.2096 | U18: 1699.6456 | V18: 1584.7321 | W18: 1544.1048 | X18: 1609.309 | Y18: 1378.5052 | Z18: 1060.2568 | AA18: 891.14208 | AB18: 835.13525 | AC18: 836.67645 | AD18: 932.71266 | AE18: 910.58754 | AF18: 829.49654 | AG18: 729.42691 | AH18: 647.48813 | AI18: 592.31409 | AJ18: 605.13638 | AK18: 621.21195 | AL18: 702.6529 | AM18: 710.6329 | AN18: 690.97848 | AO18: 640.63798 | AP18: 636.28939 | AQ18: 575.06961 | AR18: 581.01301 | AS18: 548.13623 | AT18: 519.57941 | AU18: 473.28154 | AV18: 403.86244 | AW18: 319.79812 | AX18: 198.80422 | AY18: 166.78639 | AZ18: 134.71491 | BA18: 111.48872 | BB18: 187.20304 | BC18: 170.439 | BD18: 161.2826 | BE18: 146.69461 | BF18: 150.08266 | BG18: 152.68841 | BH18: 169.06431 | BI18: 167.27883 | BJ18: 156.9928 | BK18: 148.2293 | BL18: 145.28483 | BM18: 139.86572 | BN18: 149.06995 | BO18: 175.12829 | BP18: 177.11233 | BQ18: 180.62827 | BR18: 181.65093 | BS18: 168.4621 | BT18: 154.17825 | BU18: 148.12872 | BV18: 140.45923 | BW18: 137.50742 | BX18: 125.30712 | BY18: 123.90923 | BZ18: 118.60959 | CA18: 126.82047 | CB18: 133.21569 | CC18: 132.75508 | CD18: 131.88238 | CE18: 133.06078 | CF18: 141.73697 | CG18: 147.46657 | CH18: 143.98427 | CI18: 141.84758 | CJ18: 140.50827 | CK18: 144.52994 | CL18: 138.28895 | CM18: 143.44413 | CN18: 139.52993 | CO18: 137.96038 | CP18: 137.13739 | CQ18: 139.23376 | CR18: 131.21751 | CS18: 142.91097 | CT18: 138.88881 | CU18: 134.37093 | CV18: 129.36562 | CW18: 136.14448 | CX18: 132.52316 | CY18: 124.82682 | CZ18: 121.87127 | DA18: 109.95153 | DD18: =(SUM(CX18:DA18)/SUM(CT18:CW18)-1)*100 -> -9.2056122 | DG18: =+SUM(CT18:CW18) -> 538.76984 | DH18: =+SUM(CX18:DA18) -> 489.17278
A19: Industrie Agro-alimentaire | B19: 154.19638 | C19: 170.30919 | D19: 157.24357 | E19: 167.98252 | F19: 171.475 | G19: 165.72274 | H19: 161.8481 | I19: 162.80037 | J19: 164.68861 | K19: 176.65672 | L19: 162.77044 | M19: 169.79882 | N19: 191.07321 | O19: 191.45519 | P19: 193.74367 | Q19: 205.53557 | R19: 215.81454 | S19: 216.55807 | T19: 204.03852 | U19: 215.21767 | V19: 219.61304 | W19: 214.80837 | X19: 213.14908 | Y19: 213.71308 | Z19: 222.36308 | AA19: 207.46301 | AB19: 206.1745 | AC19: 203.99244 | AD19: 210.60113 | AE19: 210.40477 | AF19: 202.38897 | AG19: 223.78584 | AH19: 243.34361 | AI19: 224.83308 | AJ19: 212.62844 | AK19: 228.87637 | AL19: 250.81227 | AM19: 259.62074 | AN19: 228.68647 | AO19: 240.24158 | AP19: 257.97885 | AQ19: 261.85557 | AR19: 246.74912 | AS19: 259.04733 | AT19: 271.48943 | AU19: 250.87285 | AV19: 247.81239 | AW19: 263.2592 | AX19: 286.54203 | AY19: 280.61668 | AZ19: 266.93832 | BA19: 282.03619 | BB19: 299.79465 | BC19: 284.9252 | BD19: 297.26986 | BE19: 313.38497 | BF19: 320.37707 | BG19: 312.56273 | BH19: 298.08553 | BI19: 326.81324 | BJ19: 319.59694 | BK19: 313.64448 | BL19: 302.3535 | BM19: 321.25776 | BN19: 328.64269 | BO19: 314.96401 | BP19: 307.55588 | BQ19: 330.26649 | BR19: 342.07276 | BS19: 329.8275 | BT19: 325.99978 | BU19: 347.52496 | BV19: 370.34042 | BW19: 358.18407 | BX19: 330.44493 | BY19: 345.39758 | BZ19: 360.90738 | CA19: 374.85478 | CB19: 356.55797 | CC19: 339.39136 | CD19: 376.21759 | CE19: 379.05159 | CF19: 355.71781 | CG19: 354.5028 | CH19: 386.28602 | CI19: 392.73901 | CJ19: 366.40018 | CK19: 373.92097 | CL19: 412.54967 | CM19: 436.27903 | CN19: 410.45746 | CO19: 404.89469 | CP19: 435.98441 | CQ19: 449.34704 | CR19: 420.88382 | CS19: 426.97861 | CT19: 454.48102 | CU19: 467.45608 | CV19: 437.68037 | CW19: 441.45614 | CX19: 462.99987 | CY19: 482.40651 | CZ19: 453.67101 | DA19: 452.53369 | DD19: =(SUM(CX19:DA19)/SUM(CT19:CW19)-1)*100 -> 2.805964 | DE19: =+SUM(CX19:DA20)/SUM(CT19:CW20)-1 -> 0.023000093 | DG19: =+SUM(CT19:CW19) -> 1801.0736 | DH19: =+SUM(CX19:DA19) -> 1851.6111
A20: Autres Industries Manufacturières | B20: 107.32315 | C20: 105.50996 | D20: 102.51422 | E20: 106.36947 | F20: 114.27596 | G20: 119.70878 | H20: 115.77627 | I20: 124.01249 | J20: 147.37331 | K20: 143.43062 | L20: 146.7642 | M20: 163.38236 | N20: 172.0022 | O20: 165.5337 | P20: 172.7734 | Q20: 170.91555 | R20: 175.32242 | S20: 175.09502 | T20: 177.2091 | U20: 194.65737 | V20: 196.66512 | W20: 191.42283 | X20: 204.942 | Y20: 218.15501 | Z20: 211.77921 | AA20: 210.29439 | AB20: 217.15147 | AC20: 214.7676 | AD20: 224.46967 | AE20: 219.18176 | AF20: 229.98349 | AG20: 299.08328 | AH20: 259.90123 | AI20: 249.61709 | AJ20: 269.14572 | AK20: 241.63182 | AL20: 250.36781 | AM20: 216.61347 | AN20: 222.52725 | AO20: 212.7574 | AP20: 242.50852 | AQ20: 235.2302 | AR20: 238.48895 | AS20: 239.45726 | AT20: 239.70914 | AU20: 243.41319 | AV20: 246.64222 | AW20: 250.22488 | AX20: 274.40411 | AY20: 263.70897 | AZ20: 284.57722 | BA20: 293.04376 | BB20: 319.58699 | BC20: 307.41801 | BD20: 287.95896 | BE20: 276.32778 | BF20: 313.97681 | BG20: 300.72327 | BH20: 298.5991 | BI20: 311.19022 | BJ20: 315.82471 | BK20: 302.92925 | BL20: 323.04682 | BM20: 343.64236 | BN20: 348.03171 | BO20: 343.17111 | BP20: 345.70404 | BQ20: 332.30715 | BR20: 358.19336 | BS20: 352.62604 | BT20: 364.18214 | BU20: 353.21846 | BV20: 352.86933 | BW20: 360.14224 | BX20: 373.27361 | BY20: 368.05882 | BZ20: 407.72527 | CA20: 397.0024 | CB20: 356.03079 | CC20: 367.74205 | CD20: 401.22641 | CE20: 393.99508 | CF20: 368.51995 | CG20: 365.71692 | CH20: 381.55 | CI20: 376.98199 | CJ20: 363.48008 | CK20: 364.86518 | CL20: 392.43423 | CM20: 386.29278 | CN20: 380.44238 | CO20: 374.63188 | CP20: 414.6794 | CQ20: 404.62256 | CR20: 400.72527 | CS20: 382.0152 | CT20: 420.42598 | CU20: 409.77332 | CV20: 414.73306 | CW20: 397.65172 | CX20: 428.62313 | CY20: 422.50272 | CZ20: 418.41413 | DA20: 401.71106 | DD20: =(SUM(CX20:DA20)/SUM(CT20:CW20)-1)*100 -> 1.745236 | DG20: =+SUM(CT20:CW20) -> 1642.5841 | DH20: =+SUM(CX20:DA20) -> 1671.251
A21: Electricité | B21: 19.745033 | C21: 20.084178 | D21: 19.610171 | E21: 20.924513 | F21: 21.718435 | G21: 21.288268 | H21: 21.049194 | I21: 21.297573 | J21: 21.0939 | K21: 20.184598 | L21: 21.202476 | M21: 21.795434 | N21: 18.62577 | O21: 20.396511 | P21: 24.45993 | Q21: 25.780877 | R21: 23.401825 | S21: 21.730622 | T21: 22.359802 | U21: 27.130435 | V21: 26.202391 | W21: 24.232203 | X21: 26.907075 | Y21: 28.673299 | Z21: 25.933368 | AA21: 27.695842 | AB21: 27.518662 | AC21: 28.507418 | AD21: 28.604577 | AE21: 29.061578 | AF21: 29.793079 | AG21: 32.036228 | AH21: 32.832313 | AI21: 31.938557 | AJ21: 33.799237 | AK21: 35.027466 | AL21: 33.315849 | AM21: 33.632103 | AN21: 33.368503 | AO21: 33.487973 | AP21: 32.007821 | AQ21: 31.553939 | AR21: 31.536299 | AS21: 32.004597 | AT21: 29.911479 | AU21: 29.504919 | AV21: 31.989956 | AW21: 33.811003 | AX21: 33.478908 | AY21: 34.162762 | AZ21: 37.758829 | BA21: 39.816564 | BB21: 39.349483 | BC21: 40.047374 | BD21: 44.393574 | BE21: 42.688954 | BF21: 43.238594 | BG21: 45.054563 | BH21: 43.697404 | BI21: 42.40618 | BJ21: 51.195831 | BK21: 48.065082 | BL21: 45.380187 | BM21: 46.680631 | BN21: 49.481208 | BO21: 49.9657 | BP21: 49.59908 | BQ21: 42.819064 | BR21: 50.819791 | BS21: 50.86093 | BT21: 52.093785 | BU21: 54.828493 | BV21: 54.88542 | BW21: 55.464773 | BX21: 55.262897 | BY21: 57.581911 | BZ21: 51.00982 | CA21: 50.92821 | CB21: 48.587497 | CC21: 49.275774 | CD21: 51.372393 | CE21: 49.87647 | CF21: 48.123359 | CG21: 50.41721 | CH21: 60.542526 | CI21: 56.331544 | CJ21: 54.616107 | CK21: 56.199324 | CL21: 56.20994 | CM21: 56.505121 | CN21: 56.005592 | CO21: 58.376488 | CP21: 59.344447 | CQ21: 56.262263 | CR21: 57.231443 | CS21: 60.702256 | CT21: 62.478328 | CU21: 60.977963 | CV21: 59.853038 | CW21: 62.305155 | CX21: 65.132405 | CY21: 64.052829 | CZ21: 61.633043 | DA21: 64.655286 | DD21: =(SUM(CX21:DA21)/SUM(CT21:CW21)-1)*100 -> 4.0140466 | DE21: =+SUM(CX21:DA22)/SUM(CT21:CW22)-1 -> 0.032742789 | DG21: =+SUM(CT21:CW21) -> 245.61448 | DH21: =+SUM(CX21:DA21) -> 255.47356
A22: Eau et Assainissement | B22: 17.689041 | C22: 17.848983 | D22: 17.570292 | E22: 18.197101 | F22: 18.526189 | G22: 18.381634 | H22: 18.48049 | I22: 18.975475 | J22: 18.982696 | K22: 18.692556 | L22: 19.075496 | M22: 18.92212 | N22: 16.945461 | O22: 17.335794 | P22: 19.005571 | Q22: 19.624997 | R22: 18.787914 | S22: 18.35125 | T22: 19.107292 | U22: 21.998355 | V22: 22.228843 | W22: 21.69973 | X22: 23.18188 | Y22: 23.935971 | Z22: 22.222943 | AA22: 22.776752 | AB22: 22.439397 | AC22: 22.723333 | AD22: 22.620224 | AE22: 22.63381 | AF22: 22.701068 | AG22: 23.354787 | AH22: 23.269691 | AI22: 22.664657 | AJ22: 23.326662 | AK22: 23.878751 | AL22: 23.406451 | AM22: 23.756935 | AN22: 23.871325 | AO22: 24.15029 | AP22: 23.753993 | AQ22: 23.789973 | AR22: 24.016702 | AS22: 24.465396 | AT22: 23.728298 | AU22: 23.614128 | AV22: 24.679286 | AW22: 25.256987 | AX22: 24.709449 | AY22: 24.665912 | AZ22: 25.843797 | BA22: 26.397775 | BB22: 25.978565 | BC22: 26.194882 | BD22: 27.924586 | BE22: 27.583626 | BF22: 28.191398 | BG22: 26.740176 | BH22: 27.761031 | BI22: 29.867063 | BJ22: 29.099212 | BK22: 29.08521 | BL22: 29.225567 | BM22: 30.722874 | BN22: 31.335338 | BO22: 32.043694 | BP22: 32.42911 | BQ22: 33.49742 | BR22: 32.075093 | BS22: 31.581731 | BT22: 30.608981 | BU22: 32.197194 | BV22: 30.966704 | BW22: 32.407036 | BX22: 33.057365 | BY22: 33.272894 | BZ22: 32.575942 | CA22: 33.0629 | CB22: 33.482614 | CC22: 33.843528 | CD22: 33.509837 | CE22: 33.586829 | CF22: 33.364299 | CG22: 34.846033 | CH22: 33.963302 | CI22: 35.163265 | CJ22: 35.549706 | CK22: 34.452116 | CL22: 34.819344 | CM22: 34.835175 | CN22: 35.521309 | CO22: 34.056783 | CP22: 34.796321 | CQ22: 35.867955 | CR22: 37.14272 | CS22: 35.139517 | CT22: 35.987564 | CU22: 36.991029 | CV22: 37.19791 | CW22: 36.446086 | CX22: 37.133792 | CY22: 37.653274 | CZ22: 38.017786 | DA22: 36.801593 | DD22: =(SUM(CX22:DA22)/SUM(CT22:CW22)-1)*100 -> 2.0350588 | DG22: =+SUM(CT22:CW22) -> 146.62259 | DH22: =+SUM(CX22:DA22) -> 149.60644
A23: BTP | B23: 105.09153 | C23: 108.51249 | D23: 98.085382 | E23: 105.252 | F23: 107.81651 | G23: 115.72941 | H23: 112.62991 | I23: 99.726899 | J23: 113.17535 | K23: 117.30826 | L23: 104.56485 | M23: 112.96814 | N23: 137.73907 | O23: 140.52521 | P23: 146.27254 | Q23: 133.4616 | R23: 136.3284 | S23: 144.15855 | T23: 150.10203 | U23: 119.66639 | V23: 152.61042 | W23: 184.69002 | X23: 160.41255 | Y23: 153.12519 | Z23: 172.67868 | AA23: 173.17042 | AB23: 166.89546 | AC23: 155.3291 | AD23: 178.72766 | AE23: 177.38542 | AF23: 173.15473 | AG23: 175.2622 | AH23: 178.62978 | AI23: 174.5783 | AJ23: 175.0892 | AK23: 154.9754 | AL23: 162.94333 | AM23: 188.48775 | AN23: 170.65615 | AO23: 144.30916 | AP23: 164.48738 | AQ23: 165.11303 | AR23: 165.8867 | AS23: 156.78081 | AT23: 184.81452 | AU23: 184.50939 | AV23: 178.77982 | AW23: 167.91021 | AX23: 203.65691 | AY23: 175.18736 | AZ23: 197.30001 | BA23: 188.33831 | BB23: 201.07179 | BC23: 215.9889 | BD23: 207.00793 | BE23: 168.30478 | BF23: 252.09069 | BG23: 194.81221 | BH23: 217.56142 | BI23: 170.49143 | BJ23: 203.35889 | BK23: 209.8759 | BL23: 223.54495 | BM23: 240.26437 | BN23: 205.02568 | BO23: 199.24044 | BP23: 239.29754 | BQ23: 283.53442 | BR23: 253.15284 | BS23: 286.4458 | BT23: 252.92333 | BU23: 245.78702 | BV23: 270.79527 | BW23: 291.59454 | BX23: 306.63025 | BY23: 257.09094 | BZ23: 303.03741 | CA23: 314.52329 | CB23: 300.12741 | CC23: 296.5147 | CD23: 319.35646 | CE23: 326.81348 | CF23: 332.2382 | CG23: 332.05991 | CH23: 324.38808 | CI23: 346.81272 | CJ23: 360.61883 | CK23: 365.45542 | CL23: 344.5171 | CM23: 379.60127 | CN23: 349.04039 | CO23: 361.44971 | CP23: 352.4034 | CQ23: 399.20853 | CR23: 365.15874 | CS23: 378.50257 | CT23: 380.25348 | CU23: 407.18134 | CV23: 374.76816 | CW23: 394.67391 | CX23: 391.78816 | CY23: 423.12551 | CZ23: 388.80062 | DA23: 421.87046 | DD23: =(SUM(CX23:DA23)/SUM(CT23:CW23)-1)*100 -> 4.4131851 | DG23: =+SUM(CT23:CW23) -> 1556.8769 | DH23: =+SUM(CX23:DA23) -> 1625.5848
A24: Secteur tertiaire | B24: 1000.733 | C24: 1031.0029 | D24: 995.13981 | E24: 996.49318 | F24: 1031.8451 | G24: 1064.2678 | H24: 1059.7515 | I24: 1080.394 | J24: 1108.6865 | K24: 1129.5152 | L24: 1129.2492 | M24: 1137.0172 | N24: 1130.5737 | O24: 1139.9914 | P24: 1157.5675 | Q24: 1175.7224 | R24: 1189.9205 | S24: 1234.1184 | T24: 1266.9762 | U24: 1313.0132 | V24: 1329.2211 | W24: 1356.9737 | X24: 1372.5969 | Y24: 1425.2118 | Z24: 1432.5938 | AA24: 1463.9326 | AB24: 1489.2635 | AC24: 1482.9653 | AD24: 1481.2468 | AE24: 1490.0978 | AF24: 1511.4873 | AG24: 1589.1413 | AH24: 1572.8544 | AI24: 1623.6606 | AJ24: 1657.7793 | AK24: 1681.0415 | AL24: 1705.6416 | AM24: 1742.1212 | AN24: 1749.3201 | AO24: 1769.6311 | AP24: 1798.4898 | AQ24: 1824.6478 | AR24: 1833.5052 | AS24: 1847.6325 | AT24: 1862.827 | AU24: 1891.9891 | AV24: 1926.9137 | AW24: 1964.0288 | AX24: 1965.1377 | AY24: 2007.7817 | AZ24: 2055.8833 | BA24: 2100.75 | BB24: 2113.1739 | BC24: 2073.1745 | BD24: 2088.3486 | BE24: 2103.2609 | BF24: 2144.7467 | BG24: 2192.2947 | BH24: 2221.7357 | BI24: 2266.4548 | BJ24: 2318.7477 | BK24: 2309.5268 | BL24: 2331.6238 | BM24: 2421.0049 | BN24: 2386.1787 | BO24: 2407.9931 | BP24: 2439.4744 | BQ24: 2450.2399 | BR24: 2480.474 | BS24: 2501.0784 | BT24: 2530.9737 | BU24: 2600.2289 | BV24: 2594.8559 | BW24: 2631.6854 | BX24: 2654.8935 | BY24: 2712.5772 | BZ24: 2724.8359 | CA24: 2777.4071 | CB24: 2780.1839 | CC24: 2851.2964 | CD24: 2840.6728 | CE24: 2878.7848 | CF24: 2866.3544 | CG24: 2898.3325 | CH24: 2860.8338 | CI24: 2809.2379 | CJ24: 2863.2021 | CK24: 2891.5575 | CL24: 2906.8145 | CM24: 2918.9642 | CN24: 2946.8489 | CO24: 2997.1085 | CP24: 3031.552 | CQ24: 3038.1672 | CR24: 3069.9375 | CS24: 3093.2545 | CT24: 3141.6647 | CU24: 3165.6338 | CV24: 3169.3396 | CW24: 3237.0397 | CX24: 3274.038 | CY24: 3266.9258 | CZ24: 3310.4324 | DA24: 3430.1798 | DD24: =(SUM(CX24:DA24)/SUM(CT24:CW24)-1)*100 -> 4.4668282 | DG24: =+SUM(CT24:CW24) -> 12713.678 | DH24: =+SUM(CX24:DA24) -> 13281.576
A25: Commerce et réparation | B25: 198.56165 | C25: 209.27186 | D25: 196.55142 | E25: 197.68475 | F25: 205.63582 | G25: 224.24878 | H25: 210.13992 | I25: 214.12346 | J25: 223.88475 | K25: 229.14334 | L25: 221.91619 | M25: 224.23396 | N25: 216.68517 | O25: 227.49087 | P25: 231.93497 | Q25: 232.36172 | R25: 222.36242 | S25: 235.86513 | T25: 240.7024 | U25: 263.22728 | V25: 260.24501 | W25: 274.15527 | X25: 274.65296 | Y25: 294.86355 | Z25: 271.57261 | AA25: 275.42077 | AB25: 282.12417 | AC25: 279.78849 | AD25: 281.00145 | AE25: 287.35747 | AF25: 292.60372 | AG25: 333.96705 | AH25: 285.19621 | AI25: 299.16684 | AJ25: 315.61787 | AK25: 331.1625 | AL25: 348.32151 | AM25: 380.14933 | AN25: 380.29252 | AO25: 383.70411 | AP25: 385.39163 | AQ25: 390.44107 | AR25: 386.17011 | AS25: 400.54842 | AT25: 411.02352 | AU25: 433.03445 | AV25: 446.69669 | AW25: 452.79013 | AX25: 429.43819 | AY25: 434.20712 | AZ25: 448.2524 | BA25: 465.76908 | BB25: 473.06523 | BC25: 473.12507 | BD25: 464.43406 | BE25: 454.48627 | BF25: 485.46177 | BG25: 492.56112 | BH25: 494.26317 | BI25: 509.42127 | BJ25: 506.62846 | BK25: 527.12273 | BL25: 518.34039 | BM25: 565.25985 | BN25: 520.14737 | BO25: 532.12204 | BP25: 531.06626 | BQ25: 525.79979 | BR25: 530.68432 | BS25: 555.0249 | BT25: 553.25278 | BU25: 598.115 | BV25: 563.23222 | BW25: 588.70928 | BX25: 599.70664 | BY25: 584.17686 | BZ25: 599.10555 | CA25: 633.78193 | CB25: 608.86939 | CC25: 618.14728 | CD25: 613.88418 | CE25: 647.40967 | CF25: 620.21737 | CG25: 648.22408 | CH25: 610.49416 | CI25: 619.37009 | CJ25: 620.44935 | CK25: 626.44327 | CL25: 640.7057 | CM25: 645.19207 | CN25: 631.6621 | CO25: 630.96375 | CP25: 634.25653 | CQ25: 650.75677 | CR25: 667.8472 | CS25: 656.64251 | CT25: 652.23172 | CU25: 698.56563 | CV25: 667.6057 | CW25: 665.81838 | CX25: 676.47203 | CY25: 710.7254 | CZ25: 693.8077 | DA25: 701.09247 | DD25: =(SUM(CX25:DA25)/SUM(CT25:CW25)-1)*100 -> 3.6463523 | DG25: =+SUM(CT25:CW25) -> 2684.2214 | DH25: =+SUM(CX25:DA25) -> 2782.0976
A26: Transports | B26: 220.52392 | C26: 220.628 | D26: 220.84956 | E26: 221.21715 | F26: 234.74454 | G26: 240.80622 | H26: 244.80359 | I26: 246.4567 | J26: 245.8691 | K26: 245.3339 | L26: 245.03731 | M26: 245.06363 | N26: 245.46033 | O26: 247.7732 | P26: 251.87659 | Q26: 257.79683 | R26: 265.71364 | S26: 273.25444 | T26: 280.01602 | U26: 285.7408 | V26: 290.40516 | W26: 296.14303 | X26: 303.20474 | Y26: 312.06867 | Z26: 323.58598 | AA26: 331.88015 | AB26: 336.19299 | AC26: 336.08823 | AD26: 331.43608 | AE26: 329.7536 | AF26: 330.8837 | AG26: 334.79578 | AH26: 341.25862 | AI26: 345.95367 | AJ26: 348.7827 | AK26: 349.73726 | AL26: 348.94421 | AM26: 349.68225 | AN26: 351.99274 | AO26: 355.78134 | AP26: 361.03788 | AQ26: 366.06892 | AR26: 371.06761 | AS26: 376.14416 | AT26: 381.43648 | AU26: 386.2794 | AV26: 390.63277 | AW26: 394.45705 | AX26: 398.20217 | AY26: 401.08482 | AZ26: 403.32846 | BA26: 404.90641 | BB26: 406.03357 | BC26: 396.59163 | BD26: 412.47438 | BE26: 424.31044 | BF26: 423.01202 | BG26: 431.62616 | BH26: 437.01347 | BI26: 447.01319 | BJ26: 452.93709 | BK26: 451.26891 | BL26: 453.31311 | BM26: 478.04899 | BN26: 475.67341 | BO26: 499.90218 | BP26: 519.09281 | BQ26: 503.49119 | BR26: 508.22148 | BS26: 503.96183 | BT26: 507.16012 | BU26: 524.23356 | BV26: 528.72717 | BW26: 531.60896 | BX26: 524.4036 | BY26: 545.05726 | BZ26: 554.02471 | CA26: 553.23345 | CB26: 553.32273 | CC26: 563.9998 | CD26: 572.27516 | CE26: 582.10087 | CF26: 580.07751 | CG26: 582.36736 | CH26: 587.76392 | CI26: 562.22977 | CJ26: 579.95086 | CK26: 577.07076 | CL26: 580.10627 | CM26: 582.93033 | CN26: 588.91171 | CO26: 591.62405 | CP26: 594.81995 | CQ26: 615.4929 | CR26: 629.43681 | CS26: 637.29493 | CT26: 643.62308 | CU26: 632.62866 | CV26: 642.40244 | CW26: 662.57275 | CX26: 651.63419 | CY26: 655.61318 | CZ26: 659.35972 | DA26: 673.99978 | DD26: =(SUM(CX26:DA26)/SUM(CT26:CW26)-1)*100 -> 2.300454 | DE26: =+SUM(CX26:DA27)/SUM(CT26:CW27)-1 -> 0.03085146 | DG26: =+SUM(CT26:CW26) -> 2581.2269 | DH26: =+SUM(CX26:DA26) -> 2640.6069
A27: Information et communication | B27: 13.822012 | C27: 14.181944 | D27: 14.905939 | E27: 16.001912 | F27: 16.399793 | G27: 17.440469 | H27: 18.678501 | I27: 20.150486 | J27: 21.907437 | K27: 22.917429 | L27: 23.133625 | M27: 22.582872 | N27: 21.471874 | O27: 21.119925 | P27: 21.515361 | Q27: 22.688201 | R27: 24.760282 | S27: 26.781694 | T27: 28.737862 | U27: 30.571617 | V27: 32.083654 | W27: 34.314267 | X27: 37.496291 | Y27: 42.037387 | Z27: 48.740609 | AA27: 54.832863 | AB27: 59.367021 | AC27: 61.468853 | AD27: 60.960919 | AE27: 61.764405 | AF27: 63.846156 | AG27: 67.273815 | AH27: 72.583259 | AI27: 76.745544 | AJ27: 79.73711 | AK27: 81.43253 | AL27: 81.80531 | AM27: 81.84571 | AN27: 81.608178 | AO27: 81.093636 | AP27: 80.297318 | AQ27: 80.14194 | AR27: 80.641374 | AS27: 81.793138 | AT27: 83.598501 | AU27: 84.233804 | AV27: 83.651932 | AW27: 81.752828 | AX27: 78.390186 | AY27: 81.283043 | AZ27: 90.832021 | BA27: 107.12906 | BB27: 79.328393 | BC27: 84.261267 | BD27: 96.890424 | BE27: 102.60195 | BF27: 92.256646 | BG27: 92.627677 | BH27: 99.007692 | BI27: 99.071134 | BJ27: 106.41059 | BK27: 94.44603 | BL27: 104.61142 | BM27: 102.9276 | BN27: 102.85645 | BO27: 101.5914 | BP27: 102.65821 | BQ27: 103.11631 | BR27: 109.7358 | BS27: 111.51044 | BT27: 112.39276 | BU27: 114.54699 | BV27: 119.68574 | BW27: 120.11984 | BX27: 120.86768 | BY27: 118.56974 | BZ27: 120.22837 | CA27: 117.38659 | CB27: 117.2657 | CC27: 121.65118 | CD27: 122.10628 | CE27: 114.73017 | CF27: 120.87884 | CG27: 126.49314 | CH27: 127.87731 | CI27: 116.48037 | CJ27: 125.23121 | CK27: 138.70567 | CL27: 130.72879 | CM27: 125.04222 | CN27: 125.30644 | CO27: 140.34726 | CP27: 144.62994 | CQ27: 133.54592 | CR27: 134.93214 | CS27: 145.29471 | CT27: 160.34994 | CU27: 148.74565 | CV27: 140.83426 | CW27: 163.29175 | CX27: 170.91634 | CY27: 156.44789 | CZ27: 148.25027 | DA27: 176.78056 | DD27: =(SUM(CX27:DA27)/SUM(CT27:CW27)-1)*100 -> 6.3881416 | DG27: =+SUM(CT27:CW27) -> 613.2216 | DH27: =+SUM(CX27:DA27) -> 652.39506
A28: Hébergement et restauration | B28: 78.956347 | C28: 79.586068 | D28: 80.857531 | E28: 82.79524 | F28: 84.046911 | G28: 85.462409 | H28: 86.38829 | I28: 86.807468 | J28: 86.822272 | K28: 87.622234 | L28: 89.301556 | M28: 91.924243 | N28: 95.835975 | O28: 99.212801 | P28: 102.03925 | Q28: 104.20966 | R28: 105.64485 | S28: 107.31608 | T28: 109.29164 | U28: 111.6458 | V28: 114.50232 | W28: 116.96381 | X28: 118.96505 | Y28: 120.42963 | Z28: 121.13465 | AA28: 123.02395 | AB28: 126.04697 | AC28: 130.07647 | AD28: 134.91383 | AE28: 138.46147 | AF28: 141.11992 | AG28: 143.02735 | AH28: 144.22066 | AI28: 145.42098 | AJ28: 146.5725 | AK28: 147.66455 | AL28: 148.7448 | AM28: 150.22068 | AN28: 152.08136 | AO28: 154.30079 | AP28: 156.79883 | AQ28: 159.32071 | AR28: 161.90014 | AS28: 164.56105 | AT28: 166.99475 | AU28: 170.28776 | AV28: 174.37688 | AW28: 179.31084 | AX28: 185.94962 | AY28: 189.31849 | AZ28: 189.6516 | BA28: 186.65445 | BB28: 205.52533 | BC28: 205.0285 | BD28: 201.83692 | BE28: 207.86134 | BF28: 211.0249 | BG28: 215.63738 | BH28: 207.50827 | BI28: 215.77542 | BJ28: 221.38279 | BK28: 223.80566 | BL28: 219.47991 | BM28: 232.62287 | BN28: 238.48521 | BO28: 227.74428 | BP28: 228.24443 | BQ28: 236.36163 | BR28: 236.93578 | BS28: 240.03922 | BT28: 243.79243 | BU28: 255.87957 | BV28: 250.78882 | BW28: 255.51875 | BX28: 260.57681 | BY28: 270.76263 | BZ28: 269.46826 | CA28: 268.95672 | CB28: 270.15414 | CC28: 283.36034 | CD28: 286.10826 | CE28: 282.51891 | CF28: 283.05058 | CG28: 285.97323 | CH28: 271.43856 | CI28: 248.80446 | CJ28: 254.24688 | CK28: 267.05363 | CL28: 281.94426 | CM28: 275.74621 | CN28: 285.54066 | CO28: 299.20666 | CP28: 298.77166 | CQ28: 294.76222 | CR28: 301.60043 | CS28: 294.32932 | CT28: 309.38343 | CU28: 304.5794 | CV28: 316.96041 | CW28: 315.60697 | CX28: 320.14997 | CY28: 315.04166 | CZ28: 325.82229 | DA28: 352.86822 | DD28: =(SUM(CX28:DA28)/SUM(CT28:CW28)-1)*100 -> 5.403152 | DE28: =+SUM(CX28:DA28,CX25:DA25)/SUM(CT28:CW28,CT25:CW25)-1 -> 0.042034732 | DG28: =+SUM(CT28:CW28) -> 1246.5302 | DH28: =+SUM(CX28:DA28) -> 1313.8821
A29: Services financiers | B29: 34.08435 | C29: 35.228478 | D29: 35.074681 | E29: 36.764878 | F29: 36.264135 | G29: 36.472969 | H29: 36.115392 | I29: 37.185271 | J29: 34.108263 | K29: 33.83703 | L29: 35.278548 | M29: 37.051996 | N29: 37.555355 | O29: 39.472446 | P29: 44.147741 | Q29: 47.71562 | R29: 49.194949 | S29: 51.247361 | T29: 51.736259 | U29: 52.186046 | V29: 49.971923 | W29: 46.977822 | X29: 46.184043 | Y29: 47.83229 | Z29: 52.512875 | AA29: 52.299429 | AB29: 52.465602 | AC29: 51.139716 | AD29: 47.495537 | AE29: 44.694515 | AF29: 42.953689 | AG29: 46.329297 | AH29: 47.896646 | AI29: 49.749848 | AJ29: 53.213754 | AK29: 56.810544 | AL29: 60.678106 | AM29: 61.19057 | AN29: 61.671137 | AO29: 67.082877 | AP29: 65.381474 | AQ29: 63.689438 | AR29: 63.869463 | AS29: 61.394406 | AT29: 63.796068 | AU29: 63.599583 | AV29: 66.656107 | AW29: 77.142504 | AX29: 87.446628 | AY29: 99.725175 | AZ29: 105.07505 | BA29: 100.75916 | BB29: 85.888502 | BC29: 78.807971 | BD29: 74.289246 | BE29: 71.466977 | BF29: 77.434535 | BG29: 82.019977 | BH29: 86.72328 | BI29: 88.911458 | BJ29: 86.903006 | BK29: 87.309689 | BL29: 85.501315 | BM29: 87.224238 | BN29: 87.052132 | BO29: 90.41929 | BP29: 96.365774 | BQ29: 99.955799 | BR29: 98.441032 | BS29: 98.554794 | BT29: 101.16937 | BU29: 103.73281 | BV29: 103.95756 | BW29: 104.67404 | BX29: 105.40686 | BY29: 107.93954 | BZ29: 113.12307 | CA29: 118.72577 | CB29: 122.79461 | CC29: 125.4363 | CD29: 124.69389 | CE29: 123.88904 | CF29: 122.63272 | CG29: 124.30292 | CH29: 127.51399 | CI29: 127.04792 | CJ29: 125.95799 | CK29: 128.68039 | CL29: 137.91744 | CM29: 140.82695 | CN29: 138.15636 | CO29: 139.21616 | CP29: 155.27155 | CQ29: 150.34427 | CR29: 142.29892 | CS29: 143.80311 | CT29: 163.7922 | CU29: 162.07846 | CV29: 154.95471 | CW29: 160.29643 | CX29: 183.36761 | CY29: 176.7805 | CZ29: 167.34172 | DA29: 178.13697 | DD29: =(SUM(CX29:DA29)/SUM(CT29:CW29)-1)*100 -> 10.061268 | DG29: =+SUM(CT29:CW29) -> 641.12181 | DH29: =+SUM(CX29:DA29) -> 705.6268
A30: Administrations publiques | B30: 183.20541 | C30: 196.07203 | D30: 178.56968 | E30: 175.6245 | F30: 184.33198 | G30: 190.63943 | H30: 191.46952 | I30: 194.18973 | J30: 202.17658 | K30: 206.82881 | L30: 208.74903 | M30: 211.87832 | N30: 207.52579 | O30: 203.03338 | P30: 203.23389 | Q30: 205.44717 | R30: 210.16681 | S30: 218.16214 | T30: 226.92103 | U30: 234.96484 | V30: 239.97178 | W30: 238.82555 | X30: 234.69498 | Y30: 237.45015 | Z30: 240.61476 | AA30: 243.81247 | AB30: 248.63105 | AC30: 247.36222 | AD30: 250.66902 | AE30: 257.56992 | AF30: 265.30053 | AG30: 273.26455 | AH30: 285.63323 | AI30: 297.88609 | AJ30: 301.11934 | AK30: 307.82999 | AL30: 314.58893 | AM30: 322.20262 | AN30: 329.86377 | AO30: 334.8976 | AP30: 343.46889 | AQ30: 353.67072 | AR30: 359.62448 | AS30: 360.79478 | AT30: 360.91857 | AU30: 365.54839 | AV30: 372.77432 | AW30: 375.90056 | AX30: 384.54341 | AY30: 391.48137 | AZ30: 400.16492 | BA30: 418.0788 | BB30: 425.20456 | BC30: 419.06775 | BD30: 418.66149 | BE30: 416.94834 | BF30: 422.3034 | BG30: 441.79483 | BH30: 451.07201 | BI30: 463.78526 | BJ30: 473.35304 | BK30: 478.68344 | BL30: 494.15098 | BM30: 498.86569 | BN30: 496.2644 | BO30: 483.22199 | BP30: 477.23548 | BQ30: 490.47738 | BR30: 505.44907 | BS30: 504.00365 | BT30: 507.86857 | BU30: 497.08371 | BV30: 525.5221 | BW30: 516.64017 | BX30: 514.31132 | BY30: 534.43941 | BZ30: 531.40421 | CA30: 536.66996 | CB30: 543.93152 | CC30: 557.36314 | CD30: 557.634 | CE30: 560.08177 | CF30: 561.28194 | CG30: 547.49394 | CH30: 564.13151 | CI30: 567.79691 | CJ30: 571.69628 | CK30: 567.85448 | CL30: 569.18748 | CM30: 582.82243 | CN30: 591.08536 | CO30: 590.87334 | CP30: 610.92337 | CQ30: 604.94784 | CR30: 592.54939 | CS30: 606.93745 | CT30: 613.91556 | CU30: 617.09429 | CV30: 625.61251 | CW30: 634.76606 | CX30: 651.69173 | CY30: 625.30132 | CZ30: 664.97341 | DA30: 690.45309 | DD30: =(SUM(CX30:DA30)/SUM(CT30:CW30)-1)*100 -> 5.6607447 | DG30: =+SUM(CT30:CW30) -> 2491.3884 | DH30: =+SUM(CX30:DA30) -> 2632.4196
A31: Autres services marchands | B31: 307.69442 | C31: 311.246 | D31: 302.79627 | E31: 299.47648 | F31: 305.7686 | G31: 304.36572 | H31: 305.46797 | I31: 313.55003 | J31: 321.66642 | K31: 329.55632 | L31: 330.29349 | M31: 329.36406 | N31: 333.12046 | O31: 330.34968 | P31: 332.61316 | Q31: 335.58638 | R31: 340.62457 | S31: 348.86588 | T31: 354.90725 | U31: 358.03491 | V31: 363.30141 | W31: 367.69832 | X31: 372.37929 | Y31: 381.76016 | Z31: 384.51867 | AA31: 388.40849 | AB31: 386.49441 | AC31: 375.79563 | AD31: 375.7223 | AE31: 369.83547 | AF31: 372.60744 | AG31: 387.09699 | AH31: 393.92833 | AI31: 405.78685 | AJ31: 409.30349 | AK31: 402.93981 | AL31: 398.90054 | AM31: 392.09054 | AN31: 387.90869 | AO31: 390.042 | AP31: 403.54631 | AQ31: 408.97351 | AR31: 408.59193 | AS31: 400.1109 | AT31: 392.82188 | AU31: 386.71793 | AV31: 390.28253 | AW31: 401.897 | AX31: 402.67303 | AY31: 412.62788 | AZ31: 419.23989 | BA31: 415.90185 | BB31: 439.22687 | BC31: 416.14986 | BD31: 418.15642 | BE31: 423.01666 | BF31: 432.16425 | BG31: 436.21924 | BH31: 445.92868 | BI31: 443.38081 | BJ31: 469.66804 | BK31: 448.93439 | BL31: 457.14064 | BM31: 458.90126 | BN31: 466.35437 | BO31: 473.10303 | BP31: 484.04017 | BQ31: 490.55599 | BR31: 491.27659 | BS31: 488.51407 | BT31: 505.15095 | BU31: 506.0234 | BV31: 502.9423 | BW31: 514.41432 | BX31: 529.62059 | BY31: 551.63179 | BZ31: 537.52459 | CA31: 549.34103 | CB31: 563.65208 | CC31: 580.91613 | CD31: 563.17254 | CE31: 568.32797 | CF31: 577.73583 | CG31: 584.29369 | CH31: 572.62257 | CI31: 569.20601 | CJ31: 587.72716 | CK31: 587.53838 | CL31: 567.46325 | CM31: 568.06229 | CN31: 586.59979 | CO31: 604.92352 | CP31: 594.8591 | CQ31: 589.32937 | CR31: 601.25663 | CS31: 610.21963 | CT31: 602.82132 | CU31: 602.33017 | CV31: 621.62047 | CW31: 639.61068 | CX31: 628.90781 | CY31: 630.77777 | CZ31: 653.45823 | DA31: 663.83099 | DD31: =(SUM(CX31:DA31)/SUM(CT31:CW31)-1)*100 -> 4.483982 | DE31: =+SUM(CX31:DA31,CX29:DA29)/SUM(CT31:CW31,CT29:CW29)-1 -> 0.056346545 | DG31: =+SUM(CT31:CW31) -> 2466.3826 | DH31: =+SUM(CX31:DA31) -> 2576.9748
A32: TOTAL DES VA | B32: 2247.9274 | C32: 2374.3958 | D32: 2243.5127 | E32: 2239.3044 | F32: 2292.7577 | G32: 2424.5727 | H32: 2361.7008 | I32: 2354.8112 | J32: 2417.1598 | K32: 2518.7988 | L32: 2450.0427 | M32: 2459.3937 | N32: 2518.8231 | O32: 2596.241 | P32: 2621.8933 | Q32: 2630.2511 | R32: 2592.6275 | S32: 2719.9565 | T32: 2758.9568 | U32: 2841.9243 | V32: 2867.9604 | W32: 3003.7102 | X32: 2979.7888 | Y32: 3000.1325 | Z32: 2970.5789 | AA32: 3022.4642 | AB32: 3055.6512 | AC32: 3020.6214 | AD32: 2990.1211 | AE32: 3076.2553 | AF32: 3112.0667 | AG32: 3278.2215 | AH32: 3168.3346 | AI32: 3248.8355 | AJ32: 3298.1312 | AK32: 3284.9558 | AL32: 3333.3585 | AM32: 3437.8673 | AN32: 3370.2575 | AO32: 3390.8743 | AP32: 3421.8813 | AQ32: 3485.1232 | AR32: 3487.31 | AS32: 3513.7623 | AT32: 3497.6293 | AU32: 3580.2561 | AV32: 3602.7359 | AW32: 3641.3053 | AX32: 3620.4702 | AY32: 3668.481 | AZ32: 3745.2026 | BA32: 3794.8503 | BB32: 3864.9812 | BC32: 3889.9921 | BD32: 3877.8612 | BE32: 3803.6818 | BF32: 3994.5245 | BG32: 4012.1541 | BH32: 4062.7613 | BI32: 4062.8331 | BJ32: 4124.7932 | BK32: 4185.1966 | BL32: 4215.9965 | BM32: 4376.4696 | BN32: 4294.1151 | BO32: 4397.2366 | BP32: 4459.9643 | BQ32: 4507.8041 | BR32: 4481.9019 | BS32: 4626.2349 | BT32: 4598.2094 | BU32: 4697.3268 | BV32: 4680.7043 | BW32: 4802.8902 | BX32: 4799.455 | BY32: 4757.0405 | BZ32: 4872.9667 | CA32: 5045.855 | CB32: 4936.4256 | CC32: 5001.9419 | CD32: 5019.8542 | CE32: 5221.0946 | CF32: 5139.0783 | CG32: 5160.6139 | CH32: 5104.8635 | CI32: 5136.4508 | CJ32: 5176.9865 | CK32: 5265.5156 | CL32: 5251.7394 | CM32: 5379.5538 | CN32: 5333.3091 | CO32: 5388.8871 | CP32: 5447.0449 | CQ32: 5621.7667 | CR32: 5530.8848 | CS32: 5539.3261 | CT32: 5590.8621 | CU32: 5788.0711 | CV32: 5698.5398 | CW32: 5756.6957 | CX32: 5809.9585 | CY32: 5914.6913 | CZ32: 5884.9863 | DA32: 5995.9106 | DD32: =(SUM(CX32:DA32)/SUM(CT32:CW32)-1)*100 -> 3.3781744 | DG32: =+SUM(CT32:CW32) -> 22834.169 | DH32: =+SUM(CX32:DA32) -> 23605.547
A33: Impôts et taxes | B33: 170.68021 | C33: 191.23548 | D33: 177.30841 | E33: 162.20377 | F33: 184.6676 | G33: 188.98213 | H33: 184.23334 | I33: 188.65428 | J33: 197.91337 | K33: 197.37791 | L33: 191.18297 | M33: 189.21922 | N33: 185.17697 | O33: 182.71993 | P33: 188.22865 | Q33: 187.79195 | R33: 197.67997 | S33: 203.6706 | T33: 202.13448 | U33: 196.1242 | V33: 184.85725 | W33: 178.87107 | X33: 171.06174 | Y33: 182.73444 | Z33: 186.28284 | AA33: 190.61139 | AB33: 197.10363 | AC33: 198.90529 | AD33: 213.35443 | AE33: 207.84575 | AF33: 207.96375 | AG33: 233.54122 | AH33: 228.27443 | AI33: 225.37571 | AJ33: 225.35697 | AK33: 217.30204 | AL33: 204.55824 | AM33: 204.63939 | AN33: 196.11856 | AO33: 186.6694 | AP33: 198.58392 | AQ33: 197.84239 | AR33: 196.13644 | AS33: 198.44197 | AT33: 205.16846 | AU33: 200.52122 | AV33: 201.55764 | AW33: 197.94372 | AX33: 201.60943 | AY33: 192.55225 | AZ33: 203.13422 | BA33: 215.62604 | BB33: 229.58491 | BC33: 228.24945 | BD33: 232.32798 | BE33: 230.80856 | BF33: 254.66019 | BG33: 250.9825 | BH33: 262.13357 | BI33: 270.2101 | BJ33: 289.74347 | BK33: 296.4359 | BL33: 307.22063 | BM33: 352.02627 | BN33: 353.74865 | BO33: 367.51821 | BP33: 389.4267 | BQ33: 401.1025 | BR33: 395.09131 | BS33: 409.63455 | BT33: 404.37063 | BU33: 425.79651 | BV33: 418.46386 | BW33: 430.02948 | BX33: 437.98779 | BY33: 421.59587 | BZ33: 426.31818 | CA33: 434.94684 | CB33: 423.84603 | CC33: 430.17421 | CD33: 440.71911 | CE33: 448.61737 | CF33: 439.20719 | CG33: 452.58571 | CH33: 432.68315 | CI33: 420.35611 | CJ33: 423.72294 | CK33: 423.47701 | CL33: 441.78801 | CM33: 447.29152 | CN33: 441.88511 | CO33: 446.65752 | CP33: 453.56239 | CQ33: 454.16956 | CR33: 473.83476 | CS33: 475.04916 | CT33: 482.85612 | CU33: 496.96586 | CV33: 477.33227 | CW33: 486.78419 | CX33: 499.43071 | CY33: 521.08374 | CZ33: 498.93884 | DA33: 512.59886 | DD33: =(SUM(CX33:DA33)/SUM(CT33:CW33)-1)*100 -> 4.5327411 | DG33: =+SUM(CT33:CW33) -> 1943.9384 | DH33: =+SUM(CX33:DA33) -> 2032.0521
A34: PIB | B34: 2426.6748 | C34: 2575.3104 | D34: 2429.6087 | E34: 2408.7174 | F34: 2486.7724 | G34: 2622.773 | H34: 2554.9293 | I34: 2552.9587 | J34: 2625.5328 | K34: 2725.7868 | L34: 2650.4559 | M34: 2657.4863 | N34: 2711.0631 | O34: 2784.5816 | P34: 2816.5523 | Q34: 2824.2828 | R34: 2799.4747 | S34: 2932.3417 | T34: 2968.8488 | U34: 3043.104 | V34: 3055.7096 | W34: 3182.5931 | X34: 3149.5551 | Y34: 3183.7134 | Z34: 3158.5419 | AA34: 3214.9629 | AB34: 3255.3907 | AC34: 3222.8043 | AD34: 3209.9098 | AE34: 3288.5437 | AF34: 3324.0949 | AG34: 3518.7478 | AH34: 3403.9293 | AI34: 3480.0033 | AJ34: 3528.6905 | AK34: 3506.0295 | AL34: 3537.7893 | AM34: 3640.9237 | AN34: 3563.7935 | AO34: 3572.5044 | AP34: 3617.7201 | AQ34: 3679.1597 | AR34: 3679.2191 | AS34: 3708.1322 | AT34: 3700.3285 | AU34: 3776.326 | AV34: 3799.7692 | AW34: 3833.5068 | AX34: 3817.399 | AY34: 3854.2562 | AZ34: 3942.5548 | BA34: 4006.3171 | BB34: 4090.8645 | BC34: 4114.2172 | BD34: 4106.6848 | BE34: 4031.3628 | BF34: 4246.4 | BG34: 4260.0661 | BH34: 4322.2405 | BI34: 4330.8485 | BJ34: 4412.4757 | BK34: 4479.6093 | BL34: 4521.418 | BM34: 4727.5475 | BN34: 4647.0709 | BO34: 4764.076 | BP34: 4849.1232 | BQ34: 4908.8253 | BR34: 4876.8954 | BS34: 5035.8267 | BT34: 5002.4485 | BU34: 5123.3954 | BV34: 5099.1682 | BW34: 5232.9196 | BX34: 5237.4428 | BY34: 5178.6363 | BZ34: 5298.693 | CA34: 5479.8341 | CB34: 5359.2337 | CC34: 5431.1028 | CD34: 5460.0354 | CE34: 5668.6365 | CF34: 5577.1022 | CG34: 5612.6206 | CH34: 5536.2536 | CI34: 5554.8226 | CJ34: 5598.7117 | CK34: 5686.6196 | CL34: 5691.7246 | CM34: 5824.9263 | CN34: 5773.2701 | CO34: 5833.6028 | CP34: 5898.6706 | CQ34: 6074.0836 | CR34: 6002.6136 | CS34: 6012.2611 | CT34: 6070.2109 | CU34: 6281.7159 | CV34: 6173.8695 | CW34: 6240.9711 | CX34: 6305.9753 | CY34: 6430.9098 | CZ34: 6381.2297 | DA34: 6505.2957 | DC34: PIB | DD34: =(SUM(CX34:DA34)/SUM(CT34:CW34)-1)*100 -> 3.45884 | DG34: =+SUM(CT34:CW34) -> 24766.768 | DH34: =+SUM(CX34:DA34) -> 25623.41
F36: =F34/B34-1 -> 0.024765389 | G36: =G34/C34-1 -> 0.018429831 | H36: =H34/D34-1 -> 0.051580537 | I36: =I34/E34-1 -> 0.059883006 | J36: =J34/F34-1 -> 0.055799404 | K36: =K34/G34-1 -> 0.039276682 | L36: =L34/H34-1 -> 0.037389158 | M36: =M34/I34-1 -> 0.040943715 | ... DA36: =DA34/CW34-1 -> 0.042353114 | DC36: Pib Hors Petrole | DD36: 3.7122403
CU37: =+SUM(CT34:CU34)/SUM(CP34:CQ34)-1 -> 0.03166963 | CW37: =+SUM(CT34:CW34)/SUM(CP34:CS34)-1 -> 0.032480853
A38: Emplois PIB trimestriel en volume chainé (reference 2016), Données brutes
A40: Libellé | B40: =B10 -> T1_1999 | C40: =C10 -> T2_1999 | D40: =D10 -> T3_1999 | E40: =E10 -> T4_1999 | F40: =F10 -> T1_2000 | G40: =G10 -> T2_2000 | H40: =H10 -> T3_2000 | I40: =I10 -> T4_2000 | ... BQ40: =BQ10 -> T4_2015 | BR40: T1_2016 | BS40: T2_2016 | BT40: T3_2016 | BU40: T4_2016 | BV40: T1_2017 | BW40: T2_2017 | BX40: T3_2017 | BY40: T4_2017 | BZ40: T1_2018 | CA40: T2_2018 | CB40: T3_2018 | CC40: T4_2018 | CD40: T1_2019 | CE40: T2_2019 | CF40: T3_2019 | CG40: T4_2019 | CH40: T1_2020 | CI40: T2_2020 | CJ40: T3_2020 | CK40: T4_2020 | CL40: T1_2021 | CM40: T2_2021 | CN40: T3_2021 | CO40: T4_2021 | CP40: T1_2022 | CQ40: T2_2022 | CR40: T3_2022 | CS40: T4_2022 | CT40: T1_2023 | CU40: T2_2023 | CV40: T3_2023 | CW40: T4_2023 | CX40: =CX10 -> T1_2024 | CY40: =CY10 -> T2_2024 | CZ40: =CZ10 -> T3_2024 | DA40: =DA10 -> T4_2024
A41: CF | B41: 1825.7287 | C41: 1953.1799 | D41: 1860.8743 | E41: 1847.1757 | F41: 1931.5388 | G41: 2038.5496 | H41: 2004.0316 | I41: 2013.8714 | J41: 2043.3614 | K41: 2169.566 | L41: 2129.0919 | M41: 2101.7615 | N41: 2133.5837 | O41: 2189.3619 | P41: 2197.0125 | Q41: 2207.2123 | R41: 2236.4141 | S41: 2362.344 | T41: 2360.6812 | U41: 2379.1127 | V41: 2393.7842 | W41: 2464.2291 | X41: 2481.545 | Y41: 2525.7605 | Z41: 2518.4883 | AA41: 2603.1313 | AB41: 2649.3494 | AC41: 2598.7372 | AD41: 2609.9016 | AE41: 2653.0352 | AF41: 2646.5771 | AG41: 2750.5611 | AH41: 2700.067 | AI41: 2757.3739 | AJ41: 2781.615 | AK41: 2786.8559 | AL41: 2869.8627 | AM41: 2993.9911 | AN41: 2926.7485 | AO41: 2886.976 | AP41: 3010.1885 | AQ41: 3106.6824 | AR41: 3069.9105 | AS41: 3058.9372 | AT41: 3058.4958 | AU41: 3135.1356 | AV41: 3163.9653 | AW41: 3171.8653 | AX41: 3167.5362 | AY41: 3261.3292 | AZ41: 3294.0577 | BA41: 3262.484 | BB41: 3382.8169 | BC41: 3438.9639 | BD41: 3450.4062 | BE41: 3399.0741 | BF41: 3476.5331 | BG41: 3642.2099 | BH41: 3662.2595 | BI41: 3675.6928 | BJ41: 3717.471 | BK41: 3808.6621 | BL41: 3846.2655 | BM41: 3883.4368 | BN41: 3947.092 | BO41: 4122.6241 | BP41: 4131.9638 | BQ41: 4010.4186 | BR41: 4048.5702 | BS41: 4191.1685 | BT41: 4211.5064 | BU41: 4164.8579 | BV41: 4132.8162 | BW41: 4361.9225 | BX41: 4366.9487 | BY41: 4422.8986 | BZ41: 4386.7369 | CA41: 4604.6595 | CB41: 4584.1179 | CC41: 4581.2088 | CD41: 4632.9138 | CE41: 4832.3313 | CF41: 4783.1858 | CG41: 4636.9576 | CH41: 4639.5207 | CI41: 4795.8754 | CJ41: 4824.4086 | CK41: 4696.5451 | CL41: 4750.3743 | CM41: 5035.0381 | CN41: 5024.8777 | CO41: 4986.0838 | CP41: 4942.8267 | CQ41: 5124.921 | CR41: 5231.3499 | CS41: 5067.9934 | CT41: 5096.59 | CU41: 5369.5153 | CV41: 5331.6975 | CW41: 5274.8985 | CX41: 5170.5713 | CY41: 5572.9968 | CZ41: 5542.4208 | DA41: 5528.3969 | DD41: =(SUM(CX41:DA41)/SUM(CT41:CW41)-1)*100 -> 3.5196458 | DE41: =+DE42+DE43 -> 2.973135
A42: CF_PRIVEE | B42: 1587.8604 | C42: 1699.4114 | D42: 1631.6919 | E42: 1622.1219 | F42: 1693.7063 | G42: 1794.5104 | H42: 1759.092 | I42: 1765.2111 | J42: 1783.5362 | K42: 1903.9276 | L42: 1859.3038 | M42: 1826.1967 | N42: 1864.3073 | O42: 1926.5961 | P42: 1933.1682 | Q42: 1939.5312 | R42: 1964.2838 | S42: 2080.7447 | T42: 2067.5939 | U42: 2076.899 | V42: 2088.2656 | W42: 2163.4917 | X42: 2187.9626 | Y42: 2229.0831 | Z42: 2217.5896 | AA42: 2298.0406 | AB42: 2337.1124 | AC42: 2286.4436 | AD42: 2303.5825 | AE42: 2337.3844 | AF42: 2320.3615 | AG42: 2415.6056 | AH42: 2350.7859 | AI42: 2394.3274 | AJ42: 2415.995 | AK42: 2414.3864 | AL42: 2480.9802 | AM42: 2597.314 | AN42: 2524.422 | AO42: 2482.4116 | AP42: 2599.042 | AQ42: 2684.8574 | AR42: 2640.0148 | AS42: 2623.4274 | AT42: 2616.9962 | AU42: 2683.9935 | AV42: 2704.1597 | AW42: 2712.2917 | AX42: 2700.2859 | AY42: 2790.7001 | AZ42: 2816.5239 | BA42: 2766.2397 | BB42: 2872.6847 | BC42: 2934.0762 | BD42: 2944.6096 | BE42: 2894.4842 | BF42: 2962.2803 | BG42: 3106.2102 | BH42: 3120.0619 | BI42: 3126.2456 | BJ42: 3169.0912 | BK42: 3259.2737 | BL42: 3279.9034 | BM42: 3307.4603 | BN42: 3357.7048 | BO42: 3539.6178 | BP42: 3549.3657 | BQ42: 3407.3375 | BR42: 3438.1698 | BS42: 3580.3015 | BT42: 3597.1988 | BU42: 3570.8879 | BV42: 3514.3037 | BW42: 3761.8436 | BX42: 3773.0208 | BY42: 3804.4479 | BZ42: 3762.9675 | CA42: 3976.1401 | CB42: 3947.4606 | CC42: 3927.9553 | CD42: 3969.264 | CE42: 4163.7918 | CF42: 4117.2115 | CG42: 3997.0428 | CH42: 3969.0221 | CI42: 4128.3899 | CJ42: 4156.661 | CK42: 4034.759 | CL42: 4070.6813 | CM42: 4344.3213 | CN42: 4334.1556 | CO42: 4310.3374 | CP42: 4276.5023 | CQ42: 4479.0817 | CR42: 4606.6035 | CS42: 4429.1332 | CT42: 4446.1618 | CU42: 4713.0999 | CV42: 4664.9369 | CW42: 4598.2029 | CX42: 4459.8555 | CY42: 4884.6872 | CZ42: 4848.8831 | DA42: 4827.3597 | DD42: =(SUM(CX42:DA42)/SUM(CT42:CW42)-1)*100 -> 3.2481333 | DE42: =+DD42*SUM(CT91:CW91)/SUM(CT$102:CW$102) -> 2.3999837
A43: CF_PUBLIQUE | B43: 234.81236 | C43: 250.56897 | D43: 227.38115 | E43: 223.5077 | F43: 235.96819 | G43: 242.7618 | H43: 243.1854 | I43: 246.6482 | J43: 257.01632 | K43: 263.69162 | L43: 266.95629 | M43: 271.83439 | N43: 266.58632 | O43: 261.77622 | P43: 262.83029 | Q43: 266.32104 | R43: 270.62539 | S43: 280.65908 | T43: 290.85134 | U43: 299.20167 | V43: 302.41953 | W43: 298.96032 | X43: 292.74395 | Y43: 296.0432 | Z43: 299.80176 | AA43: 304.63762 | AB43: 311.57712 | AC43: 310.95394 | AD43: 305.78618 | AE43: 314.65433 | AF43: 324.01459 | AG43: 333.10223 | AH43: 347.27689 | AI43: 360.84533 | AJ43: 363.4145 | AK43: 370.11018 | AL43: 387.26563 | AM43: 394.46138 | AN43: 401.01381 | AO43: 403.72108 | AP43: 409.62072 | AQ43: 420.1817 | AR43: 428.62999 | AS43: 434.44475 | AT43: 440.87413 | AU43: 450.43964 | AV43: 459.29176 | AW43: 458.99877 | AX43: 467.35278 | AY43: 469.92007 | AZ43: 476.98765 | BA43: 497.51731 | BB43: 510.5891 | BC43: 504.8711 | BD43: 505.75285 | BE43: 504.76849 | BF43: 514.38137 | BG43: 536.07322 | BH43: 542.34354 | BI43: 549.71026 | BJ43: 548.50331 | BK43: 549.34086 | BL43: 566.47571 | BM43: 576.14922 | BN43: 589.72893 | BO43: 582.5394 | BP43: 582.08639 | BQ43: 603.53548 | BR43: 610.67156 | BS43: 610.83835 | BT43: 614.28575 | BU43: 593.74934 | BV43: 618.51246 | BW43: 600.07898 | BX43: 593.9279 | BY43: 618.45066 | BZ43: 623.76957 | CA43: 628.5189 | CB43: 636.65702 | CC43: 653.25375 | CD43: 663.33115 | CE43: 668.7108 | CF43: 666.05383 | CG43: 640.11307 | CH43: 669.97486 | CI43: 667.57924 | CJ43: 667.93393 | CK43: 661.6764 | CL43: 679.35259 | CM43: 691.02259 | CN43: 690.99575 | CO43: 676.23441 | CP43: 666.8474 | CQ43: 647.28441 | CR43: 626.91335 | CS43: 640.28532 | CT43: 651.86883 | CU43: 657.69139 | CV43: 668.15302 | CW43: 678.21609 | CX43: 712.48438 | CY43: 689.71755 | CZ43: 694.99569 | DA43: 702.55084 | DD43: =(SUM(CX43:DA43)/SUM(CT43:CW43)-1)*100 -> 5.4150209 | DE43: =+DD43*SUM(CT92:CW92)/SUM(CT$102:CW$102) -> 0.57315134
A44: INVESTISSEMENT | B44: 373.26308 | C44: 380.63908 | D44: 353.78457 | E44: 371.12905 | F44: 389.75671 | G44: 419.24635 | H44: 410.83192 | I44: 398.94786 | J44: 440.56721 | K44: 446.48251 | L44: 434.17782 | M44: 435.52215 | N44: 458.64275 | O44: 469.05871 | P44: 471.91078 | Q44: 422.53282 | R44: 410.00878 | S44: 434.83409 | T44: 460.64055 | U44: 410.4555 | V44: 452.41978 | W44: 529.36093 | X44: 453.89996 | Y44: 484.28337 | Z44: 494.82665 | AA44: 487.59014 | AB44: 486.6882 | AC44: 469.15035 | AD44: 498.24875 | AE44: 496.43038 | AF44: 490.79061 | AG44: 505.34945 | AH44: 522.51442 | AI44: 549.33918 | AJ44: 557.16514 | AK44: 553.78504 | AL44: 575.3366 | AM44: 635.40241 | AN44: 593.98952 | AO44: 562.48727 | AP44: 602.74733 | AQ44: 586.05474 | AR44: 586.64672 | AS44: 592.79851 | AT44: 613.92274 | AU44: 656.95673 | AV44: 675.01385 | AW44: 629.30089 | AX44: 678.7875 | AY44: 627.15593 | AZ44: 687.57896 | BA44: 687.21901 | BB44: 718.75963 | BC44: 723.81026 | BD44: 710.2006 | BE44: 646.60098 | BF44: 836.98265 | BG44: 752.64129 | BH44: 817.72973 | BI44: 720.88115 | BJ44: 874.90607 | BK44: 881.63308 | BL44: 860.06651 | BM44: 937.04438 | BN44: 822.65386 | BO44: 836.57142 | BP44: 927.0751 | BQ44: 1032.2201 | BR44: 926.07769 | BS44: 1018.1601 | BT44: 957.43378 | BU44: 997.35542 | BV44: 984.18571 | BW44: 1017.0635 | BX44: 1051.2536 | BY44: 934.0312 | BZ44: 1048.8931 | CA44: 1069.0586 | CB44: 1046.9453 | CC44: 1063.6201 | CD44: 1061.6034 | CE44: 1056.6421 | CF44: 1082.769 | CG44: 1165.0563 | CH44: 990.28439 | CI44: 1017.8528 | CJ44: 1078.1451 | CK44: 1095.739 | CL44: 1082.3857 | CM44: 1118.1317 | CN44: 1074.6943 | CO44: 1109.7112 | CP44: 1125.0314 | CQ44: 1221.0963 | CR44: 1164.2894 | CS44: 1202.1372 | CT44: 1235.376 | CU44: 1268.3591 | CV44: 1160.8257 | CW44: 1244.3823 | CX44: 1271.5313 | CY44: 1316.1948 | CZ44: 1236.0658 | DA44: 1376.7892 | DD44: =(SUM(CX44:DA44)/SUM(CT44:CW44)-1)*100 -> 5.9409528 | DE44: =+DE45+DE46 -> 1.1363959
A45: FBCF_PRIVEE | B45: 290.92506 | C45: 256.51573 | D45: 250.38083 | E45: 263.02577 | F45: 268.53264 | G45: 301.46974 | H45: 300.64367 | I45: 290.61305 | J45: 325.06893 | K45: 322.34711 | L45: 306.45574 | M45: 306.35281 | N45: 332.10292 | O45: 348.22742 | P45: 339.17485 | Q45: 287.63104 | R45: 288.70401 | S45: 313.26863 | T45: 339.02694 | U45: 289.97043 | V45: 326.04118 | W45: 389.53008 | X45: 313.89859 | Y45: 347.81491 | Z45: 353.55857 | AA45: 354.7945 | AB45: 353.01315 | AC45: 329.06145 | AD45: 356.33313 | AE45: 353.54984 | AF45: 350.77976 | AG45: 367.57566 | AH45: 381.83322 | AI45: 392.73312 | AJ45: 396.98133 | AK45: 394.12274 | AL45: 411.44321 | AM45: 470.06001 | AN45: 423.1868 | AO45: 393.53621 | AP45: 440.09593 | AQ45: 430.6065 | AR45: 424.39401 | AS45: 404.28288 | AT45: 411.24033 | AU45: 464.79902 | AV45: 503.23325 | AW45: 466.78752 | AX45: 509.15257 | AY45: 443.39513 | AZ45: 492.36447 | BA45: 479.1925 | BB45: 500.90056 | BC45: 520.97869 | BD45: 526.46822 | BE45: 461.85779 | BF45: 643.24617 | BG45: 534.89763 | BH45: 578.93573 | BI45: 478.81024 | BJ45: 633.13624 | BK45: 635.01924 | BL45: 602.88589 | BM45: 689.06608 | BN45: 579.21268 | BO45: 588.32615 | BP45: 671.37551 | BQ45: 763.21351 | BR45: 685.98539 | BS45: 783.24168 | BT45: 770.71924 | BU45: 507.7157 | BV45: 849.60699 | BW45: 753.96623 | BX45: 863.51086 | BY45: 472.70824 | BZ45: 774.96354 | CA45: 721.47307 | CB45: 764.02921 | CC45: 763.79537 | CD45: 900.44167 | CE45: 733.19865 | CF45: 799.84584 | CG45: 684.89926 | CH45: 730.63391 | CI45: 798.69108 | CJ45: 879.85393 | CK45: 890.99932 | CL45: 852.85206 | CM45: 884.78799 | CN45: 850.51314 | CO45: 870.85305 | CP45: 881.2356 | CQ45: 980.83117 | CR45: 914.32461 | CS45: 968.29615 | CT45: 1024.0997 | CU45: 1065.1723 | CV45: 966.41564 | CW45: 1051.0581 | CX45: 1068.062 | CY45: 1101.2846 | CZ45: 1026.8226 | DA45: 1077.5071 | DB45: =+SUM(CT47:CW47)-SUM(CT50:CW50) -> -1338.018 | DD45: =(SUM(CX45:DA45)/SUM(CT45:CW45)-1)*100 -> 4.0647878 | DE45: =+DD45*SUM(CT94:CW94)/SUM(CT$102:CW$102) -> 0.65046098
A46: FBCF_PUBLIQUE | B46: 82.338022 | C46: 124.12335 | D46: 103.40375 | E46: 108.10328 | F46: 121.22407 | G46: 117.77661 | H46: 110.18826 | I46: 108.3348 | J46: 115.49828 | K46: 124.1354 | L46: 127.72208 | M46: 129.16934 | N46: 126.53983 | O46: 120.8313 | P46: 132.73594 | Q46: 134.90178 | R46: 121.30478 | S46: 121.56546 | T46: 121.61361 | U46: 120.48507 | V46: 126.3786 | W46: 139.83085 | X46: 140.00137 | Y46: 136.46846 | Z46: 141.26808 | AA46: 132.79565 | AB46: 133.67505 | AC46: 140.0889 | AD46: 141.91563 | AE46: 142.88054 | AF46: 140.01085 | AG46: 137.7738 | AH46: 140.68119 | AI46: 156.60607 | AJ46: 160.1838 | AK46: 159.6623 | AL46: 163.89338 | AM46: 165.34239 | AN46: 170.80272 | AO46: 168.95107 | AP46: 162.6514 | AQ46: 155.44824 | AR46: 162.25271 | AS46: 188.51563 | AT46: 202.68241 | AU46: 192.15771 | AV46: 171.7806 | AW46: 162.51337 | AX46: 169.63493 | AY46: 183.76081 | AZ46: 195.2145 | BA46: 208.02651 | BB46: 217.85907 | BC46: 202.83158 | BD46: 183.73237 | BE46: 184.74319 | BF46: 193.73647 | BG46: 217.74366 | BH46: 238.79399 | BI46: 242.07091 | BJ46: 241.76983 | BK46: 246.61384 | BL46: 257.18062 | BM46: 247.9783 | BN46: 243.44119 | BO46: 248.24528 | BP46: 255.69958 | BQ46: 269.00657 | BR46: 240.09231 | BS46: 234.91843 | BT46: 186.71454 | BU46: 489.63972 | BV46: 134.57872 | BW46: 263.09731 | BX46: 187.74269 | BY46: 461.32295 | BZ46: 273.92959 | CA46: 347.58554 | CB46: 282.91608 | CC46: 299.82469 | CD46: 161.16169 | CE46: 323.44349 | CF46: 282.92321 | CG46: 480.15701 | CH46: 259.65047 | CI46: 219.16169 | CJ46: 198.29114 | CK46: 204.73969 | CL46: 229.53365 | CM46: 233.34372 | CN46: 224.18112 | CO46: 238.85814 | CP46: 243.79583 | CQ46: 240.26516 | CR46: 249.96479 | CS46: 233.84106 | CT46: 211.27634 | CU46: 203.18678 | CV46: 194.41004 | CW46: 193.32416 | CX46: 203.46929 | CY46: 214.91019 | CZ46: 209.24318 | DA46: 299.28215 | DD46: =(SUM(CX46:DA46)/SUM(CT46:CW46)-1)*100 -> 15.545738 | DE46: =+DD46*SUM(CT95:CW95)/SUM(CT$102:CW$102) -> 0.4859349
A47: Export | B47: 491.83272 | C47: 526.64439 | D47: 531.08899 | E47: 726.59885 | F47: 555.35732 | G47: 607.10695 | H47: 616.43813 | I47: 721.26893 | J47: 637.02993 | K47: 655.84334 | L47: 614.17038 | M47: 750.87585 | N47: 580.8089 | O47: 572.16732 | P47: 642.44581 | Q47: 855.4999 | R47: 557.06455 | S47: 536.56568 | T47: 540.03664 | U47: 704.09729 | V47: 651.30411 | W47: 593.63301 | X47: 626.18879 | Y47: 675.64299 | Z47: 485.66366 | AA47: 489.24808 | AB47: 647.76516 | AC47: 766.70725 | AD47: 523.07478 | AE47: 524.39777 | AF47: 680.92019 | AG47: 891.69495 | AH47: 611.18749 | AI47: 704.98663 | AJ47: 768.4416 | AK47: 909.95587 | AL47: 700.67391 | AM47: 620.88527 | AN47: 738.3024 | AO47: 837.97308 | AP47: 500.69806 | AQ47: 672.18108 | AR47: 649.63043 | AS47: 727.83105 | AT47: 611.05562 | AU47: 675.19748 | AV47: 706.21785 | AW47: 894.11506 | AX47: 710.98382 | AY47: 606.53984 | AZ47: 775.04695 | BA47: 941.09966 | BB47: 599.46668 | BC47: 717.93625 | BD47: 762.77763 | BE47: 990.68077 | BF47: 697.7895 | BG47: 725.92887 | BH47: 735.08851 | BI47: 1012.0375 | BJ47: 806.89801 | BK47: 748.72106 | BL47: 803.40417 | BM47: 1168.1982 | BN47: 829.11691 | BO47: 787.00996 | BP47: 980.5821 | BQ47: 1098.7192 | BR47: 774.71559 | BS47: 811.03476 | BT47: 848.68989 | BU47: 1362.8638 | BV47: 968.32833 | BW47: 872.54727 | BX47: 915.10294 | BY47: 981.67346 | BZ47: 866.74892 | CA47: 798.38092 | CB47: 863.67952 | CC47: 1288.4308 | CD47: 958.74008 | CE47: 950.1569 | CF47: 1019.7076 | CG47: 1317.0427 | CH47: 1001.169 | CI47: 640.99944 | CJ47: 878.11548 | CK47: 1115.6428 | CL47: 987.15475 | CM47: 890.70707 | CN47: 861.36296 | CO47: 1023.3605 | CP47: 920.83022 | CQ47: 936.63157 | CR47: 936.24956 | CS47: 1077.8532 | CT47: 1056.6483 | CU47: 929.34617 | CV47: 865.04919 | CW47: 1017.475 | CX47: 958.87804 | CY47: 879.0918 | CZ47: 822.49113 | DA47: 1038.0576 | DB47: =+SUM(CX47:DA47)-SUM(CX50:DA50) -> -1557.0998 | DD47: =(SUM(CX47:DA47)/SUM(CT47:CW47)-1)*100 -> -4.394448 | DE47: =+DE48+DE49 -> -0.73010451
A48: Export_Biens | B48: 443.15965 | C48: 482.29367 | D48: 462.17403 | E48: 609.33604 | F48: 463.12389 | G48: 521.05463 | H48: 493.00891 | I48: 517.42905 | J48: 503.36281 | K48: 530.12502 | L48: 451.19909 | M48: 492.0656 | N48: 464.72716 | O48: 458.26521 | P48: 485.49615 | Q48: 597.90801 | R48: 461.23949 | S48: 445.59765 | T48: 419.83836 | U48: 520.61762 | V48: 516.34401 | W48: 468.84956 | X48: 458.23104 | Y48: 394.68414 | Z48: 359.38969 | AA48: 364.14941 | AB48: 476.1627 | AC48: 461.90117 | AD48: 383.85927 | AE48: 389.73447 | AF48: 501.7235 | AG48: 608.57478 | AH48: 445.89584 | AI48: 540.73761 | AJ48: 555.35594 | AK48: 580.53871 | AL48: 534.67155 | AM48: 463.6394 | AN48: 534.98326 | AO48: 534.09631 | AP48: 363.27988 | AQ48: 527.99605 | AR48: 475.01226 | AS48: 468.50138 | AT48: 466.52495 | AU48: 533.20347 | AV48: 515.98792 | AW48: 590.9199 | AX48: 517.10405 | AY48: 422.31075 | AZ48: 530.9761 | BA48: 559.62572 | BB48: 410.46414 | BC48: 527.25574 | BD48: 519.99381 | BE48: 616.9095 | BF48: 494.30478 | BG48: 526.37341 | BH48: 485.20534 | BI48: 624.29064 | BJ48: 597.60045 | BK48: 549.02683 | BL48: 552.06995 | BM48: 776.96129 | BN48: 648.4482 | BO48: 613.42981 | BP48: 752.10639 | BQ48: 756.21596 | BR48: 651.60442 | BS48: 639.00172 | BT48: 638.18825 | BU48: 850.01761 | BV48: 749.72242 | BW48: 648.13419 | BX48: 599.76888 | BY48: 633.1195 | BZ48: 676.03588 | CA48: 573.91302 | CB48: 588.68809 | CC48: 800.0149 | CD48: 680.96806 | CE48: 718.72353 | CF48: 693.85515 | CG48: 851.7698 | CH48: 764.8302 | CI48: 468.05895 | CJ48: 603.05138 | CK48: 746.85226 | CL48: 719.3149 | CM48: 664.4021 | CN48: 633.06878 | CO48: 758.51196 | CP48: 693.76899 | CQ48: 674.37468 | CR48: 676.15917 | CS48: 797.21573 | CT48: 684.22338 | CU48: 595.15918 | CV48: 654.67975 | CW48: 836.84774 | CX48: 649.53647 | CY48: 588.23756 | CZ48: 632.72547 | DA48: 877.91553 | DD48: =(SUM(CX48:DA48)/SUM(CT48:CW48)-1)*100 -> -0.81182746 | DE48: =+DD48*SUM(CT97:CW97)/SUM(CT$102:CW$102) -> -0.10103977
A49: Export_Service | B49: 64.850538 | C49: 62.827012 | D49: 83.953955 | E49: 134.42489 | F49: 104.96363 | G49: 102.16357 | H49: 134.43251 | I49: 207.88794 | J49: 145.52219 | K49: 136.27812 | L49: 179.11744 | M49: 286.78859 | N49: 130.61845 | O49: 128.22249 | P49: 173.03207 | Q49: 279.01287 | R49: 109.61808 | S49: 104.24839 | T49: 133.67443 | U49: 201.15248 | V49: 151.21211 | W49: 139.56357 | X49: 182.8762 | Y49: 295.21009 | Z49: 139.62629 | AA49: 138.99446 | AB49: 188.73966 | AC49: 303.61865 | AD49: 146.1315 | AE49: 140.97709 | AF49: 187.94329 | AG49: 300.69674 | AH49: 173.15758 | AI49: 167.74301 | AJ49: 224.08781 | AK49: 358.73078 | AL49: 168.73503 | AM49: 162.16369 | AN49: 213.18599 | AO49: 333.06205 | AP49: 143.10211 | AQ49: 135.97587 | AR49: 180.54825 | AS49: 291.00901 | AT49: 151.38362 | AU49: 148.54441 | AV49: 199.48843 | AW49: 318.51523 | AX49: 203.53795 | AY49: 195.68583 | AZ49: 260.19008 | BA49: 415.58884 | BB49: 200.34457 | BC49: 193.71611 | BD49: 257.89339 | BE49: 410.67714 | BF49: 210.68727 | BG49: 202.86877 | BH49: 269.7054 | BI49: 430.09526 | BJ49: 207.12525 | BK49: 199.721 | BL49: 265.15645 | BM49: 420.93237 | BN49: 171.72468 | BO49: 165.67605 | BP49: 222.05235 | BQ49: 359.58516 | BR49: 115.16255 | BS49: 167.76222 | BT49: 208.89375 | BU49: 526.67348 | BV49: 218.60591 | BW49: 224.41307 | BX49: 315.33405 | BY49: 348.55396 | BZ49: 188.99147 | CA49: 224.15549 | CB49: 275.49276 | CC49: 491.20401 | CD49: 275.70641 | CE49: 223.66303 | CF49: 327.62525 | CG49: 473.35811 | CH49: 228.23219 | CI49: 170.24569 | CJ49: 275.77494 | CK49: 371.92341 | CL49: 266.97831 | CM49: 226.40054 | CN49: 227.85005 | CO49: 264.6834 | CP49: 225.2965 | CQ49: 263.53175 | CR49: 261.16274 | CS49: 280.02906 | CT49: 403.86507 | CU49: 364.12326 | CV49: 203.5504 | CW49: 149.59439 | CX49: 322.93097 | CY49: 304.82218 | CZ49: 185.694 | DA49: 138.4879 | DB49: =+DB47/DB45-1 -> 0.16373608 | DD49: =(SUM(CX49:DA49)/SUM(CT49:CW49)-1)*100 -> -15.091703 | DE49: =+DD49*SUM(CT98:CW98)/SUM(CT$102:CW$102) -> -0.62906474
A50: Import | B50: 368.02874 | C50: 369.06361 | D50: 407.6554 | E50: 456.35333 | F50: 427.84954 | G50: 477.49945 | H50: 496.59014 | I50: 582.54385 | J50: 511.44557 | K50: 483.29821 | L50: 573.874 | M50: 643.86954 | N50: 501.12803 | O50: 532.31823 | P50: 563.92735 | Q50: 585.18729 | R50: 416.83127 | S50: 420.26244 | T50: 481.22164 | U50: 556.8282 | V50: 421.92124 | W50: 506.36084 | X50: 484.68413 | Y50: 630.86965 | Z50: 476.96506 | AA50: 483.67602 | AB50: 563.97266 | AC50: 613.68205 | AD50: 582.14914 | AE50: 478.44818 | AF50: 545.44798 | AG50: 612.62338 | AH50: 589.53313 | AI50: 596.02282 | AJ50: 747.43237 | AK50: 614.20932 | AL50: 604.18297 | AM50: 563.68515 | AN50: 804.14119 | AO50: 848.47582 | AP50: 586.89617 | AQ50: 653.36558 | AR50: 696.15481 | AS50: 694.8083 | AT50: 679.52251 | AU50: 703.53446 | AV50: 791.03884 | AW50: 833.46828 | AX50: 731.88192 | AY50: 772.17474 | AZ50: 799.60123 | BA50: 935.1258 | BB50: 749.43575 | BC50: 795.78013 | BD50: 870.26186 | BE50: 922.66537 | BF50: 851.97642 | BG50: 902.93654 | BH50: 974.61562 | BI50: 1007.936 | BJ50: 985.71252 | BK50: 997.94697 | BL50: 1069.7757 | BM50: 1253.0299 | BN50: 979.5971 | BO50: 1030.3768 | BP50: 1153.8726 | BQ50: 1137.9077 | BR50: 892.92105 | BS50: 942.93095 | BT50: 1003.7445 | BU50: 1506.4985 | BV50: 883.82715 | BW50: 956.35833 | BX50: 1060.2931 | BY50: 1393.1834 | BZ50: 1049.6486 | CA50: 1014.294 | CB50: 1134.4278 | CC50: 1458.9638 | CD50: 842.88943 | CE50: 1620.1261 | CF50: 1278.8235 | CG50: 1444.3906 | CH50: 1138.1783 | CI50: 904.77466 | CJ50: 1167.2213 | CK50: 1091.694 | CL50: 1186.5602 | CM50: 1162.0612 | CN50: 1175.0126 | CO50: 1329.0215 | CP50: 1239.5494 | CQ50: 1060.4029 | CR50: 1435.7851 | CS50: 1373.5017 | CT50: 1256.3227 | CU50: 1417.8163 | CV50: 1284.6786 | CW50: 1247.719 | CX50: 1132.4982 | CY50: 1373.8033 | CZ50: 1479.6082 | DA50: 1269.7088 | DD50: =(SUM(CX50:DA50)/SUM(CT50:CW50)-1)*100 -> 0.94269549 | DE50: =+DE51+DE52 -> 0.19422864
A51: Import_Biens | B51: 305.83781 | C51: 309.94527 | D51: 319.18202 | E51: 329.07093 | F51: 297.80363 | G51: 356.43847 | H51: 317.79695 | I51: 334.25508 | J51: 345.98581 | K51: 322.48058 | L51: 356.63072 | M51: 352.0035 | N51: 312.94949 | O51: 350.57772 | P51: 330.04713 | Q51: 287.50022 | R51: 293.71926 | S51: 303.33669 | T51: 330.36584 | U51: 361.14667 | V51: 294.60238 | W51: 382.74406 | X51: 316.627 | Y51: 401.83168 | Z51: 349.22286 | AA51: 357.10575 | AB51: 391.25822 | AC51: 381.34202 | AD51: 441.46549 | AE51: 346.91309 | AF51: 374.9344 | AG51: 392.90342 | AH51: 441.52332 | AI51: 452.54237 | AJ51: 558.66005 | AK51: 382.69296 | AL51: 423.18932 | AM51: 390.31907 | AN51: 572.06105 | AO51: 556.23291 | AP51: 453.35128 | AQ51: 519.09848 | AR51: 530.40859 | AS51: 490.44928 | AT51: 540.10496 | AU51: 565.52097 | AV51: 607.13397 | AW51: 590.9315 | AX51: 618.27509 | AY51: 659.69993 | AZ51: 655.16516 | BA51: 745.38359 | BB51: 611.68532 | BC51: 658.99839 | BD51: 696.52734 | BE51: 703.77912 | BF51: 685.39872 | BG51: 738.96025 | BH51: 765.08065 | BI51: 739.24208 | BJ51: 808.98863 | BK51: 823.12504 | BL51: 840.77811 | BM51: 950.32183 | BN51: 813.98498 | BO51: 867.41446 | BP51: 944.74328 | BQ51: 876.93856 | BR51: 795.93048 | BS51: 800.93249 | BT51: 894.39572 | BU51: 1009.0443 | BV51: 705.57916 | BW51: 783.04962 | BX51: 831.48988 | BY51: 1074.5833 | BZ51: 880.42254 | CA51: 818.38417 | CB51: 920.92241 | CC51: 1120.8691 | CD51: 631.45949 | CE51: 1462.5397 | CF51: 999.69608 | CG51: 1125.433 | CH51: 942.48948 | CI51: 817.51756 | CJ51: 938.4819 | CK51: 877.84289 | CL51: 996.73621 | CM51: 1011.9052 | CN51: 1036.8712 | CO51: 1095.7126 | CP51: 1025.0037 | CQ51: 911.56582 | CR51: 1278.8468 | CS51: 1221.3192 | CT51: 1053.8531 | CU51: 1242.6423 | CV51: 1120.9859 | CW51: 1132.2577 | CX51: 973.00379 | CY51: 1229.7331 | CZ51: 1346.7901 | DA51: 1167.8364 | DD51: =(SUM(CX51:DA51)/SUM(CT51:CW51)-1)*100 -> 3.6842658 | DE51: =+DD51*SUM(CT100:CW100)/SUM(CT$102:CW$102) -> 0.6447054
A52: Import_Service | B52: 88.010322 | C52: 85.401905 | D52: 114.7111 | E52: 153.24921 | F52: 153.09899 | G52: 149.69239 | H52: 202.19151 | I52: 271.08884 | J52: 189.99422 | K52: 184.33318 | L52: 247.11709 | M52: 328.95578 | N52: 213.97102 | O52: 204.61878 | P52: 268.41292 | Q52: 347.21444 | R52: 135.41611 | S52: 127.41658 | T52: 167.38103 | U52: 220.42051 | V52: 141.24564 | W52: 137.28413 | X52: 186.33135 | Y52: 253.89847 | Z52: 142.20106 | AA52: 140.97379 | AB52: 191.69944 | AC52: 256.86817 | AD52: 148.49775 | AE52: 142.82984 | AF52: 189.68555 | AG52: 249.8905 | AH52: 156.77694 | AI52: 150.27281 | AJ52: 200.26424 | AK52: 266.65149 | AL52: 199.75081 | AM52: 192.34976 | AN52: 254.14139 | AO52: 331.12438 | AP52: 130.84528 | AQ52: 124.47337 | AR52: 166.00369 | AS52: 222.96653 | AT52: 138.33827 | AU52: 136.21499 | AV52: 184.97313 | AW52: 248.90903 | AX52: 105.73353 | AY52: 103.01756 | AZ52: 138.99878 | BA52: 186.62702 | BB52: 134.19102 | BC52: 130.15971 | BD52: 173.7287 | BE52: 229.27395 | BF52: 165.55107 | BG52: 159.22428 | BH52: 213.89478 | BI52: 288.36447 | BJ52: 174.84101 | BK52: 172.16601 | BL52: 233.76401 | BM52: 314.60316 | BN52: 160.78186 | BO52: 155.46685 | BP52: 206.46048 | BQ52: 270.10154 | BR52: 85.296674 | BS52: 135.67713 | BT52: 96.252346 | BU52: 528.56585 | BV52: 178.24799 | BW52: 173.30871 | BX52: 228.80321 | BY52: 318.60009 | BZ52: 168.88782 | CA52: 195.79975 | CB52: 213.34469 | CC52: 338.31316 | CD52: 208.47586 | CE52: 167.66918 | CF52: 277.28398 | CG52: 316.64164 | CH52: 197.83659 | CI52: 95.13801 | CJ52: 228.406 | CK52: 213.5472 | CL52: 193.83304 | CM52: 159.00771 | CN52: 148.97775 | CO52: 234.94804 | CP52: 216.70179 | CQ52: 155.24473 | CR52: 171.47728 | CS52: 165.82096 | CT52: 208.0299 | CU52: 186.44141 | CV52: 173.43683 | CW52: 129.00001 | CX52: 165.9463 | CY52: 158.64856 | CZ52: 151.57305 | DA52: 119.62081 | DD52: =(SUM(CX52:DA52)/SUM(CT52:CW52)-1)*100 -> -14.50972 | DE52: =+DD52*SUM(CT101:CW101)/SUM(CT$102:CW$102) -> -0.45047677
A53: PIB | B53: 2426.6748 | C53: 2575.3104 | D53: 2429.6087 | E53: 2408.7174 | F53: 2486.7724 | G53: 2622.773 | H53: 2554.9293 | I53: 2552.9587 | J53: 2625.5328 | K53: 2725.7868 | L53: 2650.4559 | M53: 2657.4863 | N53: 2711.0631 | O53: 2784.5816 | P53: 2816.5523 | Q53: 2824.2828 | R53: 2799.4747 | S53: 2932.3417 | T53: 2968.8488 | U53: 3043.104 | V53: 3055.7096 | W53: 3182.5931 | X53: 3149.5551 | Y53: 3183.7134 | Z53: 3158.5419 | AA53: 3214.9629 | AB53: 3255.3907 | AC53: 3222.8043 | AD53: 3209.9098 | AE53: 3288.5437 | AF53: 3324.0949 | AG53: 3518.7478 | AH53: 3403.9293 | AI53: 3480.0033 | AJ53: 3528.6905 | AK53: 3506.0295 | AL53: 3537.7893 | AM53: 3640.9237 | AN53: 3563.7935 | AO53: 3572.5044 | AP53: 3617.7201 | AQ53: 3679.1597 | AR53: 3679.2191 | AS53: 3708.1322 | AT53: 3700.3285 | AU53: 3776.326 | AV53: 3799.7692 | AW53: 3833.5068 | AX53: 3817.399 | AY53: 3854.2562 | AZ53: 3942.5548 | BA53: 4006.3171 | BB53: 4090.8645 | BC53: 4114.2172 | BD53: 4106.6848 | BE53: 4031.3628 | BF53: 4246.4 | BG53: 4260.0661 | BH53: 4322.2405 | BI53: 4330.8485 | BJ53: 4412.4757 | BK53: 4479.6093 | BL53: 4521.418 | BM53: 4727.5475 | BN53: 4647.0709 | BO53: 4764.076 | BP53: 4849.1232 | BQ53: 4908.8253 | BR53: 4876.8954 | BS53: 5035.8267 | BT53: 5002.4485 | BU53: 5123.3954 | BV53: 5099.1682 | BW53: 5232.9196 | BX53: 5237.4428 | BY53: 5178.6363 | BZ53: 5298.693 | CA53: 5479.8341 | CB53: 5359.2337 | CC53: 5431.1028 | CD53: 5460.0354 | CE53: 5668.6365 | CF53: 5577.1022 | CG53: 5612.6206 | CH53: 5536.2536 | CI53: 5554.8226 | CJ53: 5598.7117 | CK53: 5686.6196 | CL53: 5691.7246 | CM53: 5824.9263 | CN53: 5773.2701 | CO53: 5833.6028 | CP53: 5898.6706 | CQ53: 6074.0836 | CR53: 6002.6136 | CS53: 6012.2611 | CT53: 6070.2109 | CU53: 6281.7159 | CV53: 6173.8695 | CW53: 6240.9711 | CX53: 6305.9753 | CY53: 6430.9098 | CZ53: 6381.2297 | DA53: 6505.2957 | DD53: =(SUM(CX53:DA53)/SUM(CT53:CW53)-1)*100 -> 3.45884 | DE53: =+DD53*SUM(CT102:CW102)/SUM(CT$102:CW$102) -> 3.45884
F55: =F53/B53-1 -> 0.024765389 | G55: =G53/C53-1 -> 0.018429831 | H55: =H53/D53-1 -> 0.051580537 | I55: =I53/E53-1 -> 0.059883006 | J55: =J53/F53-1 -> 0.055799404 | K55: =K53/G53-1 -> 0.039276682 | L55: =L53/H53-1 -> 0.037389158 | M55: =M53/I53-1 -> 0.040943715 | ... DA55: =DA53/CW53-1 -> 0.042353114
A57: Offre du PIB trimestriel aux prix courants, Données brutes
A59: Libellé | B59: =B10 -> T1_1999 | C59: =C10 -> T2_1999 | D59: =D10 -> T3_1999 | E59: =E10 -> T4_1999 | F59: =F10 -> T1_2000 | G59: =G10 -> T2_2000 | H59: =H10 -> T3_2000 | I59: =I10 -> T4_2000 | ... BQ59: =BQ10 -> T4_2015 | BR59: T1_2016 | BS59: T2_2016 | BT59: T3_2016 | BU59: T4_2016 | BV59: T1_2017 | BW59: T2_2017 | BX59: T3_2017 | BY59: T4_2017 | BZ59: T1_2018 | CA59: T2_2018 | CB59: T3_2018 | CC59: T4_2018 | CD59: T1_2019 | CE59: T2_2019 | CF59: T3_2019 | CG59: T4_2019 | CH59: T1_2020 | CI59: T2_2020 | CJ59: T3_2020 | CK59: T4_2020 | CL59: T1_2021 | CM59: T2_2021 | CN59: T3_2021 | CO59: T4_2021 | CP59: T1_2022 | CQ59: T2_2022 | CR59: T3_2022 | CS59: T4_2022 | CT59: T1_2023 | CU59: T2_2023 | CV59: T3_2023 | CW59: T4_2023 | CX59: =CX10 -> T1_2024 | CY59: =CY10 -> T2_2024 | CZ59: =CZ10 -> T3_2024 | DA59: =DA10 -> T4_2024 | DD59: Deflateur 2024/2023 (en %) | DG59: 2023 | DH59: 2024 | DK59: 2024 aux prix de 2023
A60: Secteur primaire | B60: 317.06677 | C60: 369.02459 | D60: 340.26982 | E60: 324.63603 | F60: 312.91886 | G60: 370.81074 | H60: 350.87051 | I60: 325.04024 | J60: 349.47991 | K60: 399.06416 | L60: 386.32261 | M60: 358.96382 | N60: 342.10583 | O60: 401.55112 | P60: 403.25724 | Q60: 427.01046 | R60: 371.01941 | S60: 413.1034 | T60: 413.93178 | U60: 420.21783 | V60: 409.05496 | W60: 463.57665 | X60: 442.21442 | Y60: 428.5665 | Z60: 394.16276 | AA60: 435.98463 | AB60: 455.94813 | AC60: 435.30452 | AD60: 362.05874 | AE60: 437.71099 | AF60: 460.49883 | AG60: 446.64473 | AH60: 398.99273 | AI60: 471.19394 | AJ60: 472.81192 | AK60: 473.14352 | AL60: 455.40782 | AM60: 497.21727 | AN60: 494.4584 | AO60: 530.81656 | AP60: 497.60066 | AQ60: 537.88175 | AR60: 541.33706 | AS60: 575.91529 | AT60: 509.15284 | AU60: 583.2812 | AV60: 611.74798 | AW60: 646.32132 | AX60: 556.4199 | AY60: 615.05184 | AZ60: 633.90867 | BA60: 604.85029 | BB60: 565.82777 | BC60: 669.44461 | BD60: 684.59514 | BE60: 644.65755 | BF60: 649.33148 | BG60: 713.16276 | BH60: 720.43663 | BI60: 702.98915 | BJ60: 668.36948 | BK60: 752.91892 | BL60: 774.77392 | BM60: 826.88849 | BN60: 792.57866 | BO60: 873.8532 | BP60: 814.46304 | BQ60: 796.30562 | BR60: 755.36516 | BS60: 862.12822 | BT60: 862.62905 | BU60: 965.04057 | BV60: 773.11292 | BW60: 927.58403 | BX60: 940.70873 | BY60: 857.57931 | BZ60: 853.09108 | CA60: 975.08297 | CB60: 915.78025 | CC60: 919.3287 | CD60: 837.90941 | CE60: 1037.4166 | CF60: 1016.8579 | CG60: 1013.2821 | CH60: 972.26575 | CI60: 1019.3389 | CJ60: 1045.056 | CK60: 1069.5924 | CL60: 981.86274 | CM60: 1079.4846 | CN60: 1080.6599 | CO60: 1091.0847 | CP60: 1059.1265 | CQ60: 1229.362 | CR60: 1186.0291 | CS60: 1102.5844 | CT60: 1099.962 | CU60: 1314.7162 | CV60: 1385.722 | CW60: 1369.3558 | CX60: 1371.9566 | CY60: 1521.7585 | CZ60: 1586.784 | DA60: 1903.2965 | DB60: =+DB61+DB62 -> 2555.013 | DC60: =+DC61+DC62 -> 2944.921 | DD60: 19.300245 | DE60: =+#REF!/DC60-1 -> #REF! | DG60: =+SUM(CT60:CW60) -> 5169.756 | DH60: =+SUM(CX60:DA60) -> 6383.7955 | DK60: =+DG60*(1+DD11/100) -> 5351.033
A61: Agrivriere | B61: 84.872852 | C61: 141.90506 | D61: 132.62414 | E61: 92.090978 | F61: 88.320451 | G61: 145.46207 | H61: 139.0189 | I61: 98.00128 | J61: 99.21225 | K61: 166.09518 | L61: 161.1452 | M61: 111.74687 | N61: 107.74445 | O61: 174.13148 | P61: 166.50295 | Q61: 119.3361 | R61: 104.3638 | S61: 170.70343 | T61: 161.16943 | U61: 113.1921 | V61: 108.92045 | W61: 177.28104 | X61: 170.33224 | Y61: 126.0056 | Z61: 112.57117 | AA61: 185.31418 | AB61: 184.2966 | AC61: 127.19616 | AD61: 107.99947 | AE61: 175.0208 | AF61: 164.85702 | AG61: 112.77461 | AH61: 105.72172 | AI61: 174.46614 | AJ61: 165.09712 | AK61: 119.48479 | AL61: 114.93778 | AM61: 181.22372 | AN61: 175.94152 | AO61: 130.85481 | AP61: 138.53316 | AQ61: 230.07655 | AR61: 211.95379 | AS61: 148.5145 | AT61: 153.6112 | AU61: 247.05043 | AV61: 235.48937 | AW61: 171.92321 | AX61: 156.22033 | AY61: 251.91284 | AZ61: 241.89839 | BA61: 174.49641 | BB61: 164.72497 | BC61: 274.03517 | BD61: 264.17563 | BE61: 189.08638 | BF61: 178.15905 | BG61: 301.22885 | BH61: 292.97368 | BI61: 210.03219 | BJ61: 183.27616 | BK61: 305.6996 | BL61: 307.33 | BM61: 234.56167 | BN61: 220.71821 | BO61: 385.80574 | BP61: 316.93156 | BQ61: 184.42824 | BR61: 230.19683 | BS61: 398.00607 | BT61: 377.90695 | BU61: 259.50014 | BV61: 242.76951 | BW61: 418.81745 | BX61: 404.15131 | BY61: 294.35773 | BZ61: 277.52821 | CA61: 446.17621 | CB61: 412.96145 | CC61: 305.45913 | CD61: 271.82394 | CE61: 463.66627 | CF61: 453.90973 | CG61: 317.39906 | CH61: 277.54703 | CI61: 446.89836 | CJ61: 447.39629 | CK61: 306.71994 | CL61: 263.72984 | CM61: 465.01704 | CN61: 456.12071 | CO61: 323.57377 | CP61: 321.7832 | CQ61: 541.01212 | CR61: 529.44424 | CS61: 364.66944 | CT61: 346.74713 | CU61: 600.92673 | CV61: 604.62838 | CW61: 443.13159 | CX61: 399.42272 | CY61: 691.48848 | CZ61: 683.5535 | DA61: 514.33862 | DB61: =+SUM(CP61:CS61) -> 1756.909 | DC61: =+SUM(CT61:CW61) -> 1995.4338 | DD61: 11.358406 | DE61: =+#REF!/DC61-1 -> #REF! | DG61: =+SUM(CT61:CW61) -> 1995.4338 | DH61: =+SUM(CX61:DA61) -> 2288.8033 | DK61: =+DG61*(1+DD12/100) -> 2055.3485
A62: Agriexport | B62: 77.696142 | C62: 69.314367 | D62: 54.829248 | E62: 81.820952 | F62: 70.791142 | G62: 69.44936 | H62: 57.35855 | I62: 72.226334 | J62: 87.348372 | K62: 65.6063 | L62: 55.938714 | M62: 77.903677 | N62: 61.575666 | O62: 50.601027 | P62: 61.565672 | Q62: 129.6218 | R62: 84.560129 | S62: 52.374823 | T62: 61.208218 | U62: 109.25602 | V62: 98.082111 | W62: 79.752547 | X62: 64.631735 | Y62: 100.04436 | Z62: 86.58822 | AA62: 57.038058 | AB62: 75.809317 | AC62: 109.36296 | AD62: 56.464953 | AE62: 64.067373 | AF62: 96.813314 | AG62: 132.23858 | AH62: 81.345876 | AI62: 79.471789 | AJ62: 85.094406 | AK62: 127.30698 | AL62: 105.72667 | AM62: 70.392119 | AN62: 69.503956 | AO62: 150.87665 | AP62: 116.23714 | AQ62: 62.552178 | AR62: 81.60315 | AS62: 177.16938 | AT62: 95.192365 | AU62: 70.346767 | AV62: 107.14232 | AW62: 204.06667 | AX62: 127.46291 | AY62: 82.109059 | AZ62: 109.21162 | BA62: 146.34022 | BB62: 106.55892 | BC62: 94.967744 | BD62: 118.15183 | BE62: 154.25034 | BF62: 155.56794 | BG62: 94.842283 | BH62: 104.71559 | BI62: 169.50899 | BJ62: 146.6809 | BK62: 109.83416 | BL62: 115.98074 | BM62: 226.50051 | BN62: 200.17652 | BO62: 112.89086 | BP62: 137.37895 | BQ62: 255.55742 | BR62: 169.03473 | BS62: 101.3698 | BT62: 116.49466 | BU62: 332.73181 | BV62: 155.9856 | BW62: 128.1339 | BX62: 147.97486 | BY62: 170.39164 | BZ62: 179.85013 | CA62: 124.45548 | CB62: 109.14885 | CC62: 217.05755 | CD62: 163.39561 | CE62: 143.42751 | CF62: 128.54885 | CG62: 250.36403 | CH62: 255.58329 | CI62: 121.20415 | CJ62: 154.72716 | CK62: 315.05278 | CL62: 266.31416 | CM62: 159.28904 | CN62: 154.28174 | CO62: 289.18771 | CP62: 243.43959 | CQ62: 167.89057 | CR62: 145.42471 | CS62: 241.34913 | CT62: 241.0601 | CU62: 178.81184 | CV62: 196.10752 | CW62: 333.50771 | CX62: 435.04208 | CY62: 273.12491 | CZ62: 316.03385 | DA62: 789.49555 | DB62: =+SUM(CP62:CS62) -> 798.104 | DC62: =+SUM(CT62:CW62) -> 949.48717 | DD62: 74.400285 | DE62: =+#REF!/DC62-1 -> #REF! | DG62: =+SUM(CT62:CW62) -> 949.48717 | DH62: =+SUM(CX62:DA62) -> 1813.6964 | DK62: =+DG62*(1+DD13/100) -> 1039.9618
A63: Elev_Chass_Pech | B63: 76.473375 | C63: 76.531669 | D63: 76.649265 | E63: 76.8282 | F63: 77.071594 | G63: 77.479123 | H63: 78.04837 | I63: 78.770311 | J63: 79.629281 | K63: 81.105575 | L63: 83.223185 | M63: 86.000646 | N63: 89.450093 | O63: 92.363684 | P63: 94.737172 | Q63: 96.555759 | R63: 97.792408 | S63: 98.537437 | T63: 98.801401 | U63: 98.584591 | V63: 97.878055 | W63: 97.667978 | X63: 97.962538 | Y63: 98.757226 | Z63: 100.03582 | AA63: 101.12842 | AB63: 102.02742 | AC63: 102.73133 | AD63: 103.24441 | AE63: 103.73805 | AF63: 104.21869 | AG63: 104.69481 | AH63: 105.1769 | AI63: 106.44205 | AJ63: 108.49052 | AK63: 111.3247 | AL63: 114.94906 | AM63: 118.00502 | AN63: 120.50344 | AO63: 122.45142 | AP63: 123.85225 | AQ63: 125.22113 | AR63: 126.5384 | AS63: 127.78306 | AT63: 128.93307 | AU63: 130.48011 | AV63: 132.45469 | AW63: 134.87393 | AX63: 137.74123 | AY63: 140.48322 | AZ63: 143.11271 | BA63: 145.61278 | BB63: 147.93619 | BC63: 150.20256 | BD63: 152.43272 | BE63: 154.65105 | BF63: 156.88613 | BG63: 158.9501 | BH63: 160.82322 | BI63: 162.47759 | BJ63: 163.87689 | BK63: 165.33957 | BL63: 166.87679 | BM63: 168.50175 | BN63: 170.22961 | BO63: 171.76607 | BP63: 173.12713 | BQ63: 174.30151 | BR63: 175.24776 | BS63: 176.79982 | BT63: 178.98899 | BU63: 181.82344 | BV63: 185.2874 | BW63: 188.48137 | BX63: 191.41278 | BY63: 194.08745 | BZ63: 196.50959 | CA63: 198.71973 | CB63: 200.71561 | CC63: 202.49508 | CD63: 204.05611 | CE63: 205.77559 | CF63: 207.6582 | CG63: 209.70611 | CH63: 212.90908 | CI63: 215.59049 | CJ63: 218.16658 | CK63: 220.64084 | CL63: 223.01537 | CM63: 226.23377 | CN63: 230.28139 | CO63: 235.11947 | CP63: 247.28534 | CQ63: 249.57287 | CR63: 252.91714 | CS63: 244.72165 | CT63: 262.96247 | CU63: 271.00627 | CV63: 279.1012 | CW63: 286.53006 | CX63: 289.07797 | CY63: 297.8784 | CZ63: 304.78825 | DA63: 318.73744 | DD63: 6.4532038 | DG63: =+SUM(CT63:CW63) -> 1099.6 | DH63: =+SUM(CX63:DA63) -> 1210.4821 | DK63: =+DG63*(1+DD14/100) -> 1137.1025
A64: Sylviculture | B64: 78.024403 | C64: 81.273487 | D64: 76.16717 | E64: 73.895896 | F64: 76.735668 | G64: 78.420184 | H64: 76.444695 | I64: 76.042317 | J64: 83.29001 | K64: 86.257109 | L64: 86.015512 | M64: 83.312636 | N64: 83.33562 | O64: 84.454931 | P64: 80.451448 | Q64: 81.496791 | R64: 84.303077 | S64: 91.487713 | T64: 92.752728 | U64: 99.185116 | V64: 104.17434 | W64: 108.87509 | X64: 109.2879 | Y64: 103.75931 | Z64: 94.96755 | AA64: 92.503968 | AB64: 93.814791 | AC64: 96.014081 | AD64: 94.349909 | AE64: 94.884766 | AF64: 94.609803 | AG64: 96.936727 | AH64: 106.74824 | AI64: 110.81396 | AJ64: 114.12988 | AK64: 115.02705 | AL64: 119.79431 | AM64: 127.59641 | AN64: 128.50948 | AO64: 126.63367 | AP64: 118.97811 | AQ64: 120.0319 | AR64: 121.24172 | AS64: 122.44835 | AT64: 131.41621 | AU64: 135.40389 | AV64: 136.6616 | AW64: 135.4575 | AX64: 134.99542 | AY64: 140.54672 | AZ64: 139.68594 | BA64: 138.40089 | BB64: 146.60769 | BC64: 150.23914 | BD64: 149.83496 | BE64: 146.66978 | BF64: 158.71835 | BG64: 158.14152 | BH64: 161.92414 | BI64: 160.97038 | BJ64: 174.53554 | BK64: 172.04558 | BL64: 184.58639 | BM64: 197.32457 | BN64: 201.45432 | BO64: 203.39052 | BP64: 187.0254 | BQ64: 182.01846 | BR64: 180.88583 | BS64: 185.95253 | BT64: 189.23845 | BU64: 190.98519 | BV64: 189.07041 | BW64: 192.15131 | BX64: 197.16979 | BY64: 198.74249 | BZ64: 199.20316 | CA64: 205.73156 | CB64: 192.95435 | CC64: 194.31694 | CD64: 198.63376 | CE64: 224.54721 | CF64: 226.74112 | CG64: 235.8129 | CH64: 226.22635 | CI64: 235.64587 | CJ64: 224.76593 | CK64: 227.17885 | CL64: 228.80338 | CM64: 228.94478 | CN64: 239.9761 | CO64: 243.20374 | CP64: 246.61837 | CQ64: 270.88639 | CR64: 258.24302 | CS64: 251.84422 | CT64: 249.19232 | CU64: 263.97135 | CV64: 305.88491 | CW64: 306.18642 | CX64: 248.41379 | CY64: 259.26671 | CZ64: 282.40836 | DA64: 280.72489 | DD64: -4.2736977 | DG64: =+SUM(CT64:CW64) -> 1125.235 | DH64: =+SUM(CX64:DA64) -> 1070.8138 | DK64: =+DG64*(1+DD15/100) -> 1118.6202
A65: Secteur secondaire | B65: 493.08087 | C65: 507.74022 | D65: 471.2188 | E65: 482.72806 | F65: 555.7423 | G65: 544.87663 | H65: 521.6047 | I65: 515.25182 | J65: 527.59902 | K65: 536.86504 | L65: 507.275 | M65: 528.84852 | N65: 585.88575 | O65: 577.73018 | P65: 600.35244 | Q65: 602.78194 | R65: 640.90653 | S65: 660.13645 | T65: 666.66356 | U65: 664.62482 | V65: 678.01078 | W65: 701.02294 | X65: 686.39479 | Y65: 682.27144 | Z65: 744.75296 | AA65: 720.84149 | AB65: 714.62528 | AC65: 696.54133 | AD65: 785.68907 | AE65: 769.1384 | AF65: 753.39132 | AG65: 827.52181 | AH65: 800.75225 | AI65: 765.44547 | AJ65: 783.0047 | AK65: 757.40814 | AL65: 844.42318 | AM65: 867.94832 | AN65: 849.32409 | AO65: 849.93367 | AP65: 869.63599 | AQ65: 877.27159 | AR65: 876.99479 | AS65: 858.79936 | AT65: 925.12917 | AU65: 875.77243 | AV65: 854.48367 | AW65: 862.19597 | AX65: 935.52391 | AY65: 898.95207 | AZ65: 939.56978 | BA65: 946.77138 | BB65: 1068.5843 | BC65: 1035.7516 | BD65: 1016.6669 | BE65: 978.12475 | BF65: 1144.4012 | BG65: 1075.2974 | BH65: 1120.5232 | BI65: 1114.5995 | BJ65: 1127.601 | BK65: 1106.3871 | BL65: 1144.4778 | BM65: 1240.2296 | BN65: 1118.2116 | BO65: 1148.3999 | BP65: 1220.4331 | BQ65: 1291.1441 | BR65: 1157.6286 | BS65: 1240.9377 | BT65: 1201.302 | BU65: 1245.8866 | BV65: 1278.0282 | BW65: 1268.8721 | BX65: 1247.778 | BY65: 1290.8877 | BZ65: 1359.3177 | CA65: 1394.6331 | CB65: 1367.386 | CC65: 1358.9402 | CD65: 1387.2647 | CE65: 1410.2713 | CF65: 1362.4462 | CG65: 1378.2568 | CH65: 1328.9936 | CI65: 1390.9124 | CJ65: 1364.3859 | CK65: 1322.3981 | CL65: 1513.6894 | CM65: 1582.5123 | CN65: 1464.7585 | CO65: 1552.5007 | CP65: 1839.7362 | CQ65: 1895.9392 | CR65: 1851.5815 | CS65: 1917.4691 | CT65: 1896.3244 | CU65: 1957.1957 | CV65: 1880.9693 | CW65: 1897.8516 | CX65: 1932.2225 | CY65: 2008.1643 | CZ65: 1941.1441 | DA65: 1870.3842 | DD65: 0.41037357 | DG65: =+SUM(CT65:CW65) -> 7632.341 | DH65: =+SUM(CX65:DA65) -> 7751.9151 | DK65: =+DG65*(1+DD16/100) -> 7720.2333
A66: Industries Extractives | B66: 83.542145 | C66: 81.241759 | D66: 72.406827 | E66: 60.240089 | F66: 130.88432 | G66: 117.62913 | H66: 111.10486 | I66: 111.78537 | J66: 92.519936 | K66: 95.214966 | L66: 91.790361 | M66: 86.872801 | N66: 101.00338 | O66: 96.303367 | P66: 100.35754 | Q66: 98.934117 | R66: 116.98695 | S66: 123.25677 | T66: 126.74949 | U66: 125.48117 | V66: 95.975786 | W66: 93.123416 | X66: 92.008682 | Y66: 81.150347 | Z66: 122.60089 | AA66: 113.55363 | AB66: 111.23766 | AC66: 110.26218 | AD66: 154.88953 | AE66: 147.75014 | AF66: 137.59994 | AG66: 131.62825 | AH66: 127.93552 | AI66: 125.20783 | AJ66: 130.56513 | AK66: 128.02592 | AL66: 176.93632 | AM66: 182.81164 | AN66: 194.86885 | AO66: 215.29927 | AP66: 150.65513 | AQ66: 159.56214 | AR66: 172.29235 | AS66: 159.56353 | AT66: 175.04497 | AU66: 153.24456 | AV66: 136.45054 | AW66: 127.36111 | AX66: 124.55435 | AY66: 125.30416 | AZ66: 127.06579 | BA66: 123.52004 | BB66: 184.24329 | BC66: 168.6165 | BD66: 162.36769 | BE66: 154.21501 | BF66: 171.30987 | BG66: 176.79886 | BH66: 215.36611 | BI66: 220.6111 | BJ66: 181.5997 | BK66: 183.85351 | BL66: 198.48373 | BM66: 221.20398 | BN66: 127.80169 | BO66: 170.68708 | BP66: 204.71755 | BQ66: 238.53255 | BR66: 120.71236 | BS66: 193.1423 | BT66: 184.00215 | BU66: 200.87819 | BV66: 219.65088 | BW66: 176.06144 | BX66: 143.97638 | BY66: 169.80029 | BZ66: 169.33402 | CA66: 216.83191 | CB66: 232.37379 | CC66: 253.13729 | CD66: 197.13674 | CE66: 236.98371 | CF66: 228.96181 | CG66: 252.18374 | CH66: 126.2979 | CI66: 128.49453 | CJ66: 129.87729 | CK66: 132.35727 | CL66: 239.9139 | CM66: 240.78627 | CN66: 226.31575 | CO66: 216.10608 | CP66: 438.89728 | CQ66: 441.40668 | CR66: 400.87183 | CS66: 458.81022 | CT66: 310.15857 | CU66: 307.61803 | CV66: 301.30703 | CW66: 315.74036 | CX66: 288.17189 | CY66: 282.79049 | CZ66: 278.05146 | DA66: 253.47262 | DD66: -2.4441725 | DG66: =+SUM(CT66:CW66) -> 1234.824 | DH66: =+SUM(CX66:DA66) -> 1102.4865 | DK66: =+DG66*(1+DD17/100) -> 1130.1083 | DM66: =+(DK66-DK67)/(DG66-DG67)-1 -> 0.08383381
A67: dont extraction d'hydrocarbure | B67: 76.405631 | C67: 73.625358 | D67: 65.85754 | E67: 52.571172 | F67: 123.33668 | G67: 108.99372 | H67: 102.6924 | I67: 104.83276 | J67: 84.110717 | K67: 86.348769 | L67: 84.80315 | M67: 79.461899 | N67: 91.923666 | O67: 87.362389 | P67: 90.588913 | Q67: 90.181095 | R67: 105.65063 | S67: 110.46927 | T67: 113.46026 | U67: 116.8881 | V67: 84.795276 | W67: 79.613366 | X67: 82.447502 | Y67: 73.134347 | Z67: 109.74903 | AA67: 101.22222 | AB67: 99.958108 | AC67: 100.38407 | AD67: 142.53623 | AE67: 135.29712 | AF67: 125.27033 | AG67: 118.48777 | AH67: 115.13516 | AI67: 112.05514 | AJ67: 116.8146 | AK67: 116.68557 | AL67: 165.25514 | AM67: 168.21881 | AN67: 182.16187 | AO67: 205.31432 | AP67: 137.23579 | AQ67: 145.63248 | AR67: 157.83124 | AS67: 145.90025 | AT67: 160.37322 | AU67: 138.10627 | AV67: 121.71497 | AW67: 113.97597 | AX67: 106.37011 | AY67: 111.30795 | AZ67: 110.07237 | BA67: 108.18221 | BB67: 167.46502 | BC67: 149.15542 | BD67: 144.04074 | BE67: 140.72423 | BF67: 146.62108 | BG67: 161.12779 | BH67: 196.11385 | BI67: 207.83915 | BJ67: 165.88149 | BK67: 167.88297 | BL67: 181.11342 | BM67: 197.09878 | BN67: 113.32825 | BO67: 156.4779 | BP67: 181.05859 | BQ67: 206.07386 | BR67: 109.59194 | BS67: 178.33789 | BT67: 172.18579 | BU67: 192.30437 | BV67: 201.64274 | BW67: 162.42997 | BX67: 133.07693 | BY67: 162.87436 | BZ67: 160.09144 | CA67: 205.755 | CB67: 221.65057 | CC67: 242.237 | CD67: 186.94652 | CE67: 226.62011 | CF67: 218.07646 | CG67: 240.32191 | CH67: 117.18826 | CI67: 118.57848 | CJ67: 118.63427 | CK67: 122.66899 | CL67: 229.24214 | CM67: 230.96127 | CN67: 218.64259 | CO67: 207.76901 | CP67: 429.25454 | CQ67: 429.88429 | CR67: 390.40756 | CS67: 448.49162 | CT67: 298.37194 | CU67: 294.7161 | CV67: 288.703 | CW67: 302.10696 | CX67: 274.35621 | CY67: 267.39671 | CZ67: 263.90386 | DA67: 237.47773 | DD67: -2.9563716 | DG67: =+SUM(CT67:CW67) -> 1183.898 | DH67: =+SUM(CX67:DA67) -> 1043.1345 | DK67: =+DG67*(1+DD18/100) -> 1074.9129
A68: Industrie Agro-alimentaire | B68: 143.35691 | C68: 158.33705 | D68: 146.1899 | E68: 156.17394 | F68: 159.06004 | G68: 154.53395 | H68: 150.7569 | I68: 152.99027 | J68: 155.12168 | K68: 166.98284 | L68: 155.41718 | M68: 163.86046 | N68: 185.89291 | O68: 187.07769 | P68: 190.00572 | Q68: 200.92734 | R68: 211.15741 | S68: 210.02997 | T68: 197.69539 | U68: 205.39436 | V68: 205.73178 | W68: 199.66048 | X68: 195.89223 | Y68: 196.81868 | Z68: 207.09979 | AA68: 193.18986 | AB68: 191.39517 | AC68: 187.44671 | AD68: 195.58407 | AE68: 193.78708 | AF68: 185.59362 | AG68: 204.20851 | AH68: 224.61154 | AI68: 206.33362 | AJ68: 192.82157 | AK68: 203.96685 | AL68: 230.70628 | AM68: 237.01948 | AN68: 213.093 | AO68: 231.58484 | AP68: 253.12856 | AQ68: 263.77164 | AR68: 250.29633 | AS68: 260.22019 | AT68: 275.6574 | AU68: 248.87091 | AV68: 242.06213 | AW68: 257.01977 | AX68: 274.97943 | AY68: 269.92613 | AZ68: 255.66627 | BA68: 266.1958 | BB68: 290.50716 | BC68: 272.72808 | BD68: 283.70747 | BE68: 301.93413 | BF68: 317.36753 | BG68: 313.32667 | BH68: 300.68243 | BI68: 330.74514 | BJ68: 323.27403 | BK68: 317.34178 | BL68: 307.21036 | BM68: 329.03093 | BN68: 340.49744 | BO68: 328.72677 | BP68: 321.57336 | BQ68: 344.06639 | BR68: 343.50224 | BS68: 329.64479 | BT68: 326.67711 | BU68: 345.60087 | BV68: 361.06709 | BW68: 344.23992 | BX68: 319.5526 | BY68: 373.78138 | BZ68: 370.18154 | CA68: 376.8589 | CB68: 351.29325 | CC68: 322.09031 | CD68: 376.79132 | CE68: 359.84506 | CF68: 341.21471 | CG68: 314.92292 | CH68: 351.13576 | CI68: 387.80655 | CJ68: 368.51334 | CK68: 378.79735 | CL68: 407.63384 | CM68: 430.21873 | CN68: 402.61281 | CO68: 419.03662 | CP68: 444.70572 | CQ68: 475.59533 | CR68: 473.83756 | CS68: 485.41939 | CT68: 533.09323 | CU68: 544.63237 | CV68: 508.95573 | CW68: 521.87267 | CX68: 548.86401 | CY68: 569.42099 | CZ68: 542.88366 | DA68: 525.13336 | DD68: 0.85724904 | DG68: =+SUM(CT68:CW68) -> 2108.554 | DH68: =+SUM(CX68:DA68) -> 2186.302 | DK68: =+DG68*(1+DD19/100) -> 2167.7193 | DM68: =+(DK68+DK69)/(DG68+DG69)-1 -> 0.023000096
A69: Autres Industries Manufacturières | B69: 125.84989 | C69: 123.7237 | D69: 120.21082 | E69: 124.73158 | F69: 125.68643 | G69: 126.20144 | H69: 116.96349 | I69: 119.98641 | J69: 133.95934 | K69: 125.32638 | L69: 125.7245 | M69: 139.20449 | N69: 144.85296 | O69: 139.36933 | P69: 145.15367 | Q69: 144.53624 | R69: 147.6344 | S69: 148.66104 | T69: 152.35871 | U69: 170.0057 | V69: 175.3671 | W69: 173.08163 | X69: 185.93089 | Y69: 197.46637 | Z69: 190.89625 | AA69: 188.23924 | AB69: 194.08239 | AC69: 193.34988 | AD69: 200.99881 | AE69: 196.8081 | AF69: 206.48566 | AG69: 267.67893 | AH69: 230.31139 | AI69: 222.00538 | AJ69: 242.16789 | AK69: 219.7592 | AL69: 230.50817 | AM69: 205.69847 | AN69: 214.29339 | AO69: 205.4168 | AP69: 237.04161 | AQ69: 229.69811 | AR69: 232.57683 | AS69: 227.91448 | AT69: 233.93491 | AU69: 233.46959 | AV69: 237.80865 | AW69: 247.42552 | AX69: 265.65165 | AY69: 263.59822 | AZ69: 291.75793 | BA69: 304.73491 | BB69: 332.66679 | BC69: 321.79573 | BD69: 300.79784 | BE69: 287.26606 | BF69: 327.75991 | BG69: 312.84165 | BH69: 309.96166 | BI69: 324.20206 | BJ69: 329.03126 | BK69: 314.64186 | BL69: 334.68778 | BM69: 352.38893 | BN69: 356.98773 | BO69: 350.87242 | BP69: 352.03437 | BQ69: 337.93264 | BR69: 352.30771 | BS69: 354.04856 | BT69: 359.26304 | BU69: 362.6007 | BV69: 348.76282 | BW69: 365.3512 | BX69: 375.24928 | BY69: 386.3477 | BZ69: 438.8846 | CA69: 414.74056 | CB69: 377.064 | CC69: 387.41584 | CD69: 413.51894 | CE69: 399.40375 | CF69: 378.67445 | CG69: 396.80986 | CH69: 412.35205 | CI69: 411.74638 | CJ69: 402.37258 | CK69: 380.65698 | CL69: 419.82457 | CM69: 413.26186 | CN69: 405.61891 | CO69: 420.68966 | CP69: 478.07066 | CQ69: 446.10226 | CR69: 460.74831 | CS69: 432.25977 | CT69: 482.32594 | CU69: 490.85587 | CV69: 488.91396 | CW69: 460.90923 | CX69: 503.65555 | CY69: 513.68726 | CZ69: 516.84861 | DA69: 444.48202 | DD69: 1.1299118 | DG69: =+SUM(CT69:CW69) -> 1923.005 | DH69: =+SUM(CX69:DA69) -> 1978.6734 | DK69: =+DG69*(1+DD20/100) -> 1956.566
A70: Electricité | B70: 12.405488 | C70: 12.618567 | D70: 12.320756 | E70: 13.146536 | F70: 13.529677 | G70: 13.210948 | H70: 13.022214 | I70: 13.142611 | J70: 12.767231 | K70: 12.098636 | L70: 12.528147 | M70: 12.645441 | N70: 11.579527 | O70: 12.49319 | P70: 14.889612 | Q70: 15.772943 | R70: 13.523954 | S70: 12.877451 | T70: 13.675358 | U70: 17.208166 | V70: 17.238516 | W70: 16.32945 | X70: 18.358068 | Y70: 19.594649 | Z70: 17.554957 | AA70: 18.665786 | AB70: 18.570086 | AC70: 19.373605 | AD70: 19.644104 | AE70: 20.003833 | AF70: 20.387247 | AG70: 21.612977 | AH70: 21.628123 | AI70: 20.655959 | AJ70: 21.582896 | AK70: 22.203109 | AL70: 21.075421 | AM70: 21.655391 | AN70: 22.339825 | AO70: 23.781694 | AP70: 21.997351 | AQ70: 22.840177 | AR70: 23.424283 | AS70: 23.733624 | AT70: 23.909092 | AU70: 23.137264 | AV70: 25.066666 | AW70: 27.088921 | AX70: 28.065907 | AY70: 29.320564 | AZ70: 32.540944 | BA70: 33.825511 | BB70: 32.293124 | BC70: 32.353631 | BD70: 35.904882 | BE70: 35.091479 | BF70: 36.358187 | BG70: 39.02937 | BH70: 39.244074 | BI70: 39.84579 | BJ70: 50.012685 | BK70: 48.730316 | BL70: 47.234421 | BM70: 49.245382 | BN70: 51.817321 | BO70: 52.018013 | BP70: 51.090212 | BQ70: 43.518168 | BR70: 53.110961 | BS70: 50.253918 | BT70: 50.668577 | BU70: 54.569544 | BV70: 57.360638 | BW70: 59.966492 | BX70: 60.881907 | BY70: 63.602963 | BZ70: 53.629897 | CA70: 51.716165 | CB70: 48.169948 | CC70: 48.49799 | CD70: 51.097621 | CE70: 50.084417 | CF70: 48.898299 | CG70: 51.955663 | CH70: 53.653696 | CI70: 51.99553 | CJ70: 51.681846 | CK70: 53.691927 | CL70: 53.369994 | CM70: 53.012789 | CN70: 51.605907 | CO70: 52.49831 | CP70: 51.739811 | CQ70: 48.685072 | CR70: 53.343213 | CS70: 55.418904 | CT70: 60.437301 | CU70: 61.303224 | CV70: 61.487088 | CW70: 64.398387 | CX70: 64.61403 | CY70: 64.457357 | CZ70: 63.338147 | DA70: 66.475702 | DD70: 0.5122624 | DG70: =+SUM(CT70:CW70) -> 247.626 | DH70: =+SUM(CX70:DA70) -> 258.88524 | DK70: =+DG70*(1+DD21/100) -> 257.56582 | DM70: =+(DK70+DK71)/(DG70+DG71)-1 -> 0.032705342
A71: Eau et Assainissement | B71: 11.551367 | C71: 11.655813 | D71: 11.473821 | E71: 11.883142 | F71: 12.038946 | G71: 11.93044 | H71: 11.999019 | I71: 12.347696 | J71: 12.395147 | K71: 12.349096 | L71: 12.843441 | M71: 13.066624 | N71: 12.065553 | O71: 12.33541 | P71: 13.098411 | Q71: 12.658791 | R71: 10.875856 | S71: 10.210812 | T71: 11.034517 | U71: 14.128881 | V71: 16.675662 | W71: 17.970396 | X71: 20.293257 | Y71: 21.339209 | Z71: 19.467921 | AA71: 19.7525 | AB71: 19.414804 | AC71: 19.773116 | AD71: 19.954275 | AE71: 20.152111 | AF71: 20.310782 | AG71: 20.905516 | AH71: 20.758714 | AI71: 20.198475 | AJ71: 20.817433 | AK71: 21.389706 | AL71: 21.099208 | AM71: 21.545343 | AN71: 21.782971 | AO71: 22.17526 | AP71: 21.935815 | AQ71: 22.048188 | AR71: 22.293495 | AS71: 22.701101 | AT71: 21.958097 | AU71: 21.845604 | AV71: 22.880773 | AW71: 23.525963 | AX71: 23.172279 | AY71: 23.257615 | AZ71: 24.469401 | BA71: 25.066846 | BB71: 24.710297 | BC71: 24.967877 | BD71: 26.683416 | BE71: 26.435205 | BF71: 27.108274 | BG71: 25.793063 | BH71: 26.85411 | BI71: 28.965527 | BJ71: 28.286369 | BK71: 28.295779 | BL71: 28.41289 | BM71: 29.802874 | BN71: 30.285394 | BO71: 30.976406 | BP71: 31.47683 | BQ71: 32.770487 | BR71: 32.146109 | BS71: 31.584879 | BT71: 30.576792 | BU71: 32.15522 | BV71: 30.949187 | BW71: 32.346849 | BX71: 32.646704 | BY71: 33.52326 | BZ71: 32.533954 | CA71: 32.705504 | CB71: 32.781634 | CC71: 32.728909 | CD71: 31.701011 | CE71: 34.110478 | CF71: 34.063857 | CG71: 36.039654 | CH71: 33.315595 | CI71: 35.040016 | CJ71: 36.406752 | CK71: 35.405637 | CL71: 35.145954 | CM71: 35.157652 | CN71: 35.787232 | CO71: 34.195162 | CP71: 34.757447 | CQ71: 35.73707 | CR71: 37.276134 | CS71: 35.367348 | CT71: 36.418 | CU71: 37.579067 | CV71: 37.878803 | CW71: 37.146131 | CX71: 37.659902 | CY71: 38.254171 | CZ71: 38.670048 | DA71: 37.455131 | DD71: -0.01015007 | DG71: =+SUM(CT71:CW71) -> 149.022 | DH71: =+SUM(CX71:DA71) -> 152.03925 | DK71: =+DG71*(1+DD22/100) -> 152.05469
A72: BTP | B72: 116.37507 | C72: 120.16333 | D72: 108.61668 | E72: 116.55277 | F72: 114.54288 | G72: 121.37071 | H72: 117.75822 | I72: 104.99946 | J72: 120.83569 | K72: 124.89311 | L72: 108.97136 | M72: 113.1987 | N72: 130.49142 | O72: 130.15121 | P72: 136.84749 | Q72: 129.95251 | R72: 140.72795 | S72: 155.10042 | T72: 165.15008 | U72: 132.40654 | V72: 167.02194 | W72: 200.85757 | X72: 173.91166 | Y72: 165.90219 | Z72: 187.13315 | AA72: 187.44047 | AB72: 179.92516 | AC72: 166.33584 | AD72: 194.61827 | AE72: 190.63714 | AF72: 183.01406 | AG72: 181.48762 | AH72: 175.50697 | AI72: 171.04421 | AJ72: 175.04978 | AK72: 162.06336 | AL72: 164.09778 | AM72: 199.21799 | AN72: 182.94606 | AO72: 151.67582 | AP72: 184.87754 | AQ72: 179.35134 | AR72: 176.1115 | AS72: 164.66644 | AT72: 194.62471 | AU72: 195.2045 | AV72: 190.21491 | AW72: 179.77468 | AX72: 219.10029 | AY72: 187.54538 | AZ72: 208.06944 | BA72: 193.42827 | BB72: 204.16365 | BC72: 215.28974 | BD72: 207.20564 | BE72: 173.18287 | BF72: 264.4974 | BG72: 207.50781 | BH72: 228.41479 | BI72: 170.22992 | BJ72: 215.39695 | BK72: 213.52389 | BL72: 228.44862 | BM72: 258.55747 | BN72: 210.82205 | BO72: 215.11918 | BP72: 259.54082 | BQ72: 294.32388 | BR72: 255.84922 | BS72: 282.26328 | BT72: 250.11438 | BU72: 250.08211 | BV72: 260.23758 | BW72: 290.90618 | BX72: 315.47114 | BY72: 263.8321 | BZ72: 294.75365 | CA72: 301.78011 | CB72: 325.70334 | CC72: 315.0699 | CD72: 317.01908 | CE72: 329.84384 | CF72: 330.63309 | CG72: 326.34499 | CH72: 352.23861 | CI72: 375.82934 | CJ72: 375.53412 | CK72: 341.48894 | CL72: 357.80118 | CM72: 410.07498 | CN72: 342.81792 | CO72: 409.97491 | CP72: 391.56528 | CQ72: 448.41274 | CR72: 425.50449 | CS72: 450.1935 | CT72: 473.89139 | CU72: 515.2071 | CV72: 482.42665 | CW72: 497.78486 | CX72: 489.25708 | CY72: 539.55401 | CZ72: 501.35221 | DA72: 543.36539 | DD72: 0.84180668 | DG72: =+SUM(CT72:CW72) -> 1969.31 | DH72: =+SUM(CX72:DA72) -> 2073.5287 | DK72: =+DG72*(1+DD23/100) -> 2056.2193
A73: Secteur tertiaire | B73: 808.77877 | C73: 833.24243 | D73: 804.25839 | E73: 805.35217 | F73: 825.9531 | G73: 842.7103 | H73: 842.41 | I73: 868.14788 | J73: 900.02233 | K73: 927.25478 | L73: 942.16552 | M73: 955.76665 | N73: 968.13832 | O73: 980.41862 | P73: 998.18813 | Q73: 1011.4556 | R73: 1015.5013 | S73: 1044.1036 | T73: 1074.0785 | U73: 1117.1836 | V73: 1154.6412 | W73: 1188.5153 | X73: 1198.0194 | Y73: 1235.1183 | Z73: 1222.638 | AA73: 1229.1171 | AB73: 1249.6038 | AC73: 1253.0078 | AD73: 1271.233 | AE73: 1284.9027 | AF73: 1307.0053 | AG73: 1372.7808 | AH73: 1360.6186 | AI73: 1397.0448 | AJ73: 1420.4931 | AK73: 1445.3795 | AL73: 1485.0617 | AM73: 1521.8544 | AN73: 1547.3613 | AO73: 1576.6942 | AP73: 1632.7235 | AQ73: 1657.7773 | AR73: 1672.26 | AS73: 1687.4676 | AT73: 1681.9513 | AU73: 1688.4869 | AV73: 1731.4131 | AW73: 1789.5435 | AX73: 1797.2536 | AY73: 1840.876 | AZ73: 1900.2838 | BA73: 1934.5244 | BB73: 1963.3564 | BC73: 1929.3469 | BD73: 1954.722 | BE73: 1967.7728 | BF73: 2013.4473 | BG73: 2062.6231 | BH73: 2114.4089 | BI73: 2191.6742 | BJ73: 2218.6093 | BK73: 2206.037 | BL73: 2273.6339 | BM73: 2361.6441 | BN73: 2314.7415 | BO73: 2330.7748 | BP73: 2373.2326 | BQ73: 2419.0562 | BR73: 2431.9668 | BS73: 2495.8805 | BT73: 2552.6803 | BU73: 2632.2273 | BV73: 2577.2164 | BW73: 2624.6207 | BX73: 2652.4316 | BY73: 2702.1863 | BZ73: 2708.5537 | CA73: 2780.6413 | CB73: 2811.7599 | CC73: 2899.836 | CD73: 2894.8555 | CE73: 2971.386 | CF73: 2974.8901 | CG73: 3019.3825 | CH73: 3014.3907 | CI73: 2995.5358 | CJ73: 3054.3176 | CK73: 3083.5059 | CL73: 3116.6878 | CM73: 3158.0608 | CN73: 3196.0364 | CO73: 3244.4389 | CP73: 3348.1849 | CQ73: 3362.7998 | CR73: 3469.0219 | CS73: 3486.2605 | CT73: 3594.7509 | CU73: 3733.4934 | CV73: 3786.7937 | CW73: 3885.858 | CX73: 3922.7454 | CY73: 4067.4853 | CZ73: 4143.0302 | DA73: 4337.5954 | DD73: 5.1043211 | DG73: =+SUM(CT73:CW73) -> 15000.896 | DH73: =+SUM(CX73:DA73) -> 16470.856 | DK73: =+DG73*(1+DD24/100) -> 15670.96
A74: Commerce et réparation | B74: 153.22558 | C74: 161.49041 | D74: 151.67434 | E74: 152.5489 | F74: 153.45128 | G74: 160.81668 | H74: 152.55644 | I74: 160.03206 | J74: 176.41402 | K74: 185.12185 | L74: 187.17269 | M74: 186.51681 | N74: 184.24911 | O74: 190.87485 | P74: 196.07189 | Q74: 198.87677 | R74: 193.80128 | S74: 201.23719 | T74: 205.81241 | U74: 219.41789 | V74: 221.42117 | W74: 231.94439 | X74: 228.80515 | Y74: 250.79708 | Z74: 233.12588 | AA74: 232.48392 | AB74: 243.49934 | AC74: 245.81266 | AD74: 250.92083 | AE74: 254.72034 | AF74: 260.18264 | AG74: 297.23929 | AH74: 263.58979 | AI74: 274.39876 | AJ74: 284.21633 | AK74: 299.00567 | AL74: 325.83431 | AM74: 345.73102 | AN74: 350.47672 | AO74: 349.12225 | AP74: 359.22192 | AQ74: 354.34964 | AR74: 353.24997 | AS74: 374.14555 | AT74: 379.40257 | AU74: 388.81253 | AV74: 413.82483 | AW74: 436.20185 | AX74: 407.29387 | AY74: 403.59798 | AZ74: 425.08871 | BA74: 432.79333 | BB74: 458.83366 | BC74: 443.58334 | BD74: 432.03339 | BE74: 416.96951 | BF74: 441.7286 | BG74: 446.84799 | BH74: 457.83267 | BI74: 478.03904 | BJ74: 475.90412 | BK74: 490.09607 | BL74: 486.5328 | BM74: 543.95618 | BN74: 493.62035 | BO74: 499.88954 | BP74: 511.10229 | BQ74: 529.12063 | BR74: 509.40363 | BS74: 551.81994 | BT74: 556.10657 | BU74: 619.74686 | BV74: 529.19125 | BW74: 575.67715 | BX74: 593.18167 | BY74: 572.61792 | BZ74: 574.30204 | CA74: 615.80658 | CB74: 598.15027 | CC74: 610.13411 | CD74: 599.49406 | CE74: 648.23051 | CF74: 634.9641 | CG74: 669.17333 | CH74: 636.32921 | CI74: 640.80934 | CJ74: 651.5929 | CK74: 634.20855 | CL74: 652.45756 | CM74: 676.2715 | CN74: 677.75245 | CO74: 698.91749 | CP74: 725.29571 | CQ74: 754.84462 | CR74: 826.51718 | CS74: 791.4945 | CT74: 787.42789 | CU74: 858.77509 | CV74: 832.4813 | CW74: 826.49272 | CX74: 832.66023 | CY74: 918.90146 | CZ74: 891.59987 | DA74: 924.49979 | DD74: 4.14415 | DG74: =+SUM(CT74:CW74) -> 3305.177 | DH74: =+SUM(CX74:DA74) -> 3567.6614 | DK74: =+DG74*(1+DD25/100) -> 3425.6954 | DM74: =+(DK74+DK77)/(DG74+DG77)-1 -> 0.042173113
A75: Transports | B75: 132.96235 | C75: 133.0251 | D75: 133.15869 | E75: 133.38033 | F75: 133.71874 | G75: 134.7582 | H75: 136.4612 | I75: 138.77734 | J75: 141.64599 | K75: 145.3692 | L75: 150.00184 | M75: 155.60782 | N75: 162.26007 | O75: 168.03973 | P75: 172.90458 | Q75: 176.80776 | R75: 179.69656 | S75: 186.74662 | T75: 198.03043 | U75: 213.63076 | V75: 233.63698 | W75: 247.50011 | X75: 255.09249 | Y75: 256.28756 | Z75: 250.94087 | AA75: 248.02564 | AB75: 247.72135 | AC75: 250.10065 | AD75: 255.10851 | AE75: 259.75854 | AF75: 264.08 | AG75: 268.0908 | AH75: 271.80021 | AI75: 274.48668 | AJ75: 276.16009 | AK75: 276.827 | AL75: 276.49074 | AM75: 279.84477 | AN75: 286.89374 | AO75: 297.65731 | AP75: 312.16788 | AQ75: 322.23601 | AR75: 327.79725 | AS75: 328.7827 | AT75: 325.11354 | AU75: 324.94891 | AV75: 328.3803 | AW75: 335.42064 | AX75: 346.00148 | AY75: 353.51732 | AZ75: 358.03184 | BA75: 359.49441 | BB75: 360.55549 | BC75: 350.78868 | BD75: 373.93815 | BE75: 382.80399 | BF75: 383.33069 | BG75: 394.07868 | BH75: 408.59425 | BI75: 426.86938 | BJ75: 419.7117 | BK75: 423.49988 | BL75: 459.31878 | BM75: 476.35387 | BN75: 478.38337 | BO75: 487.93295 | BP75: 504.13706 | BQ75: 487.22556 | BR75: 496.84354 | BS75: 501.69432 | BT75: 514.11677 | BU75: 530.92237 | BV75: 528.36387 | BW75: 530.21773 | BX75: 524.78647 | BY75: 540.66093 | BZ75: 547.4728 | CA75: 550.20147 | CB75: 559.47452 | CC75: 575.09621 | CD75: 580.13656 | CE75: 593.98072 | CF75: 594.26512 | CG75: 599.7916 | CH75: 613.33376 | CI75: 618.50573 | CJ75: 620.13514 | CK75: 629.90737 | CL75: 640.18885 | CM75: 642.28838 | CN75: 646.57541 | CO75: 642.21436 | CP75: 680.47685 | CQ75: 688.45061 | CR75: 697.83273 | CS75: 706.76381 | CT75: 740.69147 | CU75: 802.18458 | CV75: 832.81186 | CW75: 864.84309 | CX75: 862.10828 | CY75: 954.77955 | CZ75: 969.96477 | DA75: 1000.7599 | DD75: 14.254101 | DG75: =+SUM(CT75:CW75) -> 3240.531 | DH75: =+SUM(CX75:DA75) -> 3787.6125 | DK75: =+DG75*(1+DD26/100) -> 3315.0779 | DM75: =+(DK75+DK76)/(DG75+DG76)-1 -> 0.029312133
A76: Information et communication | B76: 28.38412 | C76: 29.123256 | D76: 30.610012 | E76: 32.860642 | F76: 35.897855 | G76: 38.770427 | H76: 41.427971 | I76: 43.800049 | J76: 45.789272 | K76: 47.137062 | L76: 48.001243 | M76: 48.44275 | N76: 48.414471 | O76: 48.910468 | P76: 49.952481 | Q76: 51.569207 | R76: 53.813867 | S76: 55.468523 | T76: 56.450843 | U76: 56.702456 | V76: 56.22366 | W76: 56.177026 | X76: 56.517152 | Y76: 57.207523 | Z76: 58.221324 | AA76: 59.371618 | AB76: 60.693887 | AC76: 62.279699 | AD76: 64.251317 | AE76: 66.71743 | AF76: 69.689296 | AG76: 73.186489 | AH76: 77.233209 | AI76: 80.669783 | AJ76: 83.441052 | AK76: 85.492983 | AL76: 86.772441 | AM76: 87.461503 | AN76: 87.580461 | AO76: 87.127364 | AP76: 86.078171 | AQ76: 85.46553 | AR76: 85.312473 | AS76: 85.593506 | AT76: 86.233404 | AU76: 87.878105 | AV76: 90.656336 | AW76: 94.648649 | AX76: 99.881866 | AY76: 100.42904 | AZ76: 96.122869 | BA76: 86.75833 | BB76: 103.33085 | BC76: 92.084099 | BD76: 94.62698 | BE76: 101.00269 | BF76: 94.467208 | BG76: 98.213534 | BH76: 102.7562 | BI76: 107.44552 | BJ76: 111.98041 | BK76: 100.63999 | BL76: 108.10253 | BM76: 104.9039 | BN76: 98.73724 | BO76: 98.34101 | BP76: 102.10093 | BQ76: 104.95304 | BR76: 107.18859 | BS76: 110.25795 | BT76: 116.31148 | BU76: 114.42798 | BV76: 122.0963 | BW76: 119.65834 | BX76: 120.00203 | BY76: 116.92733 | BZ76: 119.24669 | CA76: 117.17168 | CB76: 117.13329 | CC76: 121.45335 | CD76: 121.6897 | CE76: 114.38489 | CF76: 120.81973 | CG76: 127.02868 | CH76: 130.29989 | CI76: 119.1312 | CJ76: 127.85346 | CK76: 140.52745 | CL76: 130.49999 | CM76: 123.4479 | CN76: 122.78509 | CO76: 137.02102 | CP76: 141.37238 | CQ76: 130.47852 | CR76: 131.60733 | CS76: 141.29577 | CT76: 155.2441 | CU76: 143.57833 | CV76: 135.58789 | CW76: 156.86469 | CX76: 166.72732 | CY76: 150.94283 | CZ76: 142.3833 | DA76: 169.39198 | DD76: 0.063421697 | DG76: =+SUM(CT76:CW76) -> 591.275 | DH76: =+SUM(CX76:DA76) -> 629.44544 | DK76: =+DG76*(1+DD27/100) -> 629.04648
A77: Hébergement et restauration | B77: 78.047185 | C77: 78.669655 | D77: 79.926477 | E77: 81.841874 | F77: 84.453353 | G77: 86.334031 | H77: 87.417806 | I77: 87.648223 | J77: 86.979884 | K77: 86.911829 | L77: 87.506111 | M77: 88.783273 | N77: 90.722346 | O77: 93.123358 | P77: 96.037951 | Q77: 99.468242 | R77: 103.3679 | S77: 106.72089 | T77: 109.55616 | U77: 111.89243 | V77: 113.74157 | W77: 114.35103 | X77: 113.68982 | Y77: 111.8193 | Z77: 108.89154 | AA77: 108.72838 | AB77: 111.20364 | AC77: 116.19927 | AD77: 123.59703 | AE77: 128.97295 | AF77: 132.39445 | AG77: 133.90749 | AH77: 133.53743 | AI77: 133.79411 | AJ77: 134.68428 | AK77: 136.23655 | AL77: 138.5011 | AM77: 141.83026 | AN77: 146.18334 | AO77: 151.59498 | AP77: 158.1779 | AQ77: 163.16923 | AR77: 166.45379 | AS77: 168.03121 | AT77: 168.01896 | AU77: 168.47784 | AV77: 169.33729 | AW77: 170.55763 | AX77: 172.12884 | AY77: 176.19501 | AZ77: 182.83933 | BA77: 192.28392 | BB77: 178.87151 | BC77: 194.63858 | BD77: 199.4519 | BE77: 208.22152 | BF77: 207.43547 | BG77: 207.70423 | BH77: 202.97329 | BI77: 214.07615 | BJ77: 218.26196 | BK77: 217.11385 | BL77: 214.63524 | BM77: 224.72835 | BN77: 229.42539 | BO77: 232.46018 | BP77: 232.12241 | BQ77: 239.74824 | BR77: 236.80558 | BS77: 241.14659 | BT77: 244.61939 | BU77: 254.07545 | BV77: 257.54342 | BW77: 257.65684 | BX77: 258.31025 | BY77: 265.79048 | BZ77: 270.69765 | CA77: 276.23013 | CB77: 285.69691 | CC77: 298.62131 | CD77: 308.15529 | CE77: 315.84899 | CF77: 314.819 | CG77: 318.17473 | CH77: 305.14756 | CI77: 282.3237 | CJ77: 291.09971 | CK77: 308.17503 | CL77: 328.28738 | CM77: 321.27419 | CN77: 329.86027 | CO77: 341.31216 | CP77: 344.3155 | CQ77: 344.3481 | CR77: 372.56498 | CS77: 366.17142 | CT77: 387.31096 | CU77: 388.16201 | CV77: 407.13334 | CW77: 408.7717 | CX77: 405.86597 | CY77: 403.18069 | CZ77: 420.58181 | DA77: 457.01624 | DD77: 0.55337766 | DG77: =+SUM(CT77:CW77) -> 1591.378 | DH77: =+SUM(CX77:DA77) -> 1686.6447 | DK77: =+DG77*(1+DD28/100) -> 1677.3626
A78: Services financiers | B78: 19.559513 | C78: 20.216078 | D78: 20.127821 | E78: 21.09775 | F78: 20.820647 | G78: 21.042821 | H78: 21.03982 | I78: 21.991508 | J78: 20.575062 | K78: 20.701069 | L78: 21.733386 | M78: 22.821718 | N78: 23.031051 | O78: 23.946911 | P78: 26.311776 | Q78: 27.730357 | R78: 27.676647 | S78: 28.110725 | T78: 27.900383 | U78: 27.92649 | V78: 26.8137 | W78: 25.506237 | X78: 25.613599 | Y78: 27.401599 | Z78: 31.486704 | AA78: 32.719094 | AB78: 34.073117 | AC78: 34.265654 | AD78: 32.613064 | AE78: 31.265962 | AF78: 30.467805 | AG78: 33.188614 | AH78: 34.461849 | AI78: 36.013585 | AJ78: 38.792451 | AK78: 41.749354 | AL78: 44.960255 | AM78: 45.774284 | AN78: 46.61626 | AO78: 51.266546 | AP78: 50.47952 | AQ78: 49.6838 | AR78: 50.309916 | AS78: 48.828139 | AT78: 51.309845 | AU78: 51.720717 | AV78: 54.733515 | AW78: 63.930685 | AX78: 73.426432 | AY78: 85.197735 | AZ78: 91.515317 | BA78: 89.639273 | BB78: 74.340657 | BC78: 69.920075 | BD78: 67.335026 | BE78: 65.69643 | BF78: 70.985393 | BG78: 75.023889 | BH78: 79.721886 | BI78: 82.546438 | BJ78: 79.457494 | BK78: 78.703849 | BL78: 78.633458 | BM78: 79.305608 | BN78: 77.176913 | BO78: 80.564436 | BP78: 87.50531 | BQ78: 93.343691 | BR78: 95.358541 | BS78: 98.59305 | BT78: 102.83766 | BU78: 105.10875 | BV78: 103.55462 | BW78: 104.00333 | BX78: 104.84185 | BY78: 107.6772 | BZ78: 113.27171 | CA78: 120.15779 | CB78: 124.99955 | CC78: 129.02595 | CD78: 127.86687 | CE78: 127.46881 | CF78: 125.97835 | CG78: 127.84497 | CH78: 129.70806 | CI78: 129.02727 | CJ78: 128.20151 | CK78: 131.76417 | CL78: 141.93336 | CM78: 146.06412 | CN78: 143.23625 | CO78: 142.80127 | CP78: 158.49689 | CQ78: 154.10886 | CR78: 146.34295 | CS78: 148.0883 | CT78: 166.99113 | CU78: 163.78917 | CV78: 155.43556 | CW78: 160.50114 | CX78: 185.80377 | CY78: 178.52623 | CZ78: 168.91317 | DA78: 179.38715 | DD78: 0.1187709 | DG78: =+SUM(CT78:CW78) -> 646.717 | DH78: =+SUM(CX78:DA78) -> 712.63033 | DK78: =+DG78*(1+DD29/100) -> 711.78493 | DM78: =+(DK78+DK80)/(DG78+DG80)-1 -> 0.055478034
A79: Administrations publiques | B79: 162.5569 | C79: 173.97336 | D79: 158.44365 | E79: 155.83041 | F79: 161.83613 | G79: 164.89234 | H79: 165.94571 | I79: 172.22532 | J79: 179.24367 | K79: 185.50443 | L79: 188.46831 | M79: 191.95286 | N79: 190.38156 | O79: 186.7965 | P79: 186.80455 | Q79: 187.64593 | R79: 189.22536 | S79: 195.49194 | T79: 202.97562 | U79: 210.32734 | V79: 216.33579 | W79: 217.16104 | X79: 213.15135 | Y79: 213.58232 | Z79: 215.19728 | AA79: 215.39209 | AB79: 218.00676 | AC79: 216.13638 | AD79: 216.71072 | AE79: 219.82473 | AF79: 223.30554 | AG79: 226.40088 | AH79: 232.65126 | AI79: 238.31419 | AJ79: 238.67392 | AK79: 244.89395 | AL79: 252.02013 | AM79: 263.93295 | AN79: 272.98271 | AO79: 277.91914 | AP79: 288.48775 | AQ79: 297.20988 | AR79: 302.40514 | AS79: 302.99178 | AT79: 300.26488 | AU79: 302.06677 | AV79: 308.29433 | AW79: 313.80998 | AX79: 325.44815 | AY79: 336.9371 | AZ79: 347.73231 | BA79: 364.65024 | BB79: 370.31755 | BC79: 369.20386 | BD79: 369.49639 | BE79: 363.48351 | BF79: 375.41278 | BG79: 398.17334 | BH79: 411.16002 | BI79: 429.99917 | BJ79: 434.04772 | BK79: 437.33137 | BL79: 452.77632 | BM79: 455.05164 | BN79: 453.96799 | BO79: 440.74076 | BP79: 438.26343 | BQ79: 465.07007 | BR79: 493.70065 | BS79: 503.75146 | BT79: 515.55216 | BU79: 501.40073 | BV79: 529.05778 | BW79: 515.31863 | BX79: 514.77512 | BY79: 543.46546 | BZ79: 548.73929 | CA79: 554.76673 | CB79: 564.24728 | CC79: 581.8307 | CD79: 585.91532 | CE79: 589.09577 | CF79: 588.89671 | CG79: 571.2172 | CH79: 597.50924 | CI79: 603.56454 | CJ79: 609.54143 | CK79: 603.63079 | CL79: 600.6679 | CM79: 620.97916 | CN79: 630.63944 | CO79: 625.91249 | CP79: 656.66493 | CQ79: 654.54409 | CR79: 642.96662 | CS79: 669.41236 | CT79: 691.29512 | CU79: 708.8935 | CV79: 730.83597 | CW79: 750.9734 | CX79: 767.56232 | CY79: 756.37345 | CZ79: 819.28985 | DA79: 864.99051 | DD79: 5.3552727 | DG79: =+SUM(CT79:CW79) -> 2881.998 | DH79: =+SUM(CX79:DA79) -> 3208.2161 | DK79: =+DG79*(1+DD30/100) -> 3045.1405
A80: Autres services marchands | B80: 234.04311 | C80: 236.74457 | D80: 230.3174 | E80: 227.79226 | F80: 235.77511 | G80: 236.0958 | H80: 237.56105 | I80: 243.67338 | J80: 249.37443 | K80: 256.50934 | L80: 259.28194 | M80: 261.64141 | N80: 269.07971 | O80: 268.72679 | P80: 270.1049 | Q80: 269.35734 | R80: 267.91966 | S80: 270.32772 | T80: 273.35262 | U80: 277.28622 | V80: 286.46838 | W80: 295.87549 | X80: 305.14985 | Y80: 318.02286 | Z80: 324.7744 | AA80: 332.3964 | AB80: 334.40574 | AC80: 328.2135 | AD80: 328.03157 | AE80: 323.64273 | AF80: 326.88555 | AG80: 340.76723 | AH80: 347.34489 | AI80: 359.36766 | AJ80: 364.52496 | AK80: 361.17397 | AL80: 360.4827 | AM80: 357.27965 | AN80: 356.62807 | AO80: 362.0066 | AP80: 378.11035 | AQ80: 385.66318 | AR80: 386.73144 | AS80: 379.0947 | AT80: 371.60812 | AU80: 364.58202 | AV80: 366.18651 | AW80: 374.97405 | AX80: 373.07294 | AY80: 385.00185 | AZ80: 398.95344 | BA80: 408.90494 | BB80: 417.10665 | BC80: 409.12829 | BD80: 417.84022 | BE80: 429.59516 | BF80: 440.08711 | BG80: 442.58143 | BH80: 451.3706 | BI80: 452.69849 | BJ80: 479.24589 | BK80: 458.65196 | BL80: 473.63478 | BM80: 477.34457 | BN80: 483.4302 | BO80: 490.84587 | BP80: 498.00119 | BQ80: 499.59498 | BR80: 492.66628 | BS80: 488.61722 | BT80: 503.13631 | BU80: 506.54519 | BV80: 507.4092 | BW80: 522.08863 | BX80: 536.53418 | BY80: 555.04698 | BZ80: 534.82357 | CA80: 546.30696 | CB80: 562.05811 | CC80: 583.67436 | CD80: 571.59766 | CE80: 582.37626 | CF80: 595.1471 | CG80: 606.15198 | CH80: 602.06296 | CI80: 602.17407 | CJ80: 625.89341 | CK80: 635.29255 | CL80: 622.65278 | CM80: 627.73559 | CN80: 645.18752 | CO80: 656.26011 | CP80: 641.56265 | CQ80: 636.02495 | CR80: 651.1901 | CS80: 663.03431 | CT80: 665.79018 | CU80: 668.11073 | CV80: 692.50784 | CW80: 717.41125 | CX80: 702.01752 | CY80: 704.78108 | CZ80: 730.29746 | DA80: 741.54986 | DD80: 0.41137563 | DG80: =+SUM(CT80:CW80) -> 2743.82 | DH80: =+SUM(CX80:DA80) -> 2878.6459 | DK80: =+DG80*(1+DD31/100) -> 2866.8524
A81: TOTAL DES VA | B81: 1618.9264 | C81: 1710.0072 | D81: 1615.747 | E81: 1612.7163 | F81: 1694.6143 | G81: 1758.3977 | H81: 1714.8852 | I81: 1708.4399 | J81: 1777.1013 | K81: 1863.184 | L81: 1835.7631 | M81: 1843.579 | N81: 1896.1299 | O81: 1959.6999 | P81: 2001.7978 | Q81: 2041.248 | R81: 2027.4272 | S81: 2117.3435 | T81: 2154.6738 | U81: 2202.0262 | V81: 2241.707 | W81: 2353.1149 | X81: 2326.6286 | Y81: 2345.9562 | Z81: 2361.5537 | AA81: 2385.9433 | AB81: 2420.1773 | AC81: 2384.8537 | AD81: 2418.9809 | AE81: 2491.7521 | AF81: 2520.8954 | AG81: 2646.9473 | AH81: 2560.3636 | AI81: 2633.6842 | AJ81: 2676.3097 | AK81: 2675.9311 | AL81: 2784.8927 | AM81: 2887.02 | AN81: 2891.1438 | AO81: 2957.4444 | AP81: 2999.9602 | AQ81: 3072.9306 | AR81: 3090.5918 | AS81: 3122.1822 | AT81: 3116.2333 | AU81: 3147.5405 | AV81: 3197.6448 | AW81: 3298.0608 | AX81: 3289.1974 | AY81: 3354.88 | AZ81: 3473.7623 | BA81: 3486.1461 | BB81: 3597.7684 | BC81: 3634.5431 | BD81: 3655.9841 | BE81: 3590.5551 | BF81: 3807.1799 | BG81: 3851.0833 | BH81: 3955.3687 | BI81: 4009.2629 | BJ81: 4014.5798 | BK81: 4065.343 | BL81: 4192.8856 | BM81: 4428.7622 | BN81: 4225.5318 | BO81: 4353.0278 | BP81: 4408.1288 | BQ81: 4506.506 | BR81: 4344.9606 | BS81: 4598.9465 | BT81: 4616.6114 | BU81: 4843.1545 | BV81: 4628.3576 | BW81: 4821.0768 | BX81: 4840.9183 | BY81: 4850.6533 | BZ81: 4920.9625 | CA81: 5150.3574 | CB81: 5094.9261 | CC81: 5178.1049 | CD81: 5120.0296 | CE81: 5419.0738 | CF81: 5354.1942 | CG81: 5410.9214 | CH81: 5315.65 | CI81: 5405.7871 | CJ81: 5463.7594 | CK81: 5475.4964 | CL81: 5612.24 | CM81: 5820.0577 | CN81: 5741.4549 | CO81: 5888.0243 | CP81: 6247.0476 | CQ81: 6488.1009 | CR81: 6506.6325 | CS81: 6506.314 | CT81: 6591.0373 | CU81: 7005.4053 | CV81: 7053.485 | CW81: 7153.0654 | CX81: 7226.9245 | CY81: 7597.4081 | CZ81: 7670.9583 | DA81: 8111.2761 | DD81: 6.4864161 | DG81: =+SUM(CT81:CW81) -> 27802.993 | DH81: =+SUM(CX81:DA81) -> 30606.567 | DK81: =+DG81*(1+DD32/100) -> 28742.227
A82: Impôts et taxes | B82: 136.5244 | C82: 152.96623 | D82: 141.82619 | E82: 129.74422 | F82: 147.39242 | G82: 174.02728 | H82: 146.19231 | I82: 160.51983 | J82: 174.45825 | K82: 185.52036 | L82: 172.1706 | M82: 170.53082 | N82: 188.66742 | O82: 183.74634 | P82: 170.48089 | Q82: 172.2412 | R82: 173.31655 | S82: 189.48197 | T82: 195.97835 | U82: 200.89699 | V82: 170.55407 | W82: 166.1153 | X82: 151.74779 | Y82: 171.95484 | Z82: 173.57229 | AA82: 174.66007 | AB82: 188.57146 | AC82: 197.40102 | AD82: 201.31527 | AE82: 202.24455 | AF82: 201.39259 | AG82: 240.65974 | AH82: 200.04752 | AI82: 226.61017 | AJ82: 215.01106 | AK82: 264.9101 | AL82: 193.92502 | AM82: 203.43884 | AN82: 173.60023 | AO82: 269.48948 | AP82: 212.57197 | AQ82: 210.66976 | AR82: 195.34591 | AS82: 232.43976 | AT82: 220.53029 | AU82: 178.8401 | AV82: 192.9654 | AW82: 258.73889 | AX82: 229.2713 | AY82: 191.34088 | AZ82: 183.4373 | BA82: 226.7393 | BB82: 257.13709 | BC82: 225.58329 | BD82: 211.48905 | BE82: 222.798 | BF82: 255.29025 | BG82: 235.26685 | BH82: 215.13097 | BI82: 329.97046 | BJ82: 311.39339 | BK82: 301.64512 | BL82: 304.66852 | BM82: 346.84554 | BN82: 364.85073 | BO82: 395.89635 | BP82: 370.36797 | BQ82: 418.75717 | BR82: 426.31412 | BS82: 411.69792 | BT82: 378.58675 | BU82: 418.29421 | BV82: 385.06678 | BW82: 465.71051 | BX82: 414.97342 | BY82: 554.10829 | BZ82: 371.49077 | CA82: 467.64085 | CB82: 401.58865 | CC82: 618.25773 | CD82: 361.02996 | CE82: 456.76604 | CF82: 422.03022 | CG82: 699.61679 | CH82: 371.49204 | CI82: 413.06491 | CJ82: 485.96494 | CK82: 537.29211 | CL82: 468.9413 | CM82: 440.59945 | CN82: 458.88871 | CO82: 530.28955 | CP82: 465.81026 | CQ82: 511.54389 | CR82: 311.68966 | CS82: 624.8812 | CT82: 562.84695 | CU82: 514.60272 | CV82: 363.08226 | CW82: 647.87808 | CX82: 582.63549 | CY82: 549.26576 | CZ82: 411.64152 | DA82: 824.4379 | DD82: 8.4701024 | DG82: =+SUM(CT82:CW82) -> 2088.41 | DH82: =+SUM(CX82:DA82) -> 2367.9807 | DK82: =+DG82*(1+DD33/100) -> 2183.0722
A83: PIB | B83: 1755.4508 | C83: 1862.9735 | D83: 1757.5732 | E83: 1742.4605 | F83: 1842.0067 | G83: 1932.4249 | H83: 1861.0775 | I83: 1868.9598 | J83: 1951.5595 | K83: 2048.7043 | L83: 2007.9337 | M83: 2014.1098 | N83: 2084.7973 | O83: 2143.4463 | P83: 2172.2787 | Q83: 2213.4892 | R83: 2200.7438 | S83: 2306.8254 | T83: 2350.6522 | U83: 2402.9232 | V83: 2412.2611 | W83: 2519.2302 | X83: 2478.3764 | Y83: 2517.911 | Z83: 2535.126 | AA83: 2560.6033 | AB83: 2608.7487 | AC83: 2582.2547 | AD83: 2620.2961 | AE83: 2693.9966 | AF83: 2722.288 | AG83: 2887.6071 | AH83: 2760.4111 | AI83: 2860.2943 | AJ83: 2891.3208 | AK83: 2940.8412 | AL83: 2978.8177 | AM83: 3090.4589 | AN83: 3064.744 | AO83: 3226.9339 | AP83: 3212.5321 | AQ83: 3283.6004 | AR83: 3285.9377 | AS83: 3354.622 | AT83: 3336.7636 | AU83: 3326.3806 | AV83: 3390.6102 | AW83: 3556.7997 | AX83: 3518.4687 | AY83: 3546.2208 | AZ83: 3657.1996 | BA83: 3712.8854 | BB83: 3854.9055 | BC83: 3860.1264 | BD83: 3867.4732 | BE83: 3813.3531 | BF83: 4062.4702 | BG83: 4086.3501 | BH83: 4170.4997 | BI83: 4339.2333 | BJ83: 4325.9731 | BK83: 4366.9881 | BL83: 4497.5541 | BM83: 4775.6077 | BN83: 4590.3825 | BO83: 4748.9242 | BP83: 4778.4968 | BQ83: 4925.2631 | BR83: 4771.2747 | BS83: 5010.6444 | BT83: 4995.1982 | BU83: 5261.4487 | BV83: 5013.4244 | BW83: 5286.7873 | BX83: 5255.8917 | BY83: 5404.7616 | BZ83: 5292.4533 | CA83: 5617.9983 | CB83: 5496.5148 | CC83: 5796.3627 | CD83: 5481.0595 | CE83: 5875.8398 | CF83: 5776.2245 | CG83: 6110.5382 | CH83: 5687.1421 | CI83: 5818.852 | CJ83: 5949.7244 | CK83: 6012.7885 | CL83: 6081.1813 | CM83: 6260.6572 | CN83: 6200.3436 | CO83: 6418.3139 | CP83: 6712.8579 | CQ83: 6999.6447 | CR83: 6818.3222 | CS83: 7131.1952 | CT83: 7153.8843 | CU83: 7520.008 | CV83: 7416.5673 | CW83: 7800.9435 | CX83: 7809.5599 | CY83: 8146.6738 | CZ83: 8082.5999 | DA83: 8935.7141 | DC83: Déflateur du PIB | DD83: 6.6264481 | DG83: =+SUM(CT83:CW83) -> 29891.403 | DH83: =+SUM(CX83:DA83) -> 32974.548 | DK83: =+DG83*(1+DD34/100) -> 30925.299
DC85: Déflateur du Pib Hors Petrole | DD85: 6.9715256
A87: Emplois PIB trimestriel aux prix courants, Données brutes
A89: Libellé | B89: =B10 -> T1_1999 | C89: =C10 -> T2_1999 | D89: =D10 -> T3_1999 | E89: =E10 -> T4_1999 | F89: =F10 -> T1_2000 | G89: =G10 -> T2_2000 | H89: =H10 -> T3_2000 | I89: =I10 -> T4_2000 | ... BQ89: =BQ10 -> T4_2015 | BR89: T1_2016 | BS89: T2_2016 | BT89: T3_2016 | BU89: T4_2016 | BV89: T1_2017 | BW89: T2_2017 | BX89: T3_2017 | BY89: T4_2017 | BZ89: T1_2018 | CA89: T2_2018 | CB89: T3_2018 | CC89: T4_2018 | CD89: T1_2019 | CE89: T2_2019 | CF89: T3_2019 | CG89: T4_2019 | CH89: T1_2020 | CI89: T2_2020 | CJ89: T3_2020 | CK89: T4_2020 | CL89: T1_2021 | CM89: T2_2021 | CN89: T3_2021 | CO89: T4_2021 | CP89: T1_2022 | CQ89: T2_2022 | CR89: T3_2022 | CS89: T4_2022 | CT89: T1_2023 | CU89: T2_2023 | CV89: T3_2023 | CW89: T4_2023 | CX89: =CX10 -> T1_2024 | CY89: =CY10 -> T2_2024 | CZ89: =CZ10 -> T3_2024 | DA89: =DA10 -> T4_2024
A90: CF | B90: 1401.0519 | C90: 1498.857 | D90: 1428.0223 | E90: 1417.5101 | F90: 1474.463 | G90: 1549.8375 | H90: 1517.8696 | I90: 1538.0998 | J90: 1575.351 | K90: 1680.2503 | L90: 1671.2468 | M90: 1673.5673 | N90: 1724.9424 | O90: 1797.9864 | P90: 1809.8559 | Q90: 1822.7034 | R90: 1851.9698 | S90: 1948.6814 | T90: 1946.3287 | U90: 1965.2043 | V90: 1979.9791 | W90: 2034.4485 | X90: 2040.1551 | Y90: 2073.7644 | Z90: 2058.0023 | AA90: 2110.0799 | AB90: 2138.7274 | AC90: 2111.4248 | AD90: 2157.5766 | AE90: 2200.6652 | AF90: 2200.5547 | AG90: 2286.5606 | AH90: 2247.5053 | AI90: 2298.4398 | AJ90: 2334.9147 | AK90: 2382.2145 | AL90: 2491.2698 | AM90: 2618.6303 | AN90: 2581.7685 | AO90: 2586.914 | AP90: 2734.1007 | AQ90: 2809.8909 | AR90: 2771.9355 | AS90: 2778.2185 | AT90: 2787.2955 | AU90: 2840.8991 | AV90: 2883.6995 | AW90: 2958.0412 | AX90: 2988.5723 | AY90: 3026.4414 | AZ90: 3050.5084 | BA90: 3107.3541 | BB90: 3282.0215 | BC90: 3243.3164 | BD90: 3226.8487 | BE90: 3223.7239 | BF90: 3395.5733 | BG90: 3490.0517 | BH90: 3483.0315 | BI90: 3582.0111 | BJ90: 3686.7779 | BK90: 3720.1189 | BL90: 3785.7756 | BM90: 3878.1388 | BN90: 3957.914 | BO90: 4148.8771 | BP90: 4132.2504 | BQ90: 4006.9779 | BR90: 4028.9698 | BS90: 4206.5972 | BT90: 4231.6429 | BU90: 4148.893 | BV90: 4115.8378 | BW90: 4381.0917 | BX90: 4409.8427 | BY90: 4501.5799 | BZ90: 4470.6736 | CA90: 4697.8677 | CB90: 4663.1836 | CC90: 4725.166 | CD90: 4794.5179 | CE90: 5027.4549 | CF90: 5006.565 | CG90: 4868.9982 | CH90: 4828.8976 | CI90: 5079.4104 | CJ90: 5153.7838 | CK90: 5028.5341 | CL90: 5095.0038 | CM90: 5416.6323 | CN90: 5419.4312 | CO90: 5431.7257 | CP90: 5584.9195 | CQ90: 5806.9249 | CR90: 5776.2547 | CS90: 5939.6709 | CT90: 6061.673 | CU90: 6289.4293 | CV90: 6462.7644 | CW90: 6436.1673 | CX90: 6339.7954 | CY90: 6963.1207 | CZ90: 7011.7762 | DA90: 7052.5983 | DD90: 4.7000907
A91: CF_PRIVEE | B91: 1203.5144 | C91: 1288.0642 | D91: 1236.7364 | E91: 1229.4828 | F91: 1278.0352 | G91: 1349.2542 | H91: 1315.4368 | I91: 1327.6529 | J91: 1353.0497 | K91: 1448.0661 | L91: 1433.3816 | M91: 1429.6211 | N91: 1483.587 | O91: 1560.049 | P91: 1570.3877 | Q91: 1580.076 | R91: 1606.4648 | S91: 1693.9945 | T91: 1682.1052 | U91: 1692.9063 | V91: 1703.2094 | W91: 1759.2921 | X91: 1770.9443 | Y91: 1803.2989 | Z91: 1785.4105 | AA91: 1835.9305 | AB91: 1860.8497 | AC91: 1836.3761 | AD91: 1890.8527 | AE91: 1930.7754 | AF91: 1927.8106 | AG91: 2012.1098 | AH91: 1967.968 | AI91: 2012.1694 | AJ91: 2046.4668 | AK91: 2083.1006 | AL91: 2168.8892 | AM91: 2279.9438 | AN91: 2231.8478 | AO91: 2233.1175 | AP91: 2373.6578 | AQ91: 2441.6367 | AR91: 2397.9776 | AS91: 2401.5941 | AT91: 2409.6423 | AU91: 2457.0557 | AV91: 2490.5374 | AW91: 2559.3195 | AX91: 2573.5026 | AY91: 2600.3037 | AZ91: 2612.1051 | BA91: 2646.8953 | BB91: 2809.0151 | BC91: 2771.6978 | BD91: 2753.4689 | BE91: 2754.5114 | BF91: 2911.7586 | BG91: 2981.3867 | BH91: 2964.3904 | BI91: 3050.0595 | BJ91: 3159.2765 | BK91: 3191.4257 | BL91: 3236.6862 | BM91: 3316.9001 | BN91: 3376.5005 | BO91: 3573.5321 | BP91: 3557.0313 | BQ91: 3405.44 | BR91: 3418.9936 | BS91: 3596.149 | BT91: 3616.5617 | BU91: 3554.8537 | BV91: 3497.0561 | BW91: 3779.5664 | BX91: 3811.0262 | BY91: 3872.3853 | BZ91: 3830.7061 | CA91: 4047.5752 | CB91: 3997.7513 | CC91: 4034.2174 | CD91: 4090.7351 | CE91: 4316.47 | CF91: 4295.7945 | CG91: 4182.9014 | CH91: 4112.5358 | CI91: 4361.9687 | CJ91: 4429.4906 | CK91: 4304.2448 | CL91: 4361.6983 | CM91: 4657.1658 | CN91: 4653.7881 | CO91: 4684.0888 | CP91: 4840.919 | CQ91: 5081.1945 | CR91: 5070.6854 | CS91: 5208.3692 | CT91: 5302.6722 | CU91: 5510.2045 | CV91: 5660.0392 | CW91: 5613.2712 | CX91: 5457.5924 | CY91: 6110.4205 | CZ91: 6143.3385 | DA91: 6167.3904 | DD91: 4.7149011
A92: CF_PUBLIQUE | B92: 197.5375 | C92: 210.79286 | D92: 191.28595 | E92: 188.02739 | F92: 196.4278 | G92: 200.58333 | H92: 202.43277 | I92: 210.44689 | J92: 222.30132 | K92: 232.18422 | L92: 237.86518 | M92: 243.94619 | N92: 241.35541 | O92: 237.93742 | P92: 239.46821 | Q92: 242.62742 | R92: 245.505 | S92: 254.6869 | T92: 264.22352 | U92: 272.29807 | V92: 276.76966 | W92: 275.15639 | X92: 269.21072 | Y92: 270.46549 | Z92: 272.59178 | AA92: 274.14938 | AB92: 277.87768 | AC92: 275.04874 | AD92: 266.72393 | AE92: 269.88982 | AF92: 272.74411 | AG92: 274.45073 | AH92: 279.53724 | AI92: 286.27043 | AJ92: 288.44791 | AK92: 299.11392 | AL92: 322.38062 | AM92: 338.68648 | AN92: 349.92071 | AO92: 353.79649 | AP92: 360.44298 | AQ92: 368.25412 | AR92: 373.95788 | AS92: 376.62441 | AT92: 377.6532 | AU92: 383.84336 | AV92: 393.16214 | AW92: 398.72165 | AX92: 415.06964 | AY92: 426.13768 | AZ92: 438.4033 | BA92: 460.45881 | BB92: 473.0064 | BC92: 471.61859 | BD92: 473.37981 | BE92: 469.21243 | BF92: 483.81473 | BG92: 508.665 | BH92: 518.64112 | BI92: 531.95162 | BJ92: 527.50147 | BK92: 528.69326 | BL92: 549.08938 | BM92: 561.23866 | BN92: 581.41357 | BO92: 575.34501 | BP92: 575.2191 | BQ92: 601.53792 | BR92: 609.97625 | BS92: 610.44821 | BT92: 615.08121 | BU92: 594.03932 | BV92: 618.78164 | BW92: 601.5253 | BX92: 598.81647 | BY92: 629.19459 | BZ92: 639.96754 | CA92: 650.29249 | CB92: 665.43231 | CC92: 690.94867 | CD92: 703.78284 | CE92: 710.98482 | CF92: 710.77049 | CG92: 686.09684 | CH92: 716.36179 | CI92: 717.44173 | CJ92: 724.29317 | CK92: 724.28931 | CL92: 733.30546 | CM92: 759.46651 | CN92: 765.6431 | CO92: 747.63693 | CP92: 744.00052 | CQ92: 725.73043 | CR92: 705.5693 | CS92: 731.30175 | CT92: 759.00084 | CU92: 779.22486 | CV92: 802.72522 | CW92: 822.89609 | CX92: 882.20301 | CY92: 852.70017 | CZ92: 868.43764 | DA92: 885.20789 | DD92: 4.5988279
A93: INVESTISSEMENT | B93: 314.60042 | C93: 320.8172 | D93: 298.18319 | E93: 312.80178 | F93: 312.05943 | G93: 345.61964 | H93: 331.66975 | I93: 323.19955 | J93: 385.61281 | K93: 382.98847 | L93: 370.29636 | M93: 403.91925 | N93: 408.39692 | O93: 419.64498 | P93: 439.87671 | Q93: 413.09713 | R93: 404.07582 | S93: 434.03901 | T93: 449.61655 | U93: 412.92254 | V93: 461.17069 | W93: 501.07511 | X93: 466.94026 | Y93: 446.27298 | Z93: 487.87607 | AA93: 482.98499 | AB93: 471.7406 | AC93: 468.70247 | AD93: 480.9158 | AE93: 494.39906 | AF93: 486.50664 | AG93: 488.76633 | AH93: 513.85984 | AI93: 519.80459 | AJ93: 552.38871 | AK93: 542.23903 | AL93: 569.98394 | AM93: 669.20587 | AN93: 629.66534 | AO93: 590.45693 | AP93: 621.20494 | AQ93: 633.02837 | AR93: 598.91287 | AS93: 590.17916 | AT93: 609.70917 | AU93: 624.30593 | AV93: 644.51665 | AW93: 642.93715 | AX93: 679.92477 | AY93: 654.771 | AZ93: 696.79717 | BA93: 701.71582 | BB93: 729.50314 | BC93: 742.60543 | BD93: 700.38102 | BE93: 629.04206 | BF93: 833.52385 | BG93: 735.59606 | BH93: 797.12099 | BI93: 697.85739 | BJ93: 869.03274 | BK93: 813.41196 | BL93: 887.50489 | BM93: 922.11032 | BN93: 819.22582 | BO93: 814.3815 | BP93: 923.65994 | BQ93: 986.9867 | BR93: 976.80865 | BS93: 1008.2534 | BT93: 953.74446 | BU93: 960.22047 | BV93: 1013.9451 | BW93: 1014.9506 | BX93: 1071.5992 | BY93: 944.14313 | BZ93: 1067.467 | CA93: 1087.6678 | CB93: 1088.422 | CC93: 1097.2032 | CD93: 1142.0181 | CE93: 1083.9697 | CF93: 1090.5884 | CG93: 1120.2917 | CH93: 1033.0183 | CI93: 1057.1379 | CJ93: 1103.1843 | CK93: 1076.1204 | CL93: 1102.2765 | CM93: 1160.2451 | CN93: 1085.215 | CO93: 1192.4974 | CP93: 1217.6652 | CQ93: 1338.374 | CR93: 1306.7525 | CS93: 1342.1443 | CT93: 1429.1202 | CU93: 1478.1634 | CV93: 1366.6649 | CW93: 1443.7315 | CX93: 1407.5005 | CY93: 1558.1811 | CZ93: 1448.1199 | DA93: 1626.3671 | DD93: -0.28388896
A94: FBCF_PRIVEE | B94: 245.20278 | C94: 216.20129 | D94: 211.03055 | E94: 221.6882 | F94: 219.11013 | G94: 251.92219 | H94: 240.11961 | I94: 230.42509 | J94: 286.1998 | K94: 274.77786 | L94: 257.39162 | M94: 288.38816 | N94: 293.95556 | O94: 309.8176 | P94: 316.70081 | Q94: 285.42154 | R94: 286.90915 | S94: 313.61145 | T94: 327.45473 | U94: 292.0296 | V94: 336.38471 | W94: 364.40938 | X94: 330.91063 | Y94: 313.65441 | Z94: 349.64311 | AA94: 352.16759 | AB94: 339.40413 | AC94: 329.8791 | AD94: 340.70931 | AE94: 353.90062 | AF94: 349.70385 | AG94: 355.06211 | AH94: 377.94248 | AI94: 368.29045 | AJ94: 396.30148 | AK94: 384.0362 | AL94: 403.69348 | AM94: 497.56043 | AN94: 450.22567 | AO94: 412.81598 | AP94: 450.27965 | AQ94: 470.87916 | AR94: 431.93679 | AS94: 400.15735 | AT94: 410.1333 | AU94: 437.08719 | AV94: 477.24076 | AW94: 483.08522 | AX94: 509.71791 | AY94: 467.43587 | AZ94: 496.23282 | BA94: 488.37657 | BB94: 509.0038 | BC94: 539.33384 | BD94: 517.5266 | BE94: 445.89223 | BF94: 642.26515 | BG94: 521.9629 | BH94: 564.00548 | BI94: 461.81499 | BJ94: 632.23636 | BK94: 571.05678 | BL94: 634.35371 | BM94: 678.09006 | BN94: 580.36883 | BO94: 570.94145 | BP94: 673.52568 | BQ94: 723.88582 | BR94: 746.70367 | BS94: 776.882 | BT94: 765.6561 | BU94: 458.42023 | BV94: 877.07662 | BW94: 748.96917 | BX94: 880.93491 | BY94: 475.6593 | BZ94: 795.38242 | CA94: 741.68829 | CB94: 786.32267 | CC94: 781.14462 | CD94: 978.20342 | CE94: 754.36331 | CF94: 803.927 | CG94: 632.45727 | CH94: 770.3884 | CI94: 832.72382 | CJ94: 899.32492 | CK94: 866.74285 | CL94: 870.07188 | CM94: 921.10499 | CN94: 850.67298 | CO94: 939.67214 | CP94: 954.61946 | CQ94: 1074.1733 | CR94: 1028.9245 | CS94: 1078.2263 | CT94: 1186.2763 | CU94: 1241.1377 | CV94: 1138.772 | CW94: 1217.1365 | CX94: 1168.7727 | CY94: 1306.2204 | CZ94: 1201.317 | DA94: 1277.9292 | DD94: -0.47240523
A95: FBCF_PUBLIQUE | B95: 69.397639 | C95: 104.61592 | D95: 87.152639 | E95: 91.113581 | F95: 92.9493 | G95: 93.697452 | H95: 91.550136 | I95: 92.774455 | J95: 99.413012 | K95: 108.21061 | L95: 112.90474 | M95: 115.53109 | N95: 114.44136 | O95: 109.82737 | P95: 123.1759 | Q95: 127.67559 | R95: 117.16666 | S95: 120.42755 | T95: 122.16181 | U95: 120.89294 | V95: 124.78598 | W95: 136.66572 | X95: 136.02963 | Y95: 132.61858 | Z95: 138.23296 | AA95: 130.8174 | AB95: 132.33648 | AC95: 138.82336 | AD95: 140.20649 | AE95: 140.49843 | AF95: 136.80278 | AG95: 133.70422 | AH95: 135.91736 | AI95: 151.51414 | AJ95: 156.08724 | AK95: 158.20283 | AL95: 166.29047 | AM95: 171.64544 | AN95: 179.43968 | AO95: 177.64095 | AP95: 170.92529 | AQ95: 162.14921 | AR95: 166.97608 | AS95: 190.02181 | AT95: 199.57588 | AU95: 187.21875 | AV95: 167.27589 | AW95: 159.85194 | AX95: 170.20686 | AY95: 187.33514 | AZ95: 200.56435 | BA95: 213.33925 | BB95: 220.49935 | BC95: 203.27159 | BD95: 182.85442 | BE95: 183.14983 | BF95: 191.2587 | BG95: 213.63316 | BH95: 233.11551 | BI95: 236.04239 | BJ95: 236.79638 | BK95: 242.35518 | BL95: 253.15118 | BM95: 244.02025 | BN95: 238.85699 | BO95: 243.44005 | BP95: 250.13427 | BQ95: 263.10088 | BR95: 230.10499 | BS95: 231.37142 | BT95: 188.08836 | BU95: 501.80024 | BV95: 136.86846 | BW95: 265.98147 | BX95: 190.66424 | BY95: 468.48383 | BZ95: 272.08457 | CA95: 345.97947 | CB95: 302.09936 | CC95: 316.0586 | CD95: 163.81468 | CE95: 329.60643 | CF95: 286.66144 | CG95: 487.83445 | CH95: 262.62992 | CI95: 224.41412 | CJ95: 203.85936 | CK95: 209.3776 | CL95: 232.20461 | CM95: 239.14008 | CN95: 234.54207 | CO95: 252.82524 | CP95: 263.04573 | CQ95: 264.20071 | CR95: 277.82795 | CS95: 263.91803 | CT95: 242.84394 | CU95: 237.0257 | CV95: 227.8929 | CW95: 226.59491 | CX95: 238.72784 | CY95: 251.96065 | CZ95: 246.80286 | DA95: 348.43785 | DD95: 0.58530227
A96: Export | B96: 298.84165 | C96: 319.99351 | D96: 322.69409 | E96: 441.48751 | F96: 389.97071 | G96: 439.13719 | H96: 488.82918 | I96: 547.4347 | J96: 488.87762 | K96: 495.41598 | L96: 464.24753 | M96: 577.99137 | N96: 436.40238 | O96: 424.0029 | P96: 480.392 | Q96: 639.23305 | R96: 427.11341 | S96: 417.11769 | T96: 416.2176 | U96: 539.63177 | V96: 492.52532 | W96: 455.46124 | X96: 500.78084 | Y96: 591.15024 | Z96: 439.80953 | AA96: 476.6609 | AB96: 638.3166 | AC96: 733.54361 | AD96: 531.82053 | AE96: 538.46079 | AF96: 689.56802 | AG96: 881.52031 | AH96: 607.45117 | AI96: 711.00282 | AJ96: 794.84659 | AK96: 976.52751 | AL96: 803.34792 | AM96: 725.27069 | AN96: 856.79605 | AO96: 953.0771 | AP96: 538.25974 | AQ96: 651.37925 | AR96: 629.12021 | AS96: 753.72243 | AT96: 616.59665 | AU96: 699.05802 | AV96: 755.49044 | AW96: 973.38479 | AX96: 795.93374 | AY96: 700.80177 | AZ96: 919.58937 | BA96: 1081.1757 | BB96: 705.19341 | BC96: 855.31342 | BD96: 918.42501 | BE96: 1197.0947 | BF96: 855.45946 | BG96: 897.39356 | BH96: 929.41636 | BI96: 1255.6641 | BJ96: 987.96078 | BK96: 912.91871 | BL96: 961.09323 | BM96: 1379.8246 | BN96: 954.03891 | BO96: 838.99832 | BP96: 1005.2639 | BQ96: 1198.6766 | BR96: 788.81967 | BS96: 823.38703 | BT96: 858.92332 | BU96: 1326.174 | BV96: 979.94696 | BW96: 910.86145 | BX96: 950.17394 | BY96: 1005.5666 | BZ96: 925.69842 | CA96: 862.34993 | CB96: 953.2399 | CC96: 1418.7838 | CD96: 1071.0678 | CE96: 1056.116 | CF96: 1105.7453 | CG96: 1380.9589 | CH96: 978.13963 | CI96: 619.05366 | CJ96: 848.57955 | CK96: 1129.8521 | CL96: 996.08521 | CM96: 953.9664 | CN96: 977.26114 | CO96: 1193.3623 | CP96: 1214.7681 | CQ96: 1305.2489 | CR96: 1327.3595 | CS96: 1497.3825 | CT96: 1434.8532 | CU96: 1185.1618 | CV96: 1065.4941 | CW96: 1280.7229 | CX96: 1444.1599 | CY96: 1166.5165 | CZ96: 1029.2024 | DA96: 1580.3759 | DD96: 9.9465411
A97: Export_Biens | B97: 255.01348 | C97: 277.53291 | D97: 265.95519 | E97: 350.63865 | F97: 321.85951 | G97: 373.15125 | H97: 400.65404 | I97: 406.25096 | J97: 384.66085 | K97: 394.45108 | L97: 329.33099 | M97: 361.96651 | N97: 339.6024 | O97: 330.22336 | P97: 355.07707 | Q97: 438.58203 | R97: 348.74445 | S97: 341.19406 | T97: 314.76301 | U97: 377.18532 | V97: 360.06243 | W97: 327.13158 | X97: 329.29756 | Y97: 316.57566 | Z97: 314.69519 | AA97: 355.4505 | AB97: 476.34658 | AC97: 474.20142 | AD97: 406.23655 | AE97: 416.7954 | AF97: 526.99 | AG97: 621.20462 | AH97: 457.56428 | AI97: 565.79284 | AJ97: 600.8066 | AK97: 665.8357 | AL97: 657.28899 | AM97: 583.76922 | AN97: 667.71167 | AO97: 650.3202 | AP97: 403.80249 | AQ97: 521.11746 | AR97: 455.05496 | AS97: 475.01329 | AT97: 474.5159 | AU97: 561.41059 | AV97: 571.55654 | AW97: 678.87634 | AX97: 605.77789 | AY97: 516.5794 | AZ97: 673.41568 | BA97: 686.99912 | BB97: 515.13322 | BC97: 671.18341 | BD97: 672.38798 | BE97: 803.18725 | BF97: 651.96764 | BG97: 700.25238 | BH97: 665.93433 | BI97: 833.60138 | BJ97: 783.94972 | BK97: 715.26874 | BL97: 697.17969 | BM97: 958.01645 | BN97: 780.57989 | BO97: 670.96838 | BP97: 780.01249 | BQ97: 835.27694 | BR97: 673.35848 | BS97: 655.91249 | BT97: 650.50757 | BU97: 799.03346 | BV97: 759.60908 | BW97: 683.81206 | BX97: 630.93641 | BY97: 653.57945 | BZ97: 735.92312 | CA97: 638.13721 | CB97: 678.26134 | CC97: 928.70034 | CD97: 795.71061 | CE97: 832.10157 | CF97: 776.09787 | CG97: 901.59095 | CH97: 743.48917 | CI97: 443.5586 | CJ97: 564.81541 | CK97: 749.53081 | CL97: 726.26151 | CM97: 725.13192 | CN97: 744.55822 | CO97: 917.48134 | CP97: 973.05893 | CQ97: 1016.2846 | CR97: 1036.8284 | CS97: 1183.5571 | CT97: 986.15853 | CU97: 780.48052 | CV97: 839.22199 | CW97: 1114.413 | CX97: 1066.9479 | CY97: 812.2618 | CZ97: 814.23423 | DA97: 1419.0483 | DD97: 11.447485
A98: Export_Service | B98: 43.828172 | C98: 42.460605 | D98: 56.738904 | E98: 90.848858 | F98: 68.111207 | G98: 65.985938 | H98: 88.175139 | I98: 141.18374 | J98: 104.21677 | K98: 100.9649 | L98: 134.91654 | M98: 216.02486 | N98: 96.799976 | O98: 93.779534 | P98: 125.31493 | Q98: 200.65102 | R98: 78.368965 | S98: 75.923625 | T98: 101.45459 | U98: 162.44645 | V98: 132.46289 | W98: 128.32966 | X98: 171.48329 | Y98: 274.57458 | Z98: 125.11433 | AA98: 121.2104 | AB98: 161.97003 | AC98: 259.3422 | AD98: 125.58398 | AE98: 121.66539 | AF98: 162.57802 | AG98: 260.31569 | AH98: 149.88689 | AI98: 145.20998 | AJ98: 194.03999 | AK98: 310.69181 | AL98: 146.05894 | AM98: 141.50147 | AN98: 189.08438 | AO98: 302.75689 | AP98: 134.45725 | AQ98: 130.26179 | AR98: 174.06525 | AS98: 278.70914 | AT98: 142.08075 | AU98: 137.64743 | AV98: 183.93391 | AW98: 294.50845 | AX98: 190.15585 | AY98: 184.22237 | AZ98: 246.17369 | BA98: 394.17663 | BB98: 190.06019 | BC98: 184.13 | BD98: 246.03703 | BE98: 393.90745 | BF98: 203.49182 | BG98: 197.14117 | BH98: 263.48202 | BI98: 422.06277 | BJ98: 204.01105 | BK98: 197.64997 | BL98: 263.91354 | BM98: 421.80811 | BN98: 173.45903 | BO98: 168.02994 | BP98: 225.25146 | BQ98: 363.39962 | BR98: 115.46119 | BS98: 167.47454 | BT98: 208.41575 | BU98: 527.14052 | BV98: 220.33788 | BW98: 227.04939 | BX98: 319.23753 | BY98: 351.98719 | BZ98: 189.7753 | CA98: 224.21273 | CB98: 274.97856 | CC98: 490.08342 | CD98: 275.35718 | CE98: 224.01448 | CF98: 329.64744 | CG98: 479.3679 | CH98: 234.65046 | CI98: 175.49506 | CJ98: 283.76414 | CK98: 380.32134 | CL98: 269.8237 | CM98: 228.83447 | CN98: 232.70292 | CO98: 275.88091 | CP98: 241.70913 | CQ98: 288.96436 | CR98: 290.53111 | CS98: 313.82539 | CT98: 448.69469 | CU98: 404.68128 | CV98: 226.27214 | CW98: 166.3099 | CX98: 377.21202 | CY98: 354.25467 | CZ98: 214.96812 | DA98: 161.32763 | DD98: 4.7111912
A99: Import | B99: 291.41201 | C99: 292.23144 | D99: 322.78914 | E99: 361.34906 | F99: 356.60082 | G99: 426.43916 | H99: 442.89116 | I99: 505.43475 | J99: 480.23321 | K99: 455.4511 | L99: 537.47083 | M99: 637.59834 | N99: 491.91409 | O99: 524.23411 | P99: 564.66857 | Q99: 615.37406 | R99: 427.7737 | S99: 429.15266 | T99: 478.52409 | U99: 591.44932 | V99: 442.75859 | W99: 506.36399 | X99: 522.20292 | Y99: 642.31533 | Z99: 514.31016 | AA99: 535.91504 | AB99: 616.38689 | AC99: 673.84849 | AD99: 640.34907 | AE99: 544.60035 | AF99: 629.48307 | AG99: 689.97472 | AH99: 690.98617 | AI99: 684.42281 | AJ99: 926.22621 | AK99: 703.25927 | AL99: 767.94167 | AM99: 742.33208 | AN99: 1092.5302 | AO99: 1095.1055 | AP99: 696.86222 | AQ99: 740.76212 | AR99: 745.80166 | AS99: 784.63778 | AT99: 744.89887 | AU99: 757.07549 | AV99: 882.6526 | AW99: 1000.2763 | AX99: 856.50351 | AY99: 978.2639 | AZ99: 966.51576 | BA99: 1138.2989 | BB99: 899.61914 | BC99: 987.72245 | BD99: 1038.5474 | BE99: 1101.558 | BF99: 1000.3515 | BG99: 1039.7393 | BH99: 1123.7047 | BI99: 1173.3302 | BJ99: 1143.0409 | BK99: 1086.9613 | BL99: 1260.2883 | BM99: 1400.5219 | BN99: 1119.0432 | BO99: 1131.6947 | BP99: 1253.9665 | BQ99: 1170.5583 | BR99: 972.15151 | BS99: 933.11227 | BT99: 968.24576 | BU99: 1472.5855 | BV99: 914.69405 | BW99: 946.75617 | BX99: 1078.1906 | BY99: 1430.2642 | BZ99: 1082.9029 | CA99: 1071.6664 | CB99: 1174.1629 | CC99: 1522.9948 | CD99: 1117.8314 | CE99: 1557.2546 | CF99: 1342.6869 | CG99: 1451.094 | CH99: 1167.8227 | CI99: 910.06865 | CJ99: 1167.3722 | CK99: 1097.1464 | CL99: 1185.1453 | CM99: 1182.9748 | CN99: 1232.0858 | CO99: 1447.3131 | CP99: 1422.4174 | CQ99: 1248.9727 | CR99: 1737.8609 | CS99: 1666.646 | CT99: 1506.6016 | CU99: 1677.2189 | CV99: 1513.7762 | CW99: 1461.0902 | CX99: 1369.6078 | CY99: 1521.1382 | CZ99: 1557.1143 | DA99: 1542.7866 | DD99: -3.6369169
A100: Import_Biens | B100: 219.56489 | C100: 222.51369 | D100: 229.14487 | E100: 236.24425 | F100: 233.65992 | G100: 307.14193 | H100: 282.65216 | I100: 291.36216 | J100: 330.43911 | K100: 310.09655 | L100: 342.23186 | M100: 376.76726 | N100: 321.38879 | O100: 358.76278 | P100: 342.40892 | Q100: 318.44449 | R100: 307.22216 | S100: 312.17397 | T100: 321.39934 | U100: 381.53725 | V100: 307.29267 | W100: 374.91296 | X100: 345.63904 | Y100: 406.43339 | Z100: 386.09864 | AA100: 411.5034 | AB100: 449.27826 | AC100: 450.59837 | AD100: 510.47883 | AE100: 418.57915 | AF100: 460.2125 | AG100: 463.83633 | AH100: 546.69769 | AI100: 544.4107 | AJ100: 738.16317 | AK100: 452.01497 | AL100: 579.99084 | AM100: 559.95167 | AN100: 847.5584 | AO100: 767.83327 | AP100: 563.16389 | AQ100: 611.02631 | AR100: 571.5418 | AS100: 551.83442 | AT100: 603.05125 | AU100: 619.43187 | AV100: 697.77017 | AW100: 753.27895 | AX100: 751.95855 | AY100: 876.81746 | AZ100: 830.25598 | BA100: 956.26837 | BB100: 769.46133 | BC100: 861.42196 | BD100: 868.89028 | BE100: 874.86791 | BF100: 833.63163 | BG100: 877.96183 | BH100: 906.46759 | BI100: 883.29826 | BJ100: 970.56808 | BK100: 919.59464 | BL100: 1035.2198 | BM100: 1099.0301 | BN100: 964.93814 | BO100: 982.17744 | BP100: 1054.1057 | BQ100: 906.53793 | BR100: 887.68874 | BS100: 797.63754 | BT100: 871.77473 | BU100: 943.20199 | BV100: 737.19836 | BW100: 773.67556 | BX100: 847.03411 | BY100: 1101.89 | BZ100: 903.84765 | CA100: 859.25162 | CB100: 938.49887 | CC100: 1144.2769 | CD100: 882.35188 | CE100: 1366.706 | CF100: 1026.4998 | CG100: 1089.8663 | CH100: 945.49288 | CI100: 802.95599 | CJ100: 908.28011 | CK100: 849.92202 | CL100: 964.45415 | CM100: 998.34808 | CN100: 1057.0095 | CO100: 1169.5313 | CP100: 1148.2265 | CQ100: 1051.2446 | CR100: 1516.7489 | CS100: 1448.732 | CT100: 1234.0884 | CU100: 1428.7456 | CV100: 1280.5007 | CW100: 1287.3272 | CX100: 1139.2265 | CY100: 1301.4008 | CZ100: 1347.1965 | DA100: 1377.7273 | DD100: -4.7539121
A101: Import_Service | B101: 71.847124 | C101: 69.717746 | D101: 93.64427 | E101: 125.10482 | F101: 122.94091 | G101: 119.29723 | H101: 160.239 | I101: 214.07259 | J101: 149.79409 | K101: 145.35455 | L101: 195.23897 | M101: 260.83107 | N101: 170.5253 | O101: 165.47133 | P101: 222.25966 | Q101: 296.92958 | R101: 120.55155 | S101: 116.97868 | T101: 157.12475 | U101: 209.91208 | V101: 135.46592 | W101: 131.45103 | X101: 176.56388 | Y101: 235.88194 | Z101: 128.21152 | AA101: 124.41164 | AB101: 167.10863 | AC101: 223.25012 | AD101: 129.87024 | AE101: 126.02119 | AF101: 169.27057 | AG101: 226.13839 | AH101: 144.28848 | AI101: 140.01211 | AJ101: 188.06304 | AK101: 251.2443 | AL101: 187.95083 | AM101: 182.38041 | AN101: 244.97184 | AO101: 327.27227 | AP101: 133.69832 | AQ101: 129.73582 | AR101: 174.25986 | AS101: 232.80336 | AT101: 141.84763 | AU101: 137.64362 | AV101: 184.88243 | AW101: 246.99738 | AX101: 104.54496 | AY101: 101.44645 | AZ101: 136.25978 | BA101: 182.03055 | BB101: 130.15782 | BC101: 126.30049 | BD101: 169.65716 | BE101: 226.69008 | BF101: 166.7199 | BG101: 161.77742 | BH101: 217.23707 | BI101: 290.0319 | BJ101: 172.47281 | BK101: 167.36669 | BL101: 225.06845 | BM101: 301.49183 | BN101: 154.1051 | BO101: 149.51728 | BP101: 199.86085 | BQ101: 264.02033 | BR101: 84.462765 | BS101: 135.47473 | BT101: 96.471033 | BU101: 529.38347 | BV101: 177.49569 | BW101: 173.08061 | BX101: 231.15646 | BY101: 328.37424 | BZ101: 179.05524 | CA101: 212.41481 | CB101: 235.66402 | CC101: 378.71793 | CD101: 235.47957 | CE101: 190.54867 | CF101: 316.18708 | CG101: 361.22768 | CH101: 222.32982 | CI101: 107.11265 | CJ101: 259.09212 | CK101: 247.2244 | CL101: 220.69117 | CM101: 184.6267 | CN101: 175.0763 | CO101: 277.78183 | CP101: 274.19094 | CQ101: 197.72803 | CR101: 221.11207 | CS101: 217.91396 | CT101: 272.51319 | CU101: 248.47332 | CV101: 233.2755 | CW101: 173.763 | CX101: 230.38133 | CY101: 219.73741 | CZ101: 209.91775 | DA101: 165.05926 | DD101: 3.9987046
A102: PIB | B102: 1755.4508 | C102: 1862.9735 | D102: 1757.5732 | E102: 1742.4605 | F102: 1842.0067 | G102: 1932.4249 | H102: 1861.0775 | I102: 1868.9598 | J102: 1951.5595 | K102: 2048.7043 | L102: 2007.9337 | M102: 2014.1098 | N102: 2084.7973 | O102: 2143.4463 | P102: 2172.2787 | Q102: 2213.4892 | R102: 2200.7438 | S102: 2306.8254 | T102: 2350.6522 | U102: 2402.9232 | V102: 2412.2611 | W102: 2519.2302 | X102: 2478.3764 | Y102: 2517.911 | Z102: 2535.126 | AA102: 2560.6033 | AB102: 2608.7487 | AC102: 2582.2547 | AD102: 2620.2961 | AE102: 2693.9966 | AF102: 2722.288 | AG102: 2887.6071 | AH102: 2760.4111 | AI102: 2860.2943 | AJ102: 2891.3208 | AK102: 2940.8412 | AL102: 2978.8177 | AM102: 3090.4589 | AN102: 3064.744 | AO102: 3226.9339 | AP102: 3212.5321 | AQ102: 3283.6004 | AR102: 3285.9377 | AS102: 3354.622 | AT102: 3336.7636 | AU102: 3326.3806 | AV102: 3390.6102 | AW102: 3556.7997 | AX102: 3518.4687 | AY102: 3546.2208 | AZ102: 3657.1996 | BA102: 3712.8854 | BB102: 3854.9055 | BC102: 3860.1264 | BD102: 3867.4732 | BE102: 3813.3531 | BF102: 4062.4702 | BG102: 4086.3501 | BH102: 4170.4997 | BI102: 4339.2333 | BJ102: 4325.9731 | BK102: 4366.9881 | BL102: 4497.5541 | BM102: 4775.6077 | BN102: 4590.3825 | BO102: 4748.9242 | BP102: 4778.4968 | BQ102: 4925.2631 | BR102: 4771.2747 | BS102: 5010.6444 | BT102: 4995.1982 | BU102: 5261.4487 | BV102: 5013.4244 | BW102: 5286.7873 | BX102: 5255.8917 | BY102: 5404.7616 | BZ102: 5292.4533 | CA102: 5617.9983 | CB102: 5496.5148 | CC102: 5796.3627 | CD102: 5481.0595 | CE102: 5875.8398 | CF102: 5776.2245 | CG102: 6110.5382 | CH102: 5687.1421 | CI102: 5818.852 | CJ102: 5949.7244 | CK102: 6012.7885 | CL102: 6081.1813 | CM102: 6260.6572 | CN102: 6200.3436 | CO102: 6418.3139 | CP102: 6712.8579 | CQ102: 6999.6447 | CR102: 6818.3222 | CS102: 7131.1952 | CT102: 7153.8843 | CU102: 7520.008 | CV102: 7416.5673 | CW102: 7800.9435 | CX102: 7809.5599 | CY102: 8146.6738 | CZ102: 8082.5999 | DA102: 8935.7141 | DD102: 6.6264481
B105: =B83-B102 -> 0 | C105: =C83-C102 -> 0 | D105: =D83-D102 -> 0 | E105: =E83-E102 -> 0 | F105: =F83-F102 -> 0 | G105: =G83-G102 -> 0 | H105: =H83-H102 -> 0 | I105: =I83-I102 -> 0 | ... DA105: =DA83-DA102 -> 0

Sheet PIB_Annuel (2005)
A2: Les Comptes Nationaux du Cameroun, selon le SCN 2008
A4: 1- Optique production
A6: Tableau 1:
A7: PIB courant, optique production
A8: Libellé | C8: 1993 | D8: 1994 | E8: 1995 | F8: 1996 | G8: 1997 | H8: 1998 | I8: 1999 | J8: 2000 | K8: 2001 | L8: 2002 | M8: 2003 | N8: 2004 | O8: 2005 | P8: 2006 | Q8: 2007 | R8: 2008 | S8: 2009 | T8: 2010 | U8: 2011 | V8: 2012 | W8: 2013 | X8: 2014 | Y8: 2015 | Z8: 2016 | AA8: 2017 | AB8: 2018 | AC8: 2019
A9: 1.Production | C9: 6349.2133 | D9: 7302.3952 | E9: 8357.2121 | F9: 8978.0312 | G9: 9828.5522 | H9: 10461.82 | I9: 11361.118 | J9: 11751.468 | K9: 12897.193 | L9: 13387.762 | M9: 14336.57 | N9: 15244.899 | O9: 16007.268 | P9: 17329.469 | Q9: 18315.901 | R9: 20329.607 | S9: 20603.617 | T9: 21916.543 | U9: 23543.673 | V9: 25005.933 | W9: 26283.722 | X9: 28207.099 | Y9: 29313.617 | Z9: 30283.611 | AA9: 30908.44 | AB9: 32610.465 | AC9: 34342.188
A10: 2.Consommation intermédiaire | C10: 2475.1446 | D10: 3017.9788 | E10: 3757.5802 | F10: 4138.5904 | G10: 4476.0783 | H10: 4635.792 | I10: 5288.6576 | J10: 5138.0688 | K10: 5927.0963 | L10: 5964.8273 | M10: 6555.7492 | N10: 6708.0502 | O10: 7220.66 | P10: 7976.137 | Q10: 8509.406 | R10: 9265.895 | S10: 9144.637 | T10: 9825.942 | U10: 10566.923 | V10: 11064.793 | W10: 11261.592 | X10: 12105.375 | Y10: 12485.484 | Z10: 12489.5 | AA10: 12245.881 | AB10: 12873.149 | AC10: 13306.479
A11: 3.Valeur Ajoutée(1-2) | C11: 3874.0688 | D11: 4284.4163 | E11: 4599.6319 | F11: 4839.4407 | G11: 5352.474 | H11: 5826.0284 | I11: 6072.4604 | J11: 6613.3995 | K11: 6970.0964 | L11: 7422.9352 | M11: 7780.8207 | N11: 8536.8485 | O11: 8786.608 | P11: 9353.332 | Q11: 9806.495 | R11: 11063.712 | S11: 11458.98 | T11: 12090.601 | U11: 12976.75 | V11: 13941.14 | W11: 15022.13 | X11: 16101.724 | Y11: 16828.133 | Z11: 17794.111 | AA11: 18662.559 | AB11: 19737.316 | AC11: 21035.709
A12: 4.Impôts sur les produits | C12: 238.63916 | D12: 319.63693 | E12: 402.0183 | F12: 436.33327 | G12: 509.57544 | H12: 563.86922 | I12: 517.07027 | J12: 566.12516 | K12: 632.48664 | L12: 647.7292 | M12: 674.97191 | N12: 671.64855 | O12: 678.324 | P12: 767.753 | Q12: 912.434 | R12: 762.728 | S12: 826.328 | T12: 857.831 | U12: 866.389 | V12: 917.464 | W12: 959.15 | X12: 1174.594 | Y12: 1457.249 | Z12: 1550.727 | AA12: 1665.804 | AB12: 1755.218 | AC12: 1819.129
A13: PIB(3+4) | C13: 4112.7079 | D13: 4604.0533 | E13: 5001.6502 | F13: 5275.774 | G13: 5862.0494 | H13: 6389.8977 | I13: 6589.5306 | J13: 7179.5247 | K13: 7602.583 | L13: 8070.6644 | M13: 8455.7926 | N13: 9208.497 | O13: 9464.932 | P13: 10121.085 | Q13: 10718.929 | R13: 11826.44 | S13: 12285.308 | T13: 12948.432 | U13: 13843.139 | V13: 14858.604 | W13: 15981.28 | X13: 17276.318 | Y13: 18285.382 | Z13: 19344.838 | AA13: 20328.363 | AB13: 21492.534 | AC13: 22854.838
A15: Tableau 2:
A16: PIB en volume, optique production (base 100 = 2005)
A17: Libellé | C17: 1993 | D17: 1994 | E17: 1995 | F17: 1996 | G17: 1997 | H17: 1998 | I17: 1999 | J17: 2000 | K17: 2001 | L17: 2002 | M17: 2003 | N17: 2004 | O17: 2005 | P17: 2006 | Q17: 2007 | R17: 2008 | S17: 2009 | T17: 2010 | U17: 2011 | V17: 2012 | W17: 2013 | X17: 2014 | Y17: 2015 | Z17: 2016 | AA17: 2017 | AB17: 2018 | AC17: 2019
A18: 1.Production | C18: 9257.325 | D18: 9632.7951 | E18: 10267.346 | F18: 10513.784 | G18: 11413.452 | H18: 11973.768 | I18: 12785.342 | J18: 13084.782 | K18: 14206.774 | L18: 14237.549 | M18: 14883.112 | N18: 15668.24 | O18: 16007.268 | P18: 16617.44 | Q18: 17346.709 | R18: 18068.145 | S18: 18349.745 | T18: 19036.443 | U18: 19568.647 | V18: 20252.113 | W18: 21113.013 | X18: 22408.828 | Y18: 23423.908 | Z18: 24320.593 | AA18: 24618.909 | AB18: 25405.235 | AC18: 26249.635
A19: 2.Consommation intermédiaire | C19: 3868.876 | D19: 4179.2227 | E19: 4698.769 | F19: 4759.508 | G19: 5488.4622 | H19: 5755.3258 | I19: 6107.738 | J19: 6210.9673 | K19: 6925.6981 | L19: 6598.7903 | M19: 6889.1063 | N19: 7101.8884 | O19: 7220.66 | P19: 7563.035 | Q19: 7858.083 | R19: 8069.837 | S19: 8150.3436 | T19: 8479.4957 | U19: 8611.91 | V19: 8782.646 | W19: 9017.186 | X19: 9686.234 | Y19: 10011.596 | Z19: 10299.928 | AA19: 10138.404 | AB19: 10325.72 | AC19: 10640.133
A20: 3.Valeur Ajoutée(1-2) | C20: 5388.449 | D20: 5453.5724 | E20: 5568.5771 | F20: 5754.2759 | G20: 5924.9901 | H20: 6218.4419 | I20: 6677.6039 | J20: 6873.8149 | K20: 7281.0758 | L20: 7638.7591 | M20: 7994.0054 | N20: 8566.352 | O20: 8786.608 | P20: 9054.405 | Q20: 9488.6263 | R20: 9998.308 | S20: 10199.401 | T20: 10556.947 | U20: 10956.737 | V20: 11469.467 | W20: 12095.827 | X20: 12722.594 | Y20: 13412.312 | Z20: 14020.664 | AA20: 14480.505 | AB20: 15079.515 | AC20: 15609.502
A21: 4.Impôts sur les produits | C21: 443.0978 | D21: 501.8327 | E21: 593.46818 | F21: 676.50152 | G21: 842.20189 | H21: 853.42873 | I21: 697.7927 | J21: 763.65711 | K21: 690.00739 | L21: 670.07514 | M21: 694.30954 | N21: 711.11375 | O21: 678.324 | P21: 737.793 | Q21: 783.605 | R21: 632.301 | S21: 664.939 | T21: 679.226 | U21: 743.409 | V21: 762.248 | W21: 796.922 | X21: 928.772 | Y21: 1010.556 | Z21: 1072.648 | AA21: 1148.482 | AB21: 1184.398 | AC21: 1259.544
A22: PIB | C22: 5831.5468 | D22: 5955.4051 | E22: 6162.0453 | F22: 6430.7774 | G22: 6767.192 | H22: 7071.8707 | I22: 7375.3966 | J22: 7637.472 | K22: 7971.0832 | L22: 8308.8343 | M22: 8688.3149 | N22: 9277.4657 | O22: 9464.932 | P22: 9792.198 | Q22: 10272.231 | R22: 10630.609 | S22: 10864.34 | T22: 11236.173 | U22: 11700.146 | V22: 12231.715 | W22: 12892.749 | X22: 13651.366 | Y22: 14422.868 | Z22: 15093.312 | AA22: 15628.987 | AB22: 16263.913 | AC22: 16869.046
A25: Tableau 3:
A26: Ventilation du PIB courant par secteurs d’activités
A27: Libellé | C27: 1993 | D27: 1994 | E27: 1995 | F27: 1996 | G27: 1997 | H27: 1998 | I27: 1999 | J27: 2000 | K27: 2001 | L27: 2002 | M27: 2003 | N27: 2004 | O27: 2005 | P27: 2006 | Q27: 2007 | R27: 2008 | S27: 2009 | T27: 2010 | U27: 2011 | V27: 2012 | W27: 2013 | X27: 2014 | Y27: 2015 | Z27: 2016 | AA27: 2017 | AB27: 2018 | AC27: 2019
A28: Secteur primaire | C28: 623.58779 | D28: 777.84115 | E28: 893.60468 | F28: 933.20477 | G28: 1065.726 | H28: 1124.146 | I28: 1207.4335 | J28: 1201.5986 | K28: 1325.0794 | L28: 1327.7599 | M28: 1345.1147 | N28: 1431.7712 | O28: 1333 | P28: 1340.056 | Q28: 1412.641 | R28: 1548.758 | S28: 1677.812 | T28: 1821.541 | U28: 1866.007 | V28: 2038.827 | W28: 2221.222 | X28: 2457.763 | Y28: 2701.203 | Z28: 2813.327 | AA28: 2921.636 | AB28: 3099.891 | AC28: 3315.703
A29: Agriculture | C29: 448.3201 | D29: 548.01507 | E29: 642.28739 | F29: 682.42884 | G29: 776.149 | H29: 799.74194 | I29: 873.29761 | J29: 865.20862 | K29: 970.02035 | L29: 1016.6031 | M29: 985.26385 | N29: 1010.1379 | O29: 957.902 | P29: 942.177 | Q29: 964.283 | R29: 1058.643 | S29: 1187.555 | T29: 1293.177 | U29: 1308.96 | V29: 1428.301 | W29: 1571.547 | X29: 1720.677 | Y29: 1889.912 | Z29: 1985.497 | AA29: 2014.105 | AB29: 2136.735 | AC29: 2326.349
A30: Elevage et chasse | C30: 66.331894 | D30: 76.94615 | E30: 85.268885 | F30: 88.353607 | G30: 96.660019 | H30: 105.10569 | I30: 112.02354 | J30: 115.02468 | K30: 120.7683 | L30: 132.94077 | M30: 141.69535 | N30: 136.93874 | O30: 124.971 | P30: 132.096 | Q30: 140.751 | R30: 164.68 | S30: 175.294 | T30: 183.021 | U30: 192.477 | V30: 223.093 | W30: 232.16 | X30: 243.851 | Y30: 261.095 | Z30: 272.758 | AA30: 290.032 | AB30: 321.173 | AC30: 319.605
A31: Sylviculture et exploitation forestière | C31: 90.017073 | D31: 131.77555 | E31: 144.88576 | F31: 142.72295 | G31: 171.3492 | H31: 195.16664 | I31: 195.40482 | J31: 191.88788 | K31: 203.10806 | L31: 142.66298 | M31: 180.51374 | N31: 248.56438 | O31: 216.676 | P31: 225.688 | Q31: 267.401 | R31: 282.98 | S31: 270.579 | T31: 299.119 | U31: 314.455 | V31: 333.577 | W31: 361.167 | X31: 433.965 | Y31: 485.964 | Z31: 488.095 | AA31: 543.316 | AB31: 559.294 | AC31: 595.793
A32: Pêche et pisciculture | C32: 18.918717 | D32: 21.104376 | E32: 21.162648 | F32: 19.699362 | G32: 21.567744 | H32: 24.131717 | I32: 26.707505 | J32: 29.477376 | K32: 31.182653 | L32: 35.553033 | M32: 37.641765 | N32: 36.130202 | O32: 33.451 | P32: 40.095 | Q32: 40.206 | R32: 42.455 | S32: 44.384 | T32: 46.224 | U32: 50.115 | V32: 53.856 | W32: 56.348 | X32: 59.27 | Y32: 64.232 | Z32: 66.977 | AA32: 74.183 | AB32: 82.689 | AC32: 73.956
